Workbook

Sheet README
A1: Symbiotec DCV: Solu-Medrol vs Solu-Cortef calculations
A2: Companion workbook to the report 'Pfizer-only Cortef vials anchor Symbiotec's DCV case'. Data as of 21 October 2026.
A4: Colour legend
A5: Input | B5: Blue text: hard-coded input copied from a cited source (source ID in the row or column note)
A6: Formula | B6: Black text: formula calculated in this workbook
A7: Link | B7: Green text: formula linking to another sheet
A8: Assumption | B8: Yellow fill: analyst assumption to review or change
A10: Sheets
A11: Sheet | B11: What it calculates | C11: Report section
A12: Report_Map | B12: Every number quoted in the report, linked live to the cell that calculates it | C12: All
A13: Assumptions | B13: ASP divisor, billing units per vial, code-change quarter, FX, review clock, key dates | C13: All
A14: CMS_PL | B14: Input: Part B payment limit per billing unit by HCPCS code, Q1 2016 to Q4 2026 | C14: ASP
A15: ASP_per_vial | B15: Implied ASP per vial = payment limit x billing units / 1.06; quarterly and annual averages | C15: ASP
A16: ASP_growth | B16: Peaks, 1y change, 3y and 5y CAGRs, quarter-on-quarter moves | C16: ASP
A17: Pfizer_WAC | B17: Pfizer list price per vial by presentation and date; Jul 2024 to Jul 2026 changes; 2025 Solu-Medrol cuts; ASP vs WAC | C17: Price points
A18: NADAC | B18: Retail acquisition cost; generic as % of brand | C18: Price points
A19: SDUD_NDC_data | B19: Input: Medicaid prescriptions, units and dollars by NDC and year (aggregated from SDUD national rows) | C19: Share proxies
A20: Medicaid_SDUD | B20: Prescription shares by labeler and strength, HSS large-vial slice, 250 mg billing-unit drag | C20: Share proxies
A21: CMS_Spending | B21: Part D and Medicaid Spending by Drug 2024; Part B volume and spend per unit; HSS vs MPSS spend ratios | C21: Share proxies; market size
A22: Market_Size | B22: Market-size figures, ICICI estimates in US$, Pfizer Medrol revenue, capacity cross-check | C22: Market size; implications
... A24: Sources | B24: Every source used in this workbook, with links | C24: All
A26: Method notes
A27: - Medicare Part B pays ASP + 6% for these multi-source drugs, so implied ASP = CMS payment limit / 1.06 (divisor in Assumptions).
A28: - CMS replaced J2920/J2930 (MPSS) with J2919 (per 5 mg) and J1020/J1030/J1040 (MPA) with J1010 (per 1 mg) from Q2 2024. Per-vial series for MPSS and MPA switch codes at that quarter, so do not splice growth across it.
A29: - Medicaid SDUD is outpatient and pre-rebate. Use prescription share for direction, not as true market share. 2026 SDUD covers Q1 only.
A30: - SDUD_NDC_data was aggregated in Python from the national rows of the SDUD annual files for every NDC RxNorm links to these molecules. All shares on Medicaid_SDUD are recomputed here with SUMIFS on that table.
A31: - Payment limits, list prices, NADAC and CMS spending figures are copied from the cited files without adjustment.

Sheet Report_Map
A1: Report figures linked to their calculations
A2: Each value is a live link. 'Report value' is what the Word report states; 'Check' compares to the rounding shown in the report.
A4: Report section | B4: Figure | C4: Workbook value | D4: Report value | E4: Check | F4: Calculated on
A5: Summary / ASP | B5: MPSS 125 mg implied ASP per vial, old-code peak (Q3 2018) | C5: =ASP_growth!$S$7 -> 6.5707547 | D5: 6.57 | E5: =IF(ABS(C5-D5)<=MAX(0.0051,ABS(D5)*0.02),"OK","Check") -> OK | F5: ASP_growth
A6: Summary / ASP | B6: MPSS 125 mg implied ASP per vial, new-code (J2919) peak (Q4 2024) | C6: =ASP_growth!$U$7 -> 7.1698113 | D6: 7.17 | E6: =IF(ABS(C6-D6)<=MAX(0.0051,ABS(D6)*0.02),"OK","Check") -> OK | F6: ASP_growth
A7: Summary / ASP | B7: MPSS 125 mg implied ASP per vial, Q4 2026 | C7: =INDEX(ASP_per_vial!$E$6:$P$49,MATCH("2026-Q4",ASP_per_vial!$A$6:$A$49,0),MATCH("MPSS 125 mg",ASP_per_vial!$E$5:$P$5,0)) -> 6.0141509 | D7: 6.01 | E7: =IF(ABS(C7-D7)<=MAX(0.0051,ABS(D7)*0.02),"OK","Check") -> OK | F7: ASP_per_vial
A8: Summary / ASP | B8: HSS 100 mg implied ASP per vial, Q4 2026 | C8: =INDEX(ASP_per_vial!$E$6:$P$49,MATCH("2026-Q4",ASP_per_vial!$A$6:$A$49,0),MATCH("HSS 100 mg",ASP_per_vial!$E$5:$P$5,0)) -> 21.838679 | D8: 21.84 | E8: =IF(ABS(C8-D8)<=MAX(0.0051,ABS(D8)*0.02),"OK","Check") -> OK | F8: ASP_per_vial
A9: Summary / ASP | B9: HSS 250 mg implied ASP per vial, Q4 2026 (2.5 units) | C9: =INDEX(ASP_per_vial!$E$6:$P$49,MATCH("2026-Q4",ASP_per_vial!$A$6:$A$49,0),MATCH("HSS 250 mg (2.5 units)",ASP_per_vial!$E$5:$P$5,0)) -> 54.596698 | D9: 54.6 | E9: =IF(ABS(C9-D9)<=MAX(0.0051,ABS(D9)*0.02),"OK","Check") -> OK | F9: ASP_per_vial
A10: Summary / ASP | B10: HSS 250 mg implied ASP per vial, Q4 2026 (3 units) | C10: =INDEX(ASP_per_vial!$E$6:$P$49,MATCH("2026-Q4",ASP_per_vial!$A$6:$A$49,0),MATCH("HSS 250 mg (3 units)",ASP_per_vial!$E$5:$P$5,0)) -> 65.516038 | D10: 65.52 | E10: =IF(ABS(C10-D10)<=MAX(0.0051,ABS(D10)*0.02),"OK","Check") -> OK | F10: ASP_per_vial
A11: Summary / ASP | B11: HSS 500 mg implied ASP per vial, Q4 2026 | C11: =INDEX(ASP_per_vial!$E$6:$P$49,MATCH("2026-Q4",ASP_per_vial!$A$6:$A$49,0),MATCH("HSS 500 mg",ASP_per_vial!$E$5:$P$5,0)) -> 109.1934 | D11: 109.19 | E11: =IF(ABS(C11-D11)<=MAX(0.0051,ABS(D11)*0.02),"OK","Check") -> OK | F11: ASP_per_vial
A12: Summary / ASP | B12: HSS 1 g implied ASP per vial, Q4 2026 | C12: =INDEX(ASP_per_vial!$E$6:$P$49,MATCH("2026-Q4",ASP_per_vial!$A$6:$A$49,0),MATCH("HSS 1 g",ASP_per_vial!$E$5:$P$5,0)) -> 218.38679 | D12: 218.39 | E12: =IF(ABS(C12-D12)<=MAX(0.0051,ABS(D12)*0.02),"OK","Check") -> OK | F12: ASP_per_vial
A13: Summary / ASP | B13: J1720 payment-limit CAGR, Q1 2016 to Q4 2026 (~11%) | C13: =ASP_growth!$B$77 -> 0.11050728 | D13: 0.11 | E13: =IF(ABS(C13-D13)<=MAX(0.006,ABS(D13)*0.02),"OK","Check") -> OK | F13: ASP_growth
A14: ASP | B14: HSS 100 mg 1y change | C14: =ASP_growth!$L$11 -> 0.086195571 | D14: 0.086 | E14: =IF(ABS(C14-D14)<=MAX(0.006,ABS(D14)*0.02),"OK","Check") -> OK | F14: ASP_growth
A15: ASP | B15: HSS 100 mg 5y CAGR | C15: =ASP_growth!$N$11 -> 0.093426438 | D15: 0.093 | E15: =IF(ABS(C15-D15)<=MAX(0.006,ABS(D15)*0.02),"OK","Check") -> OK | F15: ASP_growth
A16: ASP | B16: MPSS 125 mg 1y change (off Q4 2025 trough) | C16: =ASP_growth!$L$7 -> 0.21428571 | D16: 0.214 | E16: =IF(ABS(C16-D16)<=MAX(0.006,ABS(D16)*0.02),"OK","Check") -> OK | F16: ASP_growth
A17: ASP | B17: MPSS 125 mg 5y CAGR (crosses recode) | C17: =ASP_growth!$N$7 -> 0.027550096 | D17: 0.027 | E17: =IF(ABS(C17-D17)<=MAX(0.006,ABS(D17)*0.02),"OK","Check") -> OK | F17: ASP_growth
A18: ASP | B18: MPSS 40 mg ASP, Q1 2024 (last old code) | C18: =INDEX(ASP_per_vial!$E$6:$P$49,MATCH("2024-Q1",ASP_per_vial!$A$6:$A$49,0),MATCH("MPSS 40 mg",ASP_per_vial!$E$5:$P$5,0)) -> 3.9509434 | D18: 3.95 | E18: =IF(ABS(C18-D18)<=MAX(0.0051,ABS(D18)*0.02),"OK","Check") -> OK | F18: ASP_per_vial
A19: ASP | B19: MPSS 40 mg ASP, Q2 2024 (first new code) | C19: =INDEX(ASP_per_vial!$E$6:$P$49,MATCH("2024-Q2",ASP_per_vial!$A$6:$A$49,0),MATCH("MPSS 40 mg",ASP_per_vial!$E$5:$P$5,0)) -> 2.0603774 | D19: 2.06 | E19: =IF(ABS(C19-D19)<=MAX(0.0051,ABS(D19)*0.02),"OK","Check") -> OK | F19: ASP_per_vial
A20: ASP | B20: MPSS 125 mg change Q1 2016 to Q3 2018 | C20: =ASP_growth!$P$7 -> 0.69671133 | D20: 0.7 | E20: =IF(ABS(C20-D20)<=MAX(0.006,ABS(D20)*0.02),"OK","Check") -> OK | F20: ASP_growth
A21: ASP | B21: MPSS 40 mg change Q1 2016 to Q3 2018 | C21: =ASP_growth!$P$6 -> 0.65804003 | D21: 0.66 | E21: =IF(ABS(C21-D21)<=MAX(0.006,ABS(D21)*0.02),"OK","Check") -> OK | F21: ASP_growth
A22: ASP | B22: J2919 change Q2 2024 to Q4 2026 | C22: =ASP_growth!$Q$7 -> -0.065934066 | D22: -0.066 | E22: =IF(ABS(C22-D22)<=MAX(0.006,ABS(D22)*0.02),"OK","Check") -> OK | F22: ASP_growth
A23: ASP | B23: J2919 change in Q4 2025 | C23: =ASP_growth!$B$73 -> -0.18918919 | D23: -0.189 | E23: =IF(ABS(C23-D23)<=MAX(0.006,ABS(D23)*0.02),"OK","Check") -> OK | F23: ASP_growth
A24: ASP | B24: J2919 change in Q1 2026 | C24: =ASP_growth!$B$74 -> 0.25714286 | D24: 0.257 | E24: =IF(ABS(C24-D24)<=MAX(0.006,ABS(D24)*0.02),"OK","Check") -> OK | F24: ASP_growth
A25: ASP | B25: J2919 implied ASP per 5 mg, 2025 average | C25: =ASP_growth!$B$75 -> 0.23301887 | D25: 0.233 | E25: =IF(ABS(C25-D25)<=MAX(0.0011,ABS(D25)*0.02),"OK","Check") -> OK | F25: ASP_growth
A26: ASP | B26: J2919 implied ASP per 5 mg, 2026 average | C26: =ASP_growth!$B$76 -> 0.23207547 | D26: 0.232 | E26: =IF(ABS(C26-D26)<=MAX(0.0011,ABS(D26)*0.02),"OK","Check") -> OK | F26: ASP_growth
A27: ASP | B27: J1720 change in Q3 2017 | C27: =ASP_growth!$B$71 -> 0.20123976 | D27: 0.201 | E27: =IF(ABS(C27-D27)<=MAX(0.006,ABS(D27)*0.02),"OK","Check") -> OK | F27: ASP_growth
A28: ASP | B28: J1720 change in Q3 2022 | C28: =ASP_growth!$B$72 -> 0.19202333 | D28: 0.192 | E28: =IF(ABS(C28-D28)<=MAX(0.006,ABS(D28)*0.02),"OK","Check") -> OK | F28: ASP_growth
A29: ASP | B29: J1720 largest quarterly fall (report: never 10% or more) | C29: =ASP_growth!$B$69 -> -0.022968821 | F29: ASP_growth
A30: ASP | B30: MPA 40 mg/mL change Q2 2024 to Q4 2026 (J1010) | C30: =ASP_growth!$Q$16 -> -0.082089552 | D30: -0.082 | E30: =IF(ABS(C30-D30)<=MAX(0.006,ABS(D30)*0.02),"OK","Check") -> OK | F30: ASP_growth
A31: ASP | B31: MPA 40 mg/mL implied ASP per vial, Q4 2026 | C31: =INDEX(ASP_per_vial!$E$6:$P$49,MATCH("2026-Q4",ASP_per_vial!$A$6:$A$49,0),MATCH("MPA 40 mg/mL 1 mL",ASP_per_vial!$E$5:$P$5,0)) -> 4.6415094 | D31: 4.64 | E31: =IF(ABS(C31-D31)<=MAX(0.0051,ABS(D31)*0.02),"OK","Check") -> OK | F31: ASP_per_vial
A32: ASP | B32: MPA 80 mg/mL implied ASP per vial, Q4 2026 | C32: =INDEX(ASP_per_vial!$E$6:$P$49,MATCH("2026-Q4",ASP_per_vial!$A$6:$A$49,0),MATCH("MPA 80 mg/mL 1 mL",ASP_per_vial!$E$5:$P$5,0)) -> 9.2830189 | D32: 9.28 | E32: =IF(ABS(C32-D32)<=MAX(0.0051,ABS(D32)*0.02),"OK","Check") -> OK | F32: ASP_per_vial
A33: Price points | B33: Solu-Cortef WAC change Jul-24 to Jul-26: low end (single vials) | C33: =Pfizer_WAC!$K$29 -> 0.17973856 | D33: 0.18 | E33: =IF(ABS(C33-D33)<=MAX(0.006,ABS(D33)*0.02),"OK","Check") -> OK | F33: Pfizer_WAC
A34: Price points | B34: Solu-Cortef WAC change Jul-24 to Jul-26: high end (single vials) | C34: =Pfizer_WAC!$K$30 -> 0.29187689 | D34: 0.292 | E34: =IF(ABS(C34-D34)<=MAX(0.006,ABS(D34)*0.02),"OK","Check") -> OK | F34: Pfizer_WAC
A35: Price points | B35: Solu-Cortef WAC change Jul-24 to Jul-26: 25-pack low end | C35: =Pfizer_WAC!$K$31 -> 0.15755483 | F35: Pfizer_WAC
A36: Price points | B36: Solu-Medrol largest mid-2025 WAC cut (1 g multi-dose vial) | C36: =Pfizer_WAC!$K$32 -> -0.42360164 | D36: -0.424 | E36: =IF(ABS(C36-D36)<=MAX(0.006,ABS(D36)*0.02),"OK","Check") -> OK | F36: Pfizer_WAC
A37: Price points | B37: Solu-Medrol smallest mid-2025 WAC cut | C37: =Pfizer_WAC!$K$33 -> -0.16998516 | D37: -0.17 | E37: =IF(ABS(C37-D37)<=MAX(0.006,ABS(D37)*0.02),"OK","Check") -> OK | F37: Pfizer_WAC
A38: Price points | B38: Solu-Medrol lines cut in mid-2025 | C38: =Pfizer_WAC!$K$34 -> 5 | D38: 5 | E38: =IF(ABS(C38-D38)<=MAX(0.0011,ABS(D38)*0.02),"OK","Check") -> OK | F38: Pfizer_WAC
A39: Price points | B39: Solu-Medrol 40 mg Act-O-Vial line A cut | C39: =Pfizer_WAC!$K$35 -> -0.24337121 | D39: -0.244 | E39: =IF(ABS(C39-D39)<=MAX(0.006,ABS(D39)*0.02),"OK","Check") -> OK | F39: Pfizer_WAC
A40: Price points | B40: Solu-Medrol 40 mg Act-O-Vial line C cut | C40: =Pfizer_WAC!$K$36 -> -0.16998516 | D40: -0.17 | E40: =IF(ABS(C40-D40)<=MAX(0.006,ABS(D40)*0.02),"OK","Check") -> OK | F40: Pfizer_WAC
A41: Price points | B41: Solu-Medrol 125 mg Act-O-Vial line A cut | C41: =Pfizer_WAC!$K$37 -> -0.2523337 | D41: -0.252 | E41: =IF(ABS(C41-D41)<=MAX(0.006,ABS(D41)*0.02),"OK","Check") -> OK | F41: Pfizer_WAC
A42: Price points | B42: Solu-Medrol 125 mg Act-O-Vial line C cut | C42: =Pfizer_WAC!$K$38 -> -0.17981109 | D42: -0.18 | E42: =IF(ABS(C42-D42)<=MAX(0.006,ABS(D42)*0.02),"OK","Check") -> OK | F42: Pfizer_WAC
A43: Price points | B43: J1720 ASP as % of 100 mg Act-O-Vial WAC | C43: =Pfizer_WAC!$K$40 -> 0.86421366 | D43: 0.86 | E43: =IF(ABS(C43-D43)<=MAX(0.006,ABS(D43)*0.02),"OK","Check") -> OK | F43: Pfizer_WAC
A44: Price points | B44: J1720 ASP as % of 100 mg plain-vial WAC | C44: =Pfizer_WAC!$K$41 -> 1.0859612 | D44: 1.09 | E44: =IF(ABS(C44-D44)<=MAX(0.006,ABS(D44)*0.02),"OK","Check") -> OK | F44: Pfizer_WAC
A45: Price points | B45: Implied ASP / WAC, HSS 1 g | C45: =Pfizer_WAC!$K$44 -> 1.0862312 | D45: 1.09 | E45: =IF(ABS(C45-D45)<=MAX(0.006,ABS(D45)*0.02),"OK","Check") -> OK | F45: Pfizer_WAC
A46: Price points | B46: HSS 1 g WAC / 100 mg plain-vial WAC | C46: =Pfizer_WAC!$K$46 -> 9.9975137 | D46: 10 | E46: =IF(ABS(C46-D46)<=MAX(0.051,ABS(D46)*0.02),"OK","Check") -> OK | F46: Pfizer_WAC
A47: Price points | B47: Generic MPSS 125 mg NADAC as % of brand | C47: =NADAC!$E$37 -> 0.32523707 | D47: 0.33 | E47: =IF(ABS(C47-D47)<=MAX(0.006,ABS(D47)*0.02),"OK","Check") -> OK | F47: NADAC
A48: Price points | B48: Generic HSS 100 mg NADAC as % of brand Act-O-Vial | C48: =NADAC!$E$38 -> 0.56643746 | D48: 0.57 | E48: =IF(ABS(C48-D48)<=MAX(0.006,ABS(D48)*0.02),"OK","Check") -> OK | F48: NADAC
A49: Price points | B49: Generic HSS 100 mg NADAC as % of brand plain vial | C49: =NADAC!$E$39 -> 0.56203528 | D49: 0.56 | E49: =IF(ABS(C49-D49)<=MAX(0.006,ABS(D49)*0.02),"OK","Check") -> OK | F49: NADAC
A50: Share proxies | B50: Pfizer share of Medicaid MPSS Rx, 2018 | C50: =Medicaid_SDUD!$B$18 -> 0.90580614 | D50: 0.906 | E50: =IF(ABS(C50-D50)<=MAX(0.006,ABS(D50)*0.02),"OK","Check") -> OK | F50: Medicaid_SDUD
A51: Share proxies | B51: Pfizer share of Medicaid MPSS Rx, 2025 | C51: =Medicaid_SDUD!$I$18 -> 0.75007832 | D51: 0.75 | E51: =IF(ABS(C51-D51)<=MAX(0.006,ABS(D51)*0.02),"OK","Check") -> OK | F51: Medicaid_SDUD
A52: Share proxies | B52: Pfizer share of Medicaid MPSS Rx, Q1 2026 | C52: =Medicaid_SDUD!$J$18 -> 0.73791431 | D52: 0.738 | E52: =IF(ABS(C52-D52)<=MAX(0.006,ABS(D52)*0.02),"OK","Check") -> OK | F52: Medicaid_SDUD
A53: Share proxies | B53: Dr. Reddy's share of Medicaid MPSS Rx, 2022 | C53: =Medicaid_SDUD!$F$20 -> 0.0036924668 | D53: 0.004 | E53: =IF(ABS(C53-D53)<=MAX(0.006,ABS(D53)*0.02),"OK","Check") -> OK | F53: Medicaid_SDUD
A54: Share proxies | B54: Dr. Reddy's share of Medicaid MPSS Rx, Q1 2026 | C54: =Medicaid_SDUD!$J$20 -> 0.16884014 | D54: 0.169 | E54: =IF(ABS(C54-D54)<=MAX(0.006,ABS(D54)*0.02),"OK","Check") -> OK | F54: Medicaid_SDUD
A55: Share proxies | B55: Fresenius Kabi share of Medicaid MPSS Rx, Q1 2026 | C55: =Medicaid_SDUD!$J$19 -> 0.060622295 | D55: 0.061 | E55: =IF(ABS(C55-D55)<=MAX(0.006,ABS(D55)*0.02),"OK","Check") -> OK | F55: Medicaid_SDUD
A56: Share proxies | B56: Pfizer share of Medicaid HSS Rx, 2025 | C56: =Medicaid_SDUD!$I$37 -> 0.94611693 | D56: 0.946 | E56: =IF(ABS(C56-D56)<=MAX(0.006,ABS(D56)*0.02),"OK","Check") -> OK | F56: Medicaid_SDUD
A57: Share proxies | B57: Pfizer share of Medicaid HSS Rx, Q1 2026 | C57: =Medicaid_SDUD!$J$37 -> 0.9321883 | D57: 0.932 | E57: =IF(ABS(C57-D57)<=MAX(0.006,ABS(D57)*0.02),"OK","Check") -> OK | F57: Medicaid_SDUD
A58: Share proxies | B58: Cipla share of Medicaid HSS Rx, Q1 2026 | C58: =Medicaid_SDUD!$J$38 -> 0.067811705 | D58: 0.068 | E58: =IF(ABS(C58-D58)<=MAX(0.006,ABS(D58)*0.02),"OK","Check") -> OK | F58: Medicaid_SDUD
A59: Share proxies | B59: Pfizer share of Medicaid MPA Rx, Q1 2026 | C59: =Medicaid_SDUD!$J$56 -> 0.57291003 | D59: 0.573 | E59: =IF(ABS(C59-D59)<=MAX(0.006,ABS(D59)*0.02),"OK","Check") -> OK | F59: Medicaid_SDUD
A60: Share proxies | B60: Teva share of Medicaid MPA Rx, 2021 | C60: =Medicaid_SDUD!$E$57 -> 0.2810634 | D60: 0.281 | E60: =IF(ABS(C60-D60)<=MAX(0.006,ABS(D60)*0.02),"OK","Check") -> OK | F60: Medicaid_SDUD
A61: Share proxies | B61: HSS 250 mg-1 g prescriptions, 2025 | C61: =Medicaid_SDUD!$B$89 -> 1157 | D61: 1157 | E61: =IF(ABS(C61-D61)<=MAX(50,ABS(D61)*0.01),"OK","Check") -> OK | F61: Medicaid_SDUD
A62: Share proxies | B62: HSS 250 mg-1 g share of HSS Medicaid Rx, 2025 | C62: =Medicaid_SDUD!$B$90 -> 0.031016272 | D62: 0.031 | E62: =IF(ABS(C62-D62)<=MAX(0.006,ABS(D62)*0.02),"OK","Check") -> OK | F62: Medicaid_SDUD
A63: Share proxies | B63: HSS 250 mg-1 g share of HSS Medicaid US$, 2025 | C63: =Medicaid_SDUD!$B$91 -> 0.060479422 | D63: 0.06 | E63: =IF(ABS(C63-D63)<=MAX(0.006,ABS(D63)*0.02),"OK","Check") -> OK | F63: Medicaid_SDUD
A64: ASP caveats | B64: J1720 drag if 250 mg counts as 3 units | C64: =Medicaid_SDUD!$B$92 -> 0.012016873 | D64: 0.012 | E64: =IF(ABS(C64-D64)<=MAX(0.006,ABS(D64)*0.02),"OK","Check") -> OK | F64: Medicaid_SDUD
A65: Share proxies | B65: Part D: Solu-Medrol share of MPSS claims, 2024 | C65: =CMS_Spending!$F$63 -> 0.46614142 | D65: 0.466 | E65: =IF(ABS(C65-D65)<=MAX(0.006,ABS(D65)*0.02),"OK","Check") -> OK | F65: CMS_Spending
A66: Share proxies | B66: Part D: Dr. Reddy's share of MPSS claims, 2024 | C66: =CMS_Spending!$F$64 -> 0.26504102 | D66: 0.265 | E66: =IF(ABS(C66-D66)<=MAX(0.006,ABS(D66)*0.02),"OK","Check") -> OK | F66: CMS_Spending
A67: Share proxies | B67: Part D: Fresenius share of MPSS claims, 2024 | C67: =CMS_Spending!$F$65 -> 0.2456049 | D67: 0.246 | E67: =IF(ABS(C67-D67)<=MAX(0.006,ABS(D67)*0.02),"OK","Check") -> OK | F67: CMS_Spending
A68: Share proxies | B68: Part D: Solu-Cortef share of HSS claims, 2024 | C68: =CMS_Spending!$G$63 -> 0.99280293 | D68: 0.993 | E68: =IF(ABS(C68-D68)<=MAX(0.006,ABS(D68)*0.02),"OK","Check") -> OK | F68: CMS_Spending
A69: Share proxies | B69: Part D: Depo-Medrol share of MPA claims, 2024 | C69: =CMS_Spending!$H$63 -> 0.073508123 | D69: 0.074 | E69: =IF(ABS(C69-D69)<=MAX(0.006,ABS(D69)*0.02),"OK","Check") -> OK | F69: CMS_Spending
A70: Share proxies | B70: Part D: Amneal share of MPA claims, 2024 | C70: =CMS_Spending!$H$67 -> 0.88491234 | D70: 0.885 | E70: =IF(ABS(C70-D70)<=MAX(0.006,ABS(D70)*0.02),"OK","Check") -> OK | F70: CMS_Spending
A71: Share proxies | B71: Part D: generic MPSS spend per unit, 2024 | C71: =CMS_Spending!$F$70 -> 4.6597265 | D71: 4.66 | E71: =IF(ABS(C71-D71)<=MAX(0.0051,ABS(D71)*0.02),"OK","Check") -> OK | F71: CMS_Spending
A72: Share proxies | B72: Part D: brand MPSS spend per unit, 2024 | C72: =CMS_Spending!$F$71 -> 7.39553 | D72: 7.4 | E72: =IF(ABS(C72-D72)<=MAX(0.0051,ABS(D72)*0.02),"OK","Check") -> OK | F72: CMS_Spending
A73: Share proxies | B73: Medicaid Spending by Drug: MPSS brand share of US$, 2024 | C73: =CMS_Spending!$F$76 -> 0.715405 | D73: 0.72 | E73: =IF(ABS(C73-D73)<=MAX(0.006,ABS(D73)*0.02),"OK","Check") -> OK | F73: CMS_Spending
A74: Share proxies | B74: Part B: J1720 average spend per unit, 2016 | C74: =CMS_Spending!$F$136 -> 7.51 | D74: 7.51 | E74: =IF(ABS(C74-D74)<=MAX(0.0051,ABS(D74)*0.02),"OK","Check") -> OK | F74: CMS_Spending
A75: Share proxies | B75: Part B: J1720 average spend per unit, 2024 | C75: =CMS_Spending!$F$137 -> 17.99459 | D75: 17.99 | E75: =IF(ABS(C75-D75)<=MAX(0.0051,ABS(D75)*0.02),"OK","Check") -> OK | F75: CMS_Spending
A76: Share proxies | B76: Part B: J1720 dosage units, 2016 | C76: =CMS_Spending!$F$138 -> 54721 | D76: 54700 | E76: =IF(ABS(C76-D76)<=MAX(50,ABS(D76)*0.01),"OK","Check") -> OK | F76: CMS_Spending
A77: Share proxies | B77: Part B: J1720 dosage units, 2024 | C77: =CMS_Spending!$F$140 -> 26691.5 | D77: 26700 | E77: =IF(ABS(C77-D77)<=MAX(50,ABS(D77)*0.01),"OK","Check") -> OK | F77: CMS_Spending
A78: Market size | B78: Part B FFS: HSS / MPSS spend, 2023 | C78: =CMS_Spending!$F$147 -> 0.22897291 | D78: 0.23 | E78: =IF(ABS(C78-D78)<=MAX(0.051,ABS(D78)*0.02),"OK","Check") -> OK | F78: CMS_Spending
A79: Market size | B79: Medicaid gross: HSS / MPSS spend, 2024 | C79: =CMS_Spending!$F$148 -> 0.13031587 | D79: 0.13 | E79: =IF(ABS(C79-D79)<=MAX(0.051,ABS(D79)*0.02),"OK","Check") -> OK | F79: CMS_Spending
A80: Market size | B80: Part D: HSS / MPSS spend, 2024 | C80: =CMS_Spending!$F$149 -> 1.4249351 | D80: 1.4 | E80: =IF(ABS(C80-D80)<=MAX(0.051,ABS(D80)*0.02),"OK","Check") -> OK | F80: CMS_Spending
A81: Market size | B81: ICICI FY29E complex injectables in US$ mn | C81: =Market_Size!$B$25 -> 24.011561 | D81: 24 | E81: =IF(ABS(C81-D81)<=MAX(0.051,ABS(D81)*0.02),"OK","Check") -> OK | F81: Market_Size
A82: Market size | B82: ICICI FY29E as % of US$288 mn | C82: =Market_Size!$B$26 -> 0.083373475 | D82: 0.08 | E82: =IF(ABS(C82-D82)<=MAX(0.006,ABS(D82)*0.02),"OK","Check") -> OK | F82: Market_Size
A83: Market size | B83: Pfizer US Medrol revenue change, 2018 to 2023 | C83: =Market_Size!$C$44 -> -0.5037594 | F83: Market_Size
A84: Implications | B84: Mhow capacity as % of US MPSS vial-equivalents (rough) | C84: =Market_Size!$B$33 -> 0.83529874 | F84: Market_Size
A85: Timing | B85: Earliest FDA action on first DCV ANDA | C85: =Timing!$B$6 -> 46569 | D85: 46569 | E85: =IF(ABS(C85-D85)<=31,"OK","Check") -> OK | F85: Timing
A86: Timing | B86: Fiscal year of earliest action | C86: =Timing!$B$7 -> FY28 | D86: FY28 | E86: =IF(C86=D86,"OK","Check") -> OK | F86: Timing
A87: Timing | B87: Cipla CGT exclusivity end | C87: =Timing!$B$10 -> 45741 | D87: 45741 | E87: =IF(ABS(C87-D87)<=31,"OK","Check") -> OK | F87: Timing
A88: Timing | B88: Months from Cipla approval to report date (report: 25) | C88: =Timing!$B$11 -> 25 | D88: 25 | E88: =IF(ABS(C88-D88)<=MAX(0.0011,ABS(D88)*0.02),"OK","Check") -> OK | F88: Timing

Sheet Assumptions
A1: Assumptions and conversion factors
A4: Parameter | B4: Value | C4: Unit | D4: Source / note
A5: ASP add-on divisor (payment limit = ASP x 1.06) | B5: 1.06 | C5: x | D5: S01: Medicare Part B pays ASP + 6% for multi-source drugs; inflation-rebate coinsurance column reads 20% in every quarter used
A6: First quarter of new codes J2919 / J1010: year | B6: 2024 | C6: year | D6: S04: J2919 and J1010 first appear in the April 2024 CMS file
A7: First quarter of new codes: quarter number | B7: 2 | C7: quarter | D7: S04
A8: Cutover quarter index | B8: =B6+(B7-1)/4 -> 2024.25 | C8: index | D8: Formula: year + (quarter - 1) / 4
A9: FX rate | B9: 86.5 | C9: INR per US$ | D9: Analyst assumption used only to convert ICICI's INR estimates; update as needed
A10: FDA review goal, standard original ANDA | B10: 10 | C10: months | D10: S09: GDUFA III, act on 90% of standard original ANDAs within 10 months of submission
A11: Symbiotec first DCV ANDA filing date | B11: 46266 | C11: date | D11: S25 slide 5: filed 'September 2026'. Day not disclosed; 1st of month assumed
A12: Second DCV ANDA filing window: start | B12: 46388 | C12: date | D12: S25 slide 5: 'scheduled for Q4 FY27' (Jan-Mar 2027)
A13: Second DCV ANDA filing window: end | B13: 46477 | C13: date | D13: S25 slide 5
A14: CGT exclusivity period | B14: 180 | C14: days | D14: S08: 180-day competitive generic therapy exclusivity
A15: Cipla HSS first commercial marketing | B15: 45561 | C15: date | D15: S08: FDA CGT list
A16: Cipla HSS ANDA 214050 approval | B16: 45540 | C16: date | D16: S05: Orange Book
A17: Report as-of date | B17: 46316 | C17: date | D17: Date the data were pulled
A20: Billing units per vial (CMS NDC-HCPCS crosswalk convention)
A21: Vial | B21: Old code (to Q1 2024) | C21: Old units per vial | D21: New code (from Q2 2024) | E21: New units per vial | F21: Source / note
A22: MPSS 40 mg | B22: J2920 | C22: 1 | D22: J2919 | E22: 8 | F22: J2920 = up to 40 mg; J2919 = 5 mg. S01, S04
A23: MPSS 125 mg | B23: J2930 | C23: 1 | D23: J2919 | E23: 25 | F23: J2930 = up to 125 mg. S01, S04
A24: MPSS 500 mg | B24: J2930 | C24: 4 | D24: J2919 | E24: 100 | F24: S01, S04
A25: MPSS 1 g | B25: J2930 | C25: 8 | D25: J2919 | E25: 200 | F25: S01, S04
A26: MPSS 2 g | B26: J2930 | C26: 16 | D26: J2919 | E26: 400 | F26: S01, S04
A27: HSS 100 mg | B27: J1720 | C27: 1 | D27: J1720 | E27: 1 | F27: J1720 = up to 100 mg. S03
A28: HSS 250 mg (2.5 units) | B28: J1720 | C28: 2.5 | D28: J1720 | E28: 2.5 | F28: CMS crosswalk convention through Q3 2026. S01
A29: HSS 250 mg (3 units) | B29: J1720 | C29: 3 | D29: J1720 | E29: 3 | F29: October 2026 crosswalk convention ('UP TO 100 MG'). S03
A30: HSS 500 mg | B30: J1720 | C30: 5 | D30: J1720 | E30: 5 | F30: S03
A31: HSS 1 g | B31: J1720 | C31: 10 | D31: J1720 | E31: 10 | F31: S03
A32: MPA 40 mg/mL 1 mL | B32: J1030 | C32: 1 | D32: J1010 | E32: 40 | F32: J1030 = 40 mg; J1010 = 1 mg. S01, S04
A33: MPA 80 mg/mL 1 mL | B33: J1040 | C33: 1 | D33: J1010 | E33: 80 | F33: J1040 = 80 mg. S01, S04

Sheet CMS_PL
A1: Input: CMS Part B payment limit per billing unit (US$)
A2: Source S01 (each quarter's pricing file, URL in column N). Values copied unchanged.
A5: Quarter | B5: Year | C5: Qtr | D5: Quarter index | E5: J2920 MPSS up to 40 mg | F5: J2930 MPSS up to 125 mg | G5: J2919 MPSS per 5 mg | H5: J1720 HSS up to 100 mg | I5: J1030 MPA 40 mg | J5: J1040 MPA 80 mg | K5: J1010 MPA per 1 mg | L5: J1020 MPA 20 mg | M5: ASP sales quarter | N5: Payment-limit file (CMS)
A6: 2016-Q1 | B6: 2016 | C6: 1 | D6: =VALUE(B6)+(C6-1)/4 -> 2016 | E6: 2.898 | F6: 4.105 | H6: 7.502 | I6: 4.308 | J6: 8.334 | L6: 4.495 | M6: 3Q15 | N6: https://www.cms.gov/Medicare/Medicare-Fee-for-Service-Part-B-Drugs/McrPartBDrugAvgSalesPrice/downloads/2016-January-ASP-Pricing-File.zip
A7: 2016-Q2 | B7: 2016 | C7: 2 | D7: =VALUE(B7)+(C7-1)/4 -> 2016.25 | E7: 2.955 | F7: 4.213 | H7: 7.462 | I7: 4.489 | J7: 8.564 | L7: 4.493 | M7: 4Q15 | N7: https://www.cms.gov/Medicare/Medicare-Fee-for-Service-Part-B-Drugs/McrPartBDrugAvgSalesPrice/downloads/2016-April-ASP-Pricing-File.zip
A8: 2016-Q3 | B8: 2016 | C8: 3 | D8: =VALUE(B8)+(C8-1)/4 -> 2016.5 | E8: 3.331 | F8: 4.964 | H8: 8.163 | I8: 4.954 | J8: 9.478 | L8: 4.754 | M8: 1Q16 | N8: https://www.cms.gov/Medicare/Medicare-Fee-for-Service-Part-B-Drugs/McrPartBDrugAvgSalesPrice/Downloads/2016-July-ASP-Pricing-File.zip
A9: 2016-Q4 | B9: 2016 | C9: 4 | D9: =VALUE(B9)+(C9-1)/4 -> 2016.75 | E9: 3.726 | F9: 5.126 | H9: 8.531 | I9: 5.222 | J9: 9.8 | L9: 4.821 | M9: 2Q16 | N9: https://www.cms.gov/Medicare/Medicare-Fee-for-Service-Part-B-Drugs/McrPartBDrugAvgSalesPrice/Downloads/2016-October-ASP-Pricing-File.zip
A10: 2017-Q1 | B10: 2017 | C10: 1 | D10: =VALUE(B10)+(C10-1)/4 -> 2017 | E10: 4.002 | F10: 5.498 | H10: 9.118 | I10: 5.472 | J10: 10.268 | L10: 4.987 | M10: 3Q16 | N10: https://www.cms.gov/Medicare/Medicare-Fee-for-Service-Part-B-Drugs/McrPartBDrugAvgSalesPrice/Downloads/2017-January-ASP-Pricing-Files.zip
A11: 2017-Q2 | B11: 2017 | C11: 2 | D11: =VALUE(B11)+(C11-1)/4 -> 2017.25 | E11: 4.064 | F11: 5.568 | H11: 9.034 | I11: 5.568 | J11: 10.614 | L11: 4.99 | M11: 4Q16 | N11: https://www.cms.gov/Medicare/Medicare-Fee-for-Service-Part-B-Drugs/McrPartBDrugAvgSalesPrice/Downloads/2017-April-ASP-Pricing.zip
A12: 2017-Q3 | B12: 2017 | C12: 3 | D12: =VALUE(B12)+(C12-1)/4 -> 2017.5 | E12: 4.348 | F12: 6.033 | H12: 10.852 | I12: 6.004 | J12: 11.53 | L12: 5.402 | M12: 1Q17 | N12: https://www.cms.gov/Medicare/Medicare-Fee-for-Service-Part-B-Drugs/McrPartBDrugAvgSalesPrice/Downloads/2017-July-ASP-Pricing-File.zip
A13: 2017-Q4 | B13: 2017 | C13: 4 | D13: =VALUE(B13)+(C13-1)/4 -> 2017.75 | E13: 4.337 | F13: 6.093 | H13: 11.279 | I13: 6.362 | J13: 12.26 | L13: 5.592 | M13: 2Q17 | N13: https://www.cms.gov/Medicare/Medicare-Fee-for-Service-Part-B-Drugs/McrPartBDrugAvgSalesPrice/Downloads/2017-October-ASP-Pricing-File.zip
A14: 2018-Q1 | B14: 2018 | C14: 1 | D14: =VALUE(B14)+(C14-1)/4 -> 2018 | E14: 4.346 | F14: 5.985 | H14: 11.931 | I14: 6.694 | J14: 12.963 | L14: 5.945 | M14: 3Q17 | N14: https://www.cms.gov/Medicare/Medicare-Fee-for-Service-Part-B-Drugs/McrPartBDrugAvgSalesPrice/Downloads/2018-January-ASP-Pricing-File.zip
A15: 2018-Q2 | B15: 2018 | C15: 2 | D15: =VALUE(B15)+(C15-1)/4 -> 2018.25 | E15: 4.537 | F15: 6.672 | H15: 12.05 | I15: 6.638 | J15: 12.909 | L15: 4.837 | M15: 4Q17 | N15: https://www.cms.gov/Medicare/Medicare-Fee-for-Service-Part-B-Drugs/McrPartBDrugAvgSalesPrice/Downloads/2018-April-ASP-Pricing-File.zip
A16: 2018-Q3 | B16: 2018 | C16: 3 | D16: =VALUE(B16)+(C16-1)/4 -> 2018.5 | E16: 4.805 | F16: 6.965 | H16: 13.177 | I16: 7.001 | J16: 13.51 | L16: 4.177 | M16: 1Q18 | N16: https://www.cms.gov/Medicare/Medicare-Fee-for-Service-Part-B-Drugs/McrPartBDrugAvgSalesPrice/Downloads/2018-July-ASP-Pricing-File.zip
A17: 2018-Q4 | B17: 2018 | C17: 4 | D17: =VALUE(B17)+(C17-1)/4 -> 2018.75 | E17: 4.717 | F17: 6.942 | H17: 13.051 | I17: 6.773 | J17: 13.321 | L17: 4.314 | M17: 2Q18 | N17: https://www.cms.gov/Medicare/Medicare-Fee-for-Service-Part-B-Drugs/McrPartBDrugAvgSalesPrice/Downloads/2018-Oct-ASP-Pricing-File.zip
... A38: 2024-Q1 | B38: 2024 | C38: 1 | D38: =VALUE(B38)+(C38-1)/4 -> 2024 | E38: 4.188 | F38: 5.882 | H38: 17.845 | I38: 6.419 | J38: 9.803 | L38: 7.038 | M38: 3Q23 | N38: https://www.cms.gov/files/zip/january-2024-asp-pricing-file.zip
A39: 2024-Q2 | B39: 2024 | C39: 2 | D39: =VALUE(B39)+(C39-1)/4 -> 2024.25 | G39: 0.273 | H39: 18.459 | K39: 0.134 | M39: 4Q23 | N39: https://www.cms.gov/files/zip/april-2024-asp-pricing-file.zip
A40: 2024-Q3 | B40: 2024 | C40: 3 | D40: =VALUE(B40)+(C40-1)/4 -> 2024.5 | G40: 0.295 | H40: 19.853 | K40: 0.138 | M40: 1Q24 | N40: https://www.cms.gov/files/zip/july-2024-asp-pricing-file.zip
A41: 2024-Q4 | B41: 2024 | C41: 4 | D41: =VALUE(B41)+(C41-1)/4 -> 2024.75 | G41: 0.304 | H41: 19.397 | K41: 0.119 | M41: 2Q24 | N41: https://www.cms.gov/files/zip/october-2024-asp-pricing-file.zip
A42: 2025-Q1 | B42: 2025 | C42: 1 | D42: =VALUE(B42)+(C42-1)/4 -> 2025 | G42: 0.268 | H42: 20.939 | K42: 0.117 | M42: 3Q24 | N42: https://www.cms.gov/files/zip/january-2025-asp-pricing-file-03/11/25-final-file.zip
A43: 2025-Q2 | B43: 2025 | C43: 2 | D43: =VALUE(B43)+(C43-1)/4 -> 2025.25 | G43: 0.251 | H43: 20.58 | K43: 0.11 | M43: 4Q24 | N43: https://www.cms.gov/files/zip/april-2025-asp-pricing-file.zip
A44: 2025-Q3 | B44: 2025 | C44: 3 | D44: =VALUE(B44)+(C44-1)/4 -> 2025.5 | G44: 0.259 | H44: 21.201 | K44: 0.12 | M44: 1Q25 | N44: https://www.cms.gov/files/zip/july-2025-asp-pricing-file.zip
A45: 2025-Q4 | B45: 2025 | C45: 4 | D45: =VALUE(B45)+(C45-1)/4 -> 2025.75 | G45: 0.21 | H45: 21.312 | K45: 0.119 | M45: 2Q25 | N45: https://www.cms.gov/files/zip/october-2025-asp-pricing-final-file.zip
A46: 2026-Q1 | B46: 2026 | C46: 1 | D46: =VALUE(B46)+(C46-1)/4 -> 2026 | G46: 0.264 | H46: 22.061 | K46: 0.12 | M46: 3Q25 | N46: https://www.cms.gov/files/zip/january-2026-medicare-part-b-payment-limit-files.zip
A47: 2026-Q2 | B47: 2026 | C47: 2 | D47: =VALUE(B47)+(C47-1)/4 -> 2026.25 | G47: 0.241 | H47: 22.141 | K47: 0.112 | M47: 4Q25 | N47: https://www.cms.gov/files/zip/april-2026-medicare-part-b-payment-limit-files-final-file.zip
A48: 2026-Q3 | B48: 2026 | C48: 3 | D48: =VALUE(B48)+(C48-1)/4 -> 2026.5 | G48: 0.224 | H48: 23.056 | K48: 0.117 | M48: 1Q26 | N48: https://www.cms.gov/files/zip/july-2026-medicare-part-b-payment-limit-files.zip
A49: 2026-Q4 | B49: 2026 | C49: 4 | D49: =VALUE(B49)+(C49-1)/4 -> 2026.75 | G49: 0.255 | H49: 23.149 | K49: 0.123 | M49: 2Q26 | N49: https://www.cms.gov/files/zip/october-2026-medicare-part-b-payment-limit-files-final.zip

Sheet ASP_per_vial
A1: Implied ASP per vial (US$) = payment limit x billing units per vial / 1.06
A2: MPSS and MPA switch from the old to the new HCPCS code at the cutover quarter in Assumptions. Inputs: CMS_PL, Assumptions.
A5: Quarter | B5: Year | C5: Quarter index | D5: Code regime | E5: MPSS 40 mg | F5: MPSS 125 mg | G5: MPSS 500 mg | H5: MPSS 1 g | I5: MPSS 2 g | J5: HSS 100 mg | K5: HSS 250 mg (2.5 units) | L5: HSS 250 mg (3 units) | M5: HSS 500 mg | N5: HSS 1 g | O5: MPA 40 mg/mL 1 mL | P5: MPA 80 mg/mL 1 mL
A6: =CMS_PL!A6 -> 2016-Q1 | B6: =CMS_PL!B6 -> 2016 | C6: =CMS_PL!D6 -> 2016 | D6: =IF(C6>=Assumptions!$B$8,"New code","Old code") -> Old code | E6: =IF($C6>=Assumptions!$B$8,CMS_PL!G6*Assumptions!$E$22,CMS_PL!E6*Assumptions!$C$22)/Assumptions!$B$5 -> 2.7339623 | F6: =IF($C6>=Assumptions!$B$8,CMS_PL!G6*Assumptions!$E$23,CMS_PL!F6*Assumptions!$C$23)/Assumptions!$B$5 -> 3.8726415 | G6: =IF($C6>=Assumptions!$B$8,CMS_PL!G6*Assumptions!$E$24,CMS_PL!F6*Assumptions!$C$24)/Assumptions!$B$5 -> 15.490566 | H6: =IF($C6>=Assumptions!$B$8,CMS_PL!G6*Assumptions!$E$25,CMS_PL!F6*Assumptions!$C$25)/Assumptions!$B$5 -> 30.981132 | I6: =IF($C6>=Assumptions!$B$8,CMS_PL!G6*Assumptions!$E$26,CMS_PL!F6*Assumptions!$C$26)/Assumptions!$B$5 -> 61.962264 | J6: =IF($C6>=Assumptions!$B$8,CMS_PL!H6*Assumptions!$E$27,CMS_PL!H6*Assumptions!$C$27)/Assumptions!$B$5 -> 7.0773585 | K6: =IF($C6>=Assumptions!$B$8,CMS_PL!H6*Assumptions!$E$28,CMS_PL!H6*Assumptions!$C$28)/Assumptions!$B$5 -> 17.693396 | L6: =IF($C6>=Assumptions!$B$8,CMS_PL!H6*Assumptions!$E$29,CMS_PL!H6*Assumptions!$C$29)/Assumptions!$B$5 -> 21.232075 | M6: =IF($C6>=Assumptions!$B$8,CMS_PL!H6*Assumptions!$E$30,CMS_PL!H6*Assumptions!$C$30)/Assumptions!$B$5 -> 35.386792 | N6: =IF($C6>=Assumptions!$B$8,CMS_PL!H6*Assumptions!$E$31,CMS_PL!H6*Assumptions!$C$31)/Assumptions!$B$5 -> 70.773585 | O6: =IF($C6>=Assumptions!$B$8,CMS_PL!K6*Assumptions!$E$32,CMS_PL!I6*Assumptions!$C$32)/Assumptions!$B$5 -> 4.0641509 | P6: =IF($C6>=Assumptions!$B$8,CMS_PL!K6*Assumptions!$E$33,CMS_PL!J6*Assumptions!$C$33)/Assumptions!$B$5 -> 7.8622642
A7: =CMS_PL!A7 -> 2016-Q2 | B7: =CMS_PL!B7 -> 2016 | C7: =CMS_PL!D7 -> 2016.25 | D7: =IF(C7>=Assumptions!$B$8,"New code","Old code") -> Old code | E7: =IF($C7>=Assumptions!$B$8,CMS_PL!G7*Assumptions!$E$22,CMS_PL!E7*Assumptions!$C$22)/Assumptions!$B$5 -> 2.7877358 | F7: =IF($C7>=Assumptions!$B$8,CMS_PL!G7*Assumptions!$E$23,CMS_PL!F7*Assumptions!$C$23)/Assumptions!$B$5 -> 3.9745283 | G7: =IF($C7>=Assumptions!$B$8,CMS_PL!G7*Assumptions!$E$24,CMS_PL!F7*Assumptions!$C$24)/Assumptions!$B$5 -> 15.898113 | H7: =IF($C7>=Assumptions!$B$8,CMS_PL!G7*Assumptions!$E$25,CMS_PL!F7*Assumptions!$C$25)/Assumptions!$B$5 -> 31.796226 | I7: =IF($C7>=Assumptions!$B$8,CMS_PL!G7*Assumptions!$E$26,CMS_PL!F7*Assumptions!$C$26)/Assumptions!$B$5 -> 63.592453 | J7: =IF($C7>=Assumptions!$B$8,CMS_PL!H7*Assumptions!$E$27,CMS_PL!H7*Assumptions!$C$27)/Assumptions!$B$5 -> 7.0396226 | K7: =IF($C7>=Assumptions!$B$8,CMS_PL!H7*Assumptions!$E$28,CMS_PL!H7*Assumptions!$C$28)/Assumptions!$B$5 -> 17.599057 | L7: =IF($C7>=Assumptions!$B$8,CMS_PL!H7*Assumptions!$E$29,CMS_PL!H7*Assumptions!$C$29)/Assumptions!$B$5 -> 21.118868 | M7: =IF($C7>=Assumptions!$B$8,CMS_PL!H7*Assumptions!$E$30,CMS_PL!H7*Assumptions!$C$30)/Assumptions!$B$5 -> 35.198113 | N7: =IF($C7>=Assumptions!$B$8,CMS_PL!H7*Assumptions!$E$31,CMS_PL!H7*Assumptions!$C$31)/Assumptions!$B$5 -> 70.396226 | O7: =IF($C7>=Assumptions!$B$8,CMS_PL!K7*Assumptions!$E$32,CMS_PL!I7*Assumptions!$C$32)/Assumptions!$B$5 -> 4.2349057 | P7: =IF($C7>=Assumptions!$B$8,CMS_PL!K7*Assumptions!$E$33,CMS_PL!J7*Assumptions!$C$33)/Assumptions!$B$5 -> 8.0792453
A8: =CMS_PL!A8 -> 2016-Q3 | B8: =CMS_PL!B8 -> 2016 | C8: =CMS_PL!D8 -> 2016.5 | D8: =IF(C8>=Assumptions!$B$8,"New code","Old code") -> Old code | E8: =IF($C8>=Assumptions!$B$8,CMS_PL!G8*Assumptions!$E$22,CMS_PL!E8*Assumptions!$C$22)/Assumptions!$B$5 -> 3.1424528 | F8: =IF($C8>=Assumptions!$B$8,CMS_PL!G8*Assumptions!$E$23,CMS_PL!F8*Assumptions!$C$23)/Assumptions!$B$5 -> 4.6830189 | G8: =IF($C8>=Assumptions!$B$8,CMS_PL!G8*Assumptions!$E$24,CMS_PL!F8*Assumptions!$C$24)/Assumptions!$B$5 -> 18.732075 | H8: =IF($C8>=Assumptions!$B$8,CMS_PL!G8*Assumptions!$E$25,CMS_PL!F8*Assumptions!$C$25)/Assumptions!$B$5 -> 37.464151 | I8: =IF($C8>=Assumptions!$B$8,CMS_PL!G8*Assumptions!$E$26,CMS_PL!F8*Assumptions!$C$26)/Assumptions!$B$5 -> 74.928302 | J8: =IF($C8>=Assumptions!$B$8,CMS_PL!H8*Assumptions!$E$27,CMS_PL!H8*Assumptions!$C$27)/Assumptions!$B$5 -> 7.7009434 | K8: =IF($C8>=Assumptions!$B$8,CMS_PL!H8*Assumptions!$E$28,CMS_PL!H8*Assumptions!$C$28)/Assumptions!$B$5 -> 19.252358 | L8: =IF($C8>=Assumptions!$B$8,CMS_PL!H8*Assumptions!$E$29,CMS_PL!H8*Assumptions!$C$29)/Assumptions!$B$5 -> 23.10283 | M8: =IF($C8>=Assumptions!$B$8,CMS_PL!H8*Assumptions!$E$30,CMS_PL!H8*Assumptions!$C$30)/Assumptions!$B$5 -> 38.504717 | N8: =IF($C8>=Assumptions!$B$8,CMS_PL!H8*Assumptions!$E$31,CMS_PL!H8*Assumptions!$C$31)/Assumptions!$B$5 -> 77.009434 | O8: =IF($C8>=Assumptions!$B$8,CMS_PL!K8*Assumptions!$E$32,CMS_PL!I8*Assumptions!$C$32)/Assumptions!$B$5 -> 4.6735849 | P8: =IF($C8>=Assumptions!$B$8,CMS_PL!K8*Assumptions!$E$33,CMS_PL!J8*Assumptions!$C$33)/Assumptions!$B$5 -> 8.9415094
A9: =CMS_PL!A9 -> 2016-Q4 | B9: =CMS_PL!B9 -> 2016 | C9: =CMS_PL!D9 -> 2016.75 | D9: =IF(C9>=Assumptions!$B$8,"New code","Old code") -> Old code | E9: =IF($C9>=Assumptions!$B$8,CMS_PL!G9*Assumptions!$E$22,CMS_PL!E9*Assumptions!$C$22)/Assumptions!$B$5 -> 3.5150943 | F9: =IF($C9>=Assumptions!$B$8,CMS_PL!G9*Assumptions!$E$23,CMS_PL!F9*Assumptions!$C$23)/Assumptions!$B$5 -> 4.8358491 | G9: =IF($C9>=Assumptions!$B$8,CMS_PL!G9*Assumptions!$E$24,CMS_PL!F9*Assumptions!$C$24)/Assumptions!$B$5 -> 19.343396 | H9: =IF($C9>=Assumptions!$B$8,CMS_PL!G9*Assumptions!$E$25,CMS_PL!F9*Assumptions!$C$25)/Assumptions!$B$5 -> 38.686792 | I9: =IF($C9>=Assumptions!$B$8,CMS_PL!G9*Assumptions!$E$26,CMS_PL!F9*Assumptions!$C$26)/Assumptions!$B$5 -> 77.373585 | J9: =IF($C9>=Assumptions!$B$8,CMS_PL!H9*Assumptions!$E$27,CMS_PL!H9*Assumptions!$C$27)/Assumptions!$B$5 -> 8.0481132 | K9: =IF($C9>=Assumptions!$B$8,CMS_PL!H9*Assumptions!$E$28,CMS_PL!H9*Assumptions!$C$28)/Assumptions!$B$5 -> 20.120283 | L9: =IF($C9>=Assumptions!$B$8,CMS_PL!H9*Assumptions!$E$29,CMS_PL!H9*Assumptions!$C$29)/Assumptions!$B$5 -> 24.14434 | M9: =IF($C9>=Assumptions!$B$8,CMS_PL!H9*Assumptions!$E$30,CMS_PL!H9*Assumptions!$C$30)/Assumptions!$B$5 -> 40.240566 | N9: =IF($C9>=Assumptions!$B$8,CMS_PL!H9*Assumptions!$E$31,CMS_PL!H9*Assumptions!$C$31)/Assumptions!$B$5 -> 80.481132 | O9: =IF($C9>=Assumptions!$B$8,CMS_PL!K9*Assumptions!$E$32,CMS_PL!I9*Assumptions!$C$32)/Assumptions!$B$5 -> 4.9264151 | P9: =IF($C9>=Assumptions!$B$8,CMS_PL!K9*Assumptions!$E$33,CMS_PL!J9*Assumptions!$C$33)/Assumptions!$B$5 -> 9.245283
A10: =CMS_PL!A10 -> 2017-Q1 | B10: =CMS_PL!B10 -> 2017 | C10: =CMS_PL!D10 -> 2017 | D10: =IF(C10>=Assumptions!$B$8,"New code","Old code") -> Old code | E10: =IF($C10>=Assumptions!$B$8,CMS_PL!G10*Assumptions!$E$22,CMS_PL!E10*Assumptions!$C$22)/Assumptions!$B$5 -> 3.7754717 | F10: =IF($C10>=Assumptions!$B$8,CMS_PL!G10*Assumptions!$E$23,CMS_PL!F10*Assumptions!$C$23)/Assumptions!$B$5 -> 5.1867925 | G10: =IF($C10>=Assumptions!$B$8,CMS_PL!G10*Assumptions!$E$24,CMS_PL!F10*Assumptions!$C$24)/Assumptions!$B$5 -> 20.74717 | H10: =IF($C10>=Assumptions!$B$8,CMS_PL!G10*Assumptions!$E$25,CMS_PL!F10*Assumptions!$C$25)/Assumptions!$B$5 -> 41.49434 | I10: =IF($C10>=Assumptions!$B$8,CMS_PL!G10*Assumptions!$E$26,CMS_PL!F10*Assumptions!$C$26)/Assumptions!$B$5 -> 82.988679 | J10: =IF($C10>=Assumptions!$B$8,CMS_PL!H10*Assumptions!$E$27,CMS_PL!H10*Assumptions!$C$27)/Assumptions!$B$5 -> 8.6018868 | K10: =IF($C10>=Assumptions!$B$8,CMS_PL!H10*Assumptions!$E$28,CMS_PL!H10*Assumptions!$C$28)/Assumptions!$B$5 -> 21.504717 | L10: =IF($C10>=Assumptions!$B$8,CMS_PL!H10*Assumptions!$E$29,CMS_PL!H10*Assumptions!$C$29)/Assumptions!$B$5 -> 25.80566 | M10: =IF($C10>=Assumptions!$B$8,CMS_PL!H10*Assumptions!$E$30,CMS_PL!H10*Assumptions!$C$30)/Assumptions!$B$5 -> 43.009434 | N10: =IF($C10>=Assumptions!$B$8,CMS_PL!H10*Assumptions!$E$31,CMS_PL!H10*Assumptions!$C$31)/Assumptions!$B$5 -> 86.018868 | O10: =IF($C10>=Assumptions!$B$8,CMS_PL!K10*Assumptions!$E$32,CMS_PL!I10*Assumptions!$C$32)/Assumptions!$B$5 -> 5.1622642 | P10: =IF($C10>=Assumptions!$B$8,CMS_PL!K10*Assumptions!$E$33,CMS_PL!J10*Assumptions!$C$33)/Assumptions!$B$5 -> 9.6867925
A11: =CMS_PL!A11 -> 2017-Q2 | B11: =CMS_PL!B11 -> 2017 | C11: =CMS_PL!D11 -> 2017.25 | D11: =IF(C11>=Assumptions!$B$8,"New code","Old code") -> Old code | E11: =IF($C11>=Assumptions!$B$8,CMS_PL!G11*Assumptions!$E$22,CMS_PL!E11*Assumptions!$C$22)/Assumptions!$B$5 -> 3.8339623 | F11: =IF($C11>=Assumptions!$B$8,CMS_PL!G11*Assumptions!$E$23,CMS_PL!F11*Assumptions!$C$23)/Assumptions!$B$5 -> 5.2528302 | G11: =IF($C11>=Assumptions!$B$8,CMS_PL!G11*Assumptions!$E$24,CMS_PL!F11*Assumptions!$C$24)/Assumptions!$B$5 -> 21.011321 | H11: =IF($C11>=Assumptions!$B$8,CMS_PL!G11*Assumptions!$E$25,CMS_PL!F11*Assumptions!$C$25)/Assumptions!$B$5 -> 42.022642 | I11: =IF($C11>=Assumptions!$B$8,CMS_PL!G11*Assumptions!$E$26,CMS_PL!F11*Assumptions!$C$26)/Assumptions!$B$5 -> 84.045283 | J11: =IF($C11>=Assumptions!$B$8,CMS_PL!H11*Assumptions!$E$27,CMS_PL!H11*Assumptions!$C$27)/Assumptions!$B$5 -> 8.5226415 | K11: =IF($C11>=Assumptions!$B$8,CMS_PL!H11*Assumptions!$E$28,CMS_PL!H11*Assumptions!$C$28)/Assumptions!$B$5 -> 21.306604 | L11: =IF($C11>=Assumptions!$B$8,CMS_PL!H11*Assumptions!$E$29,CMS_PL!H11*Assumptions!$C$29)/Assumptions!$B$5 -> 25.567925 | M11: =IF($C11>=Assumptions!$B$8,CMS_PL!H11*Assumptions!$E$30,CMS_PL!H11*Assumptions!$C$30)/Assumptions!$B$5 -> 42.613208 | N11: =IF($C11>=Assumptions!$B$8,CMS_PL!H11*Assumptions!$E$31,CMS_PL!H11*Assumptions!$C$31)/Assumptions!$B$5 -> 85.226415 | O11: =IF($C11>=Assumptions!$B$8,CMS_PL!K11*Assumptions!$E$32,CMS_PL!I11*Assumptions!$C$32)/Assumptions!$B$5 -> 5.2528302 | P11: =IF($C11>=Assumptions!$B$8,CMS_PL!K11*Assumptions!$E$33,CMS_PL!J11*Assumptions!$C$33)/Assumptions!$B$5 -> 10.013208
A12: =CMS_PL!A12 -> 2017-Q3 | B12: =CMS_PL!B12 -> 2017 | C12: =CMS_PL!D12 -> 2017.5 | D12: =IF(C12>=Assumptions!$B$8,"New code","Old code") -> Old code | E12: =IF($C12>=Assumptions!$B$8,CMS_PL!G12*Assumptions!$E$22,CMS_PL!E12*Assumptions!$C$22)/Assumptions!$B$5 -> 4.1018868 | F12: =IF($C12>=Assumptions!$B$8,CMS_PL!G12*Assumptions!$E$23,CMS_PL!F12*Assumptions!$C$23)/Assumptions!$B$5 -> 5.6915094 | G12: =IF($C12>=Assumptions!$B$8,CMS_PL!G12*Assumptions!$E$24,CMS_PL!F12*Assumptions!$C$24)/Assumptions!$B$5 -> 22.766038 | H12: =IF($C12>=Assumptions!$B$8,CMS_PL!G12*Assumptions!$E$25,CMS_PL!F12*Assumptions!$C$25)/Assumptions!$B$5 -> 45.532075 | I12: =IF($C12>=Assumptions!$B$8,CMS_PL!G12*Assumptions!$E$26,CMS_PL!F12*Assumptions!$C$26)/Assumptions!$B$5 -> 91.064151 | J12: =IF($C12>=Assumptions!$B$8,CMS_PL!H12*Assumptions!$E$27,CMS_PL!H12*Assumptions!$C$27)/Assumptions!$B$5 -> 10.237736 | K12: =IF($C12>=Assumptions!$B$8,CMS_PL!H12*Assumptions!$E$28,CMS_PL!H12*Assumptions!$C$28)/Assumptions!$B$5 -> 25.59434 | L12: =IF($C12>=Assumptions!$B$8,CMS_PL!H12*Assumptions!$E$29,CMS_PL!H12*Assumptions!$C$29)/Assumptions!$B$5 -> 30.713208 | M12: =IF($C12>=Assumptions!$B$8,CMS_PL!H12*Assumptions!$E$30,CMS_PL!H12*Assumptions!$C$30)/Assumptions!$B$5 -> 51.188679 | N12: =IF($C12>=Assumptions!$B$8,CMS_PL!H12*Assumptions!$E$31,CMS_PL!H12*Assumptions!$C$31)/Assumptions!$B$5 -> 102.37736 | O12: =IF($C12>=Assumptions!$B$8,CMS_PL!K12*Assumptions!$E$32,CMS_PL!I12*Assumptions!$C$32)/Assumptions!$B$5 -> 5.6641509 | P12: =IF($C12>=Assumptions!$B$8,CMS_PL!K12*Assumptions!$E$33,CMS_PL!J12*Assumptions!$C$33)/Assumptions!$B$5 -> 10.877358
A13: =CMS_PL!A13 -> 2017-Q4 | B13: =CMS_PL!B13 -> 2017 | C13: =CMS_PL!D13 -> 2017.75 | D13: =IF(C13>=Assumptions!$B$8,"New code","Old code") -> Old code | E13: =IF($C13>=Assumptions!$B$8,CMS_PL!G13*Assumptions!$E$22,CMS_PL!E13*Assumptions!$C$22)/Assumptions!$B$5 -> 4.0915094 | F13: =IF($C13>=Assumptions!$B$8,CMS_PL!G13*Assumptions!$E$23,CMS_PL!F13*Assumptions!$C$23)/Assumptions!$B$5 -> 5.7481132 | G13: =IF($C13>=Assumptions!$B$8,CMS_PL!G13*Assumptions!$E$24,CMS_PL!F13*Assumptions!$C$24)/Assumptions!$B$5 -> 22.992453 | H13: =IF($C13>=Assumptions!$B$8,CMS_PL!G13*Assumptions!$E$25,CMS_PL!F13*Assumptions!$C$25)/Assumptions!$B$5 -> 45.984906 | I13: =IF($C13>=Assumptions!$B$8,CMS_PL!G13*Assumptions!$E$26,CMS_PL!F13*Assumptions!$C$26)/Assumptions!$B$5 -> 91.969811 | J13: =IF($C13>=Assumptions!$B$8,CMS_PL!H13*Assumptions!$E$27,CMS_PL!H13*Assumptions!$C$27)/Assumptions!$B$5 -> 10.640566 | K13: =IF($C13>=Assumptions!$B$8,CMS_PL!H13*Assumptions!$E$28,CMS_PL!H13*Assumptions!$C$28)/Assumptions!$B$5 -> 26.601415 | L13: =IF($C13>=Assumptions!$B$8,CMS_PL!H13*Assumptions!$E$29,CMS_PL!H13*Assumptions!$C$29)/Assumptions!$B$5 -> 31.921698 | M13: =IF($C13>=Assumptions!$B$8,CMS_PL!H13*Assumptions!$E$30,CMS_PL!H13*Assumptions!$C$30)/Assumptions!$B$5 -> 53.20283 | N13: =IF($C13>=Assumptions!$B$8,CMS_PL!H13*Assumptions!$E$31,CMS_PL!H13*Assumptions!$C$31)/Assumptions!$B$5 -> 106.40566 | O13: =IF($C13>=Assumptions!$B$8,CMS_PL!K13*Assumptions!$E$32,CMS_PL!I13*Assumptions!$C$32)/Assumptions!$B$5 -> 6.0018868 | P13: =IF($C13>=Assumptions!$B$8,CMS_PL!K13*Assumptions!$E$33,CMS_PL!J13*Assumptions!$C$33)/Assumptions!$B$5 -> 11.566038
A14: =CMS_PL!A14 -> 2018-Q1 | B14: =CMS_PL!B14 -> 2018 | C14: =CMS_PL!D14 -> 2018 | D14: =IF(C14>=Assumptions!$B$8,"New code","Old code") -> Old code | E14: =IF($C14>=Assumptions!$B$8,CMS_PL!G14*Assumptions!$E$22,CMS_PL!E14*Assumptions!$C$22)/Assumptions!$B$5 -> 4.1 | F14: =IF($C14>=Assumptions!$B$8,CMS_PL!G14*Assumptions!$E$23,CMS_PL!F14*Assumptions!$C$23)/Assumptions!$B$5 -> 5.6462264 | G14: =IF($C14>=Assumptions!$B$8,CMS_PL!G14*Assumptions!$E$24,CMS_PL!F14*Assumptions!$C$24)/Assumptions!$B$5 -> 22.584906 | H14: =IF($C14>=Assumptions!$B$8,CMS_PL!G14*Assumptions!$E$25,CMS_PL!F14*Assumptions!$C$25)/Assumptions!$B$5 -> 45.169811 | I14: =IF($C14>=Assumptions!$B$8,CMS_PL!G14*Assumptions!$E$26,CMS_PL!F14*Assumptions!$C$26)/Assumptions!$B$5 -> 90.339623 | J14: =IF($C14>=Assumptions!$B$8,CMS_PL!H14*Assumptions!$E$27,CMS_PL!H14*Assumptions!$C$27)/Assumptions!$B$5 -> 11.25566 | K14: =IF($C14>=Assumptions!$B$8,CMS_PL!H14*Assumptions!$E$28,CMS_PL!H14*Assumptions!$C$28)/Assumptions!$B$5 -> 28.139151 | L14: =IF($C14>=Assumptions!$B$8,CMS_PL!H14*Assumptions!$E$29,CMS_PL!H14*Assumptions!$C$29)/Assumptions!$B$5 -> 33.766981 | M14: =IF($C14>=Assumptions!$B$8,CMS_PL!H14*Assumptions!$E$30,CMS_PL!H14*Assumptions!$C$30)/Assumptions!$B$5 -> 56.278302 | N14: =IF($C14>=Assumptions!$B$8,CMS_PL!H14*Assumptions!$E$31,CMS_PL!H14*Assumptions!$C$31)/Assumptions!$B$5 -> 112.5566 | O14: =IF($C14>=Assumptions!$B$8,CMS_PL!K14*Assumptions!$E$32,CMS_PL!I14*Assumptions!$C$32)/Assumptions!$B$5 -> 6.3150943 | P14: =IF($C14>=Assumptions!$B$8,CMS_PL!K14*Assumptions!$E$33,CMS_PL!J14*Assumptions!$C$33)/Assumptions!$B$5 -> 12.229245
A15: =CMS_PL!A15 -> 2018-Q2 | B15: =CMS_PL!B15 -> 2018 | C15: =CMS_PL!D15 -> 2018.25 | D15: =IF(C15>=Assumptions!$B$8,"New code","Old code") -> Old code | E15: =IF($C15>=Assumptions!$B$8,CMS_PL!G15*Assumptions!$E$22,CMS_PL!E15*Assumptions!$C$22)/Assumptions!$B$5 -> 4.2801887 | F15: =IF($C15>=Assumptions!$B$8,CMS_PL!G15*Assumptions!$E$23,CMS_PL!F15*Assumptions!$C$23)/Assumptions!$B$5 -> 6.2943396 | G15: =IF($C15>=Assumptions!$B$8,CMS_PL!G15*Assumptions!$E$24,CMS_PL!F15*Assumptions!$C$24)/Assumptions!$B$5 -> 25.177358 | H15: =IF($C15>=Assumptions!$B$8,CMS_PL!G15*Assumptions!$E$25,CMS_PL!F15*Assumptions!$C$25)/Assumptions!$B$5 -> 50.354717 | I15: =IF($C15>=Assumptions!$B$8,CMS_PL!G15*Assumptions!$E$26,CMS_PL!F15*Assumptions!$C$26)/Assumptions!$B$5 -> 100.70943 | J15: =IF($C15>=Assumptions!$B$8,CMS_PL!H15*Assumptions!$E$27,CMS_PL!H15*Assumptions!$C$27)/Assumptions!$B$5 -> 11.367925 | K15: =IF($C15>=Assumptions!$B$8,CMS_PL!H15*Assumptions!$E$28,CMS_PL!H15*Assumptions!$C$28)/Assumptions!$B$5 -> 28.419811 | L15: =IF($C15>=Assumptions!$B$8,CMS_PL!H15*Assumptions!$E$29,CMS_PL!H15*Assumptions!$C$29)/Assumptions!$B$5 -> 34.103774 | M15: =IF($C15>=Assumptions!$B$8,CMS_PL!H15*Assumptions!$E$30,CMS_PL!H15*Assumptions!$C$30)/Assumptions!$B$5 -> 56.839623 | N15: =IF($C15>=Assumptions!$B$8,CMS_PL!H15*Assumptions!$E$31,CMS_PL!H15*Assumptions!$C$31)/Assumptions!$B$5 -> 113.67925 | O15: =IF($C15>=Assumptions!$B$8,CMS_PL!K15*Assumptions!$E$32,CMS_PL!I15*Assumptions!$C$32)/Assumptions!$B$5 -> 6.2622642 | P15: =IF($C15>=Assumptions!$B$8,CMS_PL!K15*Assumptions!$E$33,CMS_PL!J15*Assumptions!$C$33)/Assumptions!$B$5 -> 12.178302
A16: =CMS_PL!A16 -> 2018-Q3 | B16: =CMS_PL!B16 -> 2018 | C16: =CMS_PL!D16 -> 2018.5 | D16: =IF(C16>=Assumptions!$B$8,"New code","Old code") -> Old code | E16: =IF($C16>=Assumptions!$B$8,CMS_PL!G16*Assumptions!$E$22,CMS_PL!E16*Assumptions!$C$22)/Assumptions!$B$5 -> 4.5330189 | F16: =IF($C16>=Assumptions!$B$8,CMS_PL!G16*Assumptions!$E$23,CMS_PL!F16*Assumptions!$C$23)/Assumptions!$B$5 -> 6.5707547 | G16: =IF($C16>=Assumptions!$B$8,CMS_PL!G16*Assumptions!$E$24,CMS_PL!F16*Assumptions!$C$24)/Assumptions!$B$5 -> 26.283019 | H16: =IF($C16>=Assumptions!$B$8,CMS_PL!G16*Assumptions!$E$25,CMS_PL!F16*Assumptions!$C$25)/Assumptions!$B$5 -> 52.566038 | I16: =IF($C16>=Assumptions!$B$8,CMS_PL!G16*Assumptions!$E$26,CMS_PL!F16*Assumptions!$C$26)/Assumptions!$B$5 -> 105.13208 | J16: =IF($C16>=Assumptions!$B$8,CMS_PL!H16*Assumptions!$E$27,CMS_PL!H16*Assumptions!$C$27)/Assumptions!$B$5 -> 12.431132 | K16: =IF($C16>=Assumptions!$B$8,CMS_PL!H16*Assumptions!$E$28,CMS_PL!H16*Assumptions!$C$28)/Assumptions!$B$5 -> 31.07783 | L16: =IF($C16>=Assumptions!$B$8,CMS_PL!H16*Assumptions!$E$29,CMS_PL!H16*Assumptions!$C$29)/Assumptions!$B$5 -> 37.293396 | M16: =IF($C16>=Assumptions!$B$8,CMS_PL!H16*Assumptions!$E$30,CMS_PL!H16*Assumptions!$C$30)/Assumptions!$B$5 -> 62.15566 | N16: =IF($C16>=Assumptions!$B$8,CMS_PL!H16*Assumptions!$E$31,CMS_PL!H16*Assumptions!$C$31)/Assumptions!$B$5 -> 124.31132 | O16: =IF($C16>=Assumptions!$B$8,CMS_PL!K16*Assumptions!$E$32,CMS_PL!I16*Assumptions!$C$32)/Assumptions!$B$5 -> 6.604717 | P16: =IF($C16>=Assumptions!$B$8,CMS_PL!K16*Assumptions!$E$33,CMS_PL!J16*Assumptions!$C$33)/Assumptions!$B$5 -> 12.745283
A17: =CMS_PL!A17 -> 2018-Q4 | B17: =CMS_PL!B17 -> 2018 | C17: =CMS_PL!D17 -> 2018.75 | D17: =IF(C17>=Assumptions!$B$8,"New code","Old code") -> Old code | E17: =IF($C17>=Assumptions!$B$8,CMS_PL!G17*Assumptions!$E$22,CMS_PL!E17*Assumptions!$C$22)/Assumptions!$B$5 -> 4.45 | F17: =IF($C17>=Assumptions!$B$8,CMS_PL!G17*Assumptions!$E$23,CMS_PL!F17*Assumptions!$C$23)/Assumptions!$B$5 -> 6.5490566 | G17: =IF($C17>=Assumptions!$B$8,CMS_PL!G17*Assumptions!$E$24,CMS_PL!F17*Assumptions!$C$24)/Assumptions!$B$5 -> 26.196226 | H17: =IF($C17>=Assumptions!$B$8,CMS_PL!G17*Assumptions!$E$25,CMS_PL!F17*Assumptions!$C$25)/Assumptions!$B$5 -> 52.392453 | I17: =IF($C17>=Assumptions!$B$8,CMS_PL!G17*Assumptions!$E$26,CMS_PL!F17*Assumptions!$C$26)/Assumptions!$B$5 -> 104.78491 | J17: =IF($C17>=Assumptions!$B$8,CMS_PL!H17*Assumptions!$E$27,CMS_PL!H17*Assumptions!$C$27)/Assumptions!$B$5 -> 12.312264 | K17: =IF($C17>=Assumptions!$B$8,CMS_PL!H17*Assumptions!$E$28,CMS_PL!H17*Assumptions!$C$28)/Assumptions!$B$5 -> 30.78066 | L17: =IF($C17>=Assumptions!$B$8,CMS_PL!H17*Assumptions!$E$29,CMS_PL!H17*Assumptions!$C$29)/Assumptions!$B$5 -> 36.936792 | M17: =IF($C17>=Assumptions!$B$8,CMS_PL!H17*Assumptions!$E$30,CMS_PL!H17*Assumptions!$C$30)/Assumptions!$B$5 -> 61.561321 | N17: =IF($C17>=Assumptions!$B$8,CMS_PL!H17*Assumptions!$E$31,CMS_PL!H17*Assumptions!$C$31)/Assumptions!$B$5 -> 123.12264 | O17: =IF($C17>=Assumptions!$B$8,CMS_PL!K17*Assumptions!$E$32,CMS_PL!I17*Assumptions!$C$32)/Assumptions!$B$5 -> 6.3896226 | P17: =IF($C17>=Assumptions!$B$8,CMS_PL!K17*Assumptions!$E$33,CMS_PL!J17*Assumptions!$C$33)/Assumptions!$B$5 -> 12.566981
... A49: =CMS_PL!A49 -> 2026-Q4 | B49: =CMS_PL!B49 -> 2026 | C49: =CMS_PL!D49 -> 2026.75 | D49: =IF(C49>=Assumptions!$B$8,"New code","Old code") -> New code | E49: =IF($C49>=Assumptions!$B$8,CMS_PL!G49*Assumptions!$E$22,CMS_PL!E49*Assumptions!$C$22)/Assumptions!$B$5 -> 1.9245283 | F49: =IF($C49>=Assumptions!$B$8,CMS_PL!G49*Assumptions!$E$23,CMS_PL!F49*Assumptions!$C$23)/Assumptions!$B$5 -> 6.0141509 | G49: =IF($C49>=Assumptions!$B$8,CMS_PL!G49*Assumptions!$E$24,CMS_PL!F49*Assumptions!$C$24)/Assumptions!$B$5 -> 24.056604 | H49: =IF($C49>=Assumptions!$B$8,CMS_PL!G49*Assumptions!$E$25,CMS_PL!F49*Assumptions!$C$25)/Assumptions!$B$5 -> 48.113208 | I49: =IF($C49>=Assumptions!$B$8,CMS_PL!G49*Assumptions!$E$26,CMS_PL!F49*Assumptions!$C$26)/Assumptions!$B$5 -> 96.226415 | J49: =IF($C49>=Assumptions!$B$8,CMS_PL!H49*Assumptions!$E$27,CMS_PL!H49*Assumptions!$C$27)/Assumptions!$B$5 -> 21.838679 | K49: =IF($C49>=Assumptions!$B$8,CMS_PL!H49*Assumptions!$E$28,CMS_PL!H49*Assumptions!$C$28)/Assumptions!$B$5 -> 54.596698 | L49: =IF($C49>=Assumptions!$B$8,CMS_PL!H49*Assumptions!$E$29,CMS_PL!H49*Assumptions!$C$29)/Assumptions!$B$5 -> 65.516038 | M49: =IF($C49>=Assumptions!$B$8,CMS_PL!H49*Assumptions!$E$30,CMS_PL!H49*Assumptions!$C$30)/Assumptions!$B$5 -> 109.1934 | N49: =IF($C49>=Assumptions!$B$8,CMS_PL!H49*Assumptions!$E$31,CMS_PL!H49*Assumptions!$C$31)/Assumptions!$B$5 -> 218.38679 | O49: =IF($C49>=Assumptions!$B$8,CMS_PL!K49*Assumptions!$E$32,CMS_PL!I49*Assumptions!$C$32)/Assumptions!$B$5 -> 4.6415094 | P49: =IF($C49>=Assumptions!$B$8,CMS_PL!K49*Assumptions!$E$33,CMS_PL!J49*Assumptions!$C$33)/Assumptions!$B$5 -> 9.2830189
A52: Annual average implied ASP per vial (mean of the quarterly files effective in each year). 2024 blends Q1 old code with Q2-Q4 new code.
A53: Year | E53: MPSS 40 mg | F53: MPSS 125 mg | G53: MPSS 500 mg | H53: MPSS 1 g | I53: MPSS 2 g | J53: HSS 100 mg | K53: HSS 250 mg (2.5 units) | L53: HSS 250 mg (3 units) | M53: HSS 500 mg | N53: HSS 1 g | O53: MPA 40 mg/mL 1 mL | P53: MPA 80 mg/mL 1 mL
A54: 2016 | E54: =AVERAGEIFS(E$6:E$49,$B$6:$B$49,$A54) -> 3.0448113 | F54: =AVERAGEIFS(F$6:F$49,$B$6:$B$49,$A54) -> 4.3415094 | G54: =AVERAGEIFS(G$6:G$49,$B$6:$B$49,$A54) -> 17.366038 | H54: =AVERAGEIFS(H$6:H$49,$B$6:$B$49,$A54) -> 34.732075 | I54: =AVERAGEIFS(I$6:I$49,$B$6:$B$49,$A54) -> 69.464151 | J54: =AVERAGEIFS(J$6:J$49,$B$6:$B$49,$A54) -> 7.4665094 | K54: =AVERAGEIFS(K$6:K$49,$B$6:$B$49,$A54) -> 18.666274 | L54: =AVERAGEIFS(L$6:L$49,$B$6:$B$49,$A54) -> 22.399528 | ... P54: =AVERAGEIFS(P$6:P$49,$B$6:$B$49,$A54) -> 8.5320755
A55: 2017 | E55: =AVERAGEIFS(E$6:E$49,$B$6:$B$49,$A55) -> 3.9507075 | F55: =AVERAGEIFS(F$6:F$49,$B$6:$B$49,$A55) -> 5.4698113 | G55: =AVERAGEIFS(G$6:G$49,$B$6:$B$49,$A55) -> 21.879245 | H55: =AVERAGEIFS(H$6:H$49,$B$6:$B$49,$A55) -> 43.758491 | I55: =AVERAGEIFS(I$6:I$49,$B$6:$B$49,$A55) -> 87.516981 | J55: =AVERAGEIFS(J$6:J$49,$B$6:$B$49,$A55) -> 9.5007075 | K55: =AVERAGEIFS(K$6:K$49,$B$6:$B$49,$A55) -> 23.751769 | L55: =AVERAGEIFS(L$6:L$49,$B$6:$B$49,$A55) -> 28.502123 | ... P55: =AVERAGEIFS(P$6:P$49,$B$6:$B$49,$A55) -> 10.535849
A56: 2018 | E56: =AVERAGEIFS(E$6:E$49,$B$6:$B$49,$A56) -> 4.3408019 | F56: =AVERAGEIFS(F$6:F$49,$B$6:$B$49,$A56) -> 6.2650943 | G56: =AVERAGEIFS(G$6:G$49,$B$6:$B$49,$A56) -> 25.060377 | H56: =AVERAGEIFS(H$6:H$49,$B$6:$B$49,$A56) -> 50.120755 | I56: =AVERAGEIFS(I$6:I$49,$B$6:$B$49,$A56) -> 100.24151 | J56: =AVERAGEIFS(J$6:J$49,$B$6:$B$49,$A56) -> 11.841745 | K56: =AVERAGEIFS(K$6:K$49,$B$6:$B$49,$A56) -> 29.604363 | L56: =AVERAGEIFS(L$6:L$49,$B$6:$B$49,$A56) -> 35.525236 | ... P56: =AVERAGEIFS(P$6:P$49,$B$6:$B$49,$A56) -> 12.429953
A57: 2019 | E57: =AVERAGEIFS(E$6:E$49,$B$6:$B$49,$A57) -> 4.3188679 | F57: =AVERAGEIFS(F$6:F$49,$B$6:$B$49,$A57) -> 6.0323113 | G57: =AVERAGEIFS(G$6:G$49,$B$6:$B$49,$A57) -> 24.129245 | H57: =AVERAGEIFS(H$6:H$49,$B$6:$B$49,$A57) -> 48.258491 | I57: =AVERAGEIFS(I$6:I$49,$B$6:$B$49,$A57) -> 96.516981 | J57: =AVERAGEIFS(J$6:J$49,$B$6:$B$49,$A57) -> 12.258726 | K57: =AVERAGEIFS(K$6:K$49,$B$6:$B$49,$A57) -> 30.646816 | L57: =AVERAGEIFS(L$6:L$49,$B$6:$B$49,$A57) -> 36.776179 | ... P57: =AVERAGEIFS(P$6:P$49,$B$6:$B$49,$A57) -> 11.62783
A58: 2020 | E58: =AVERAGEIFS(E$6:E$49,$B$6:$B$49,$A58) -> 4.1856132 | F58: =AVERAGEIFS(F$6:F$49,$B$6:$B$49,$A58) -> 5.9106132 | G58: =AVERAGEIFS(G$6:G$49,$B$6:$B$49,$A58) -> 23.642453 | H58: =AVERAGEIFS(H$6:H$49,$B$6:$B$49,$A58) -> 47.284906 | I58: =AVERAGEIFS(I$6:I$49,$B$6:$B$49,$A58) -> 94.569811 | J58: =AVERAGEIFS(J$6:J$49,$B$6:$B$49,$A58) -> 12.792217 | K58: =AVERAGEIFS(K$6:K$49,$B$6:$B$49,$A58) -> 31.980542 | L58: =AVERAGEIFS(L$6:L$49,$B$6:$B$49,$A58) -> 38.376651 | ... P58: =AVERAGEIFS(P$6:P$49,$B$6:$B$49,$A58) -> 10.94717
A59: 2021 | E59: =AVERAGEIFS(E$6:E$49,$B$6:$B$49,$A59) -> 3.9591981 | F59: =AVERAGEIFS(F$6:F$49,$B$6:$B$49,$A59) -> 5.259434 | G59: =AVERAGEIFS(G$6:G$49,$B$6:$B$49,$A59) -> 21.037736 | H59: =AVERAGEIFS(H$6:H$49,$B$6:$B$49,$A59) -> 42.075472 | I59: =AVERAGEIFS(I$6:I$49,$B$6:$B$49,$A59) -> 84.150943 | J59: =AVERAGEIFS(J$6:J$49,$B$6:$B$49,$A59) -> 13.666509 | K59: =AVERAGEIFS(K$6:K$49,$B$6:$B$49,$A59) -> 34.166274 | L59: =AVERAGEIFS(L$6:L$49,$B$6:$B$49,$A59) -> 40.999528 | ... P59: =AVERAGEIFS(P$6:P$49,$B$6:$B$49,$A59) -> 10.042689
A60: 2022 | E60: =AVERAGEIFS(E$6:E$49,$B$6:$B$49,$A60) -> 3.9938679 | F60: =AVERAGEIFS(F$6:F$49,$B$6:$B$49,$A60) -> 5.4896226 | G60: =AVERAGEIFS(G$6:G$49,$B$6:$B$49,$A60) -> 21.958491 | H60: =AVERAGEIFS(H$6:H$49,$B$6:$B$49,$A60) -> 43.916981 | I60: =AVERAGEIFS(I$6:I$49,$B$6:$B$49,$A60) -> 87.833962 | J60: =AVERAGEIFS(J$6:J$49,$B$6:$B$49,$A60) -> 15.318868 | K60: =AVERAGEIFS(K$6:K$49,$B$6:$B$49,$A60) -> 38.29717 | L60: =AVERAGEIFS(L$6:L$49,$B$6:$B$49,$A60) -> 45.956604 | ... P60: =AVERAGEIFS(P$6:P$49,$B$6:$B$49,$A60) -> 10.465566
A61: 2023 | E61: =AVERAGEIFS(E$6:E$49,$B$6:$B$49,$A61) -> 3.745283 | F61: =AVERAGEIFS(F$6:F$49,$B$6:$B$49,$A61) -> 5.2183962 | G61: =AVERAGEIFS(G$6:G$49,$B$6:$B$49,$A61) -> 20.873585 | H61: =AVERAGEIFS(H$6:H$49,$B$6:$B$49,$A61) -> 41.74717 | I61: =AVERAGEIFS(I$6:I$49,$B$6:$B$49,$A61) -> 83.49434 | J61: =AVERAGEIFS(J$6:J$49,$B$6:$B$49,$A61) -> 16.740094 | K61: =AVERAGEIFS(K$6:K$49,$B$6:$B$49,$A61) -> 41.850236 | L61: =AVERAGEIFS(L$6:L$49,$B$6:$B$49,$A61) -> 50.220283 | ... P61: =AVERAGEIFS(P$6:P$49,$B$6:$B$49,$A61) -> 11.233726
A62: 2024 | E62: =AVERAGEIFS(E$6:E$49,$B$6:$B$49,$A62) -> 2.6330189 | F62: =AVERAGEIFS(F$6:F$49,$B$6:$B$49,$A62) -> 6.5287736 | G62: =AVERAGEIFS(G$6:G$49,$B$6:$B$49,$A62) -> 26.115094 | H62: =AVERAGEIFS(H$6:H$49,$B$6:$B$49,$A62) -> 52.230189 | I62: =AVERAGEIFS(I$6:I$49,$B$6:$B$49,$A62) -> 104.46038 | J62: =AVERAGEIFS(J$6:J$49,$B$6:$B$49,$A62) -> 17.81934 | K62: =AVERAGEIFS(K$6:K$49,$B$6:$B$49,$A62) -> 44.548349 | L62: =AVERAGEIFS(L$6:L$49,$B$6:$B$49,$A62) -> 53.458019 | ... P62: =AVERAGEIFS(P$6:P$49,$B$6:$B$49,$A62) -> 9.6893868
A63: 2025 | E63: =AVERAGEIFS(E$6:E$49,$B$6:$B$49,$A63) -> 1.8641509 | F63: =AVERAGEIFS(F$6:F$49,$B$6:$B$49,$A63) -> 5.8254717 | G63: =AVERAGEIFS(G$6:G$49,$B$6:$B$49,$A63) -> 23.301887 | H63: =AVERAGEIFS(H$6:H$49,$B$6:$B$49,$A63) -> 46.603774 | I63: =AVERAGEIFS(I$6:I$49,$B$6:$B$49,$A63) -> 93.207547 | J63: =AVERAGEIFS(J$6:J$49,$B$6:$B$49,$A63) -> 19.818868 | K63: =AVERAGEIFS(K$6:K$49,$B$6:$B$49,$A63) -> 49.54717 | L63: =AVERAGEIFS(L$6:L$49,$B$6:$B$49,$A63) -> 59.456604 | ... P63: =AVERAGEIFS(P$6:P$49,$B$6:$B$49,$A63) -> 8.7924528
A64: 2026 | E64: =AVERAGEIFS(E$6:E$49,$B$6:$B$49,$A64) -> 1.8566038 | F64: =AVERAGEIFS(F$6:F$49,$B$6:$B$49,$A64) -> 5.8018868 | G64: =AVERAGEIFS(G$6:G$49,$B$6:$B$49,$A64) -> 23.207547 | H64: =AVERAGEIFS(H$6:H$49,$B$6:$B$49,$A64) -> 46.415094 | I64: =AVERAGEIFS(I$6:I$49,$B$6:$B$49,$A64) -> 92.830189 | J64: =AVERAGEIFS(J$6:J$49,$B$6:$B$49,$A64) -> 21.322406 | K64: =AVERAGEIFS(K$6:K$49,$B$6:$B$49,$A64) -> 53.306014 | L64: =AVERAGEIFS(L$6:L$49,$B$6:$B$49,$A64) -> 63.967217 | ... P64: =AVERAGEIFS(P$6:P$49,$B$6:$B$49,$A64) -> 8.9056604

Sheet ASP_growth
A1: ASP growth: peaks, changes and CAGRs per vial
A2: All values look up ASP_per_vial. Row 4 holds the quarter looked up in each column; row 3 its quarter index.
A3: Quarter index | B3: =INDEX(CMS_PL!$D$6:$D$49,MATCH(B4,CMS_PL!$A$6:$A$49,0)) -> 2016 | C3: =INDEX(CMS_PL!$D$6:$D$49,MATCH(C4,CMS_PL!$A$6:$A$49,0)) -> 2018.5 | D3: =INDEX(CMS_PL!$D$6:$D$49,MATCH(D4,CMS_PL!$A$6:$A$49,0)) -> 2021.75 | E3: =INDEX(CMS_PL!$D$6:$D$49,MATCH(E4,CMS_PL!$A$6:$A$49,0)) -> 2023.75 | F3: =INDEX(CMS_PL!$D$6:$D$49,MATCH(F4,CMS_PL!$A$6:$A$49,0)) -> 2024 | G3: =INDEX(CMS_PL!$D$6:$D$49,MATCH(G4,CMS_PL!$A$6:$A$49,0)) -> 2024.25 | H3: =INDEX(CMS_PL!$D$6:$D$49,MATCH(H4,CMS_PL!$A$6:$A$49,0)) -> 2025.75 | I3: =INDEX(CMS_PL!$D$6:$D$49,MATCH(I4,CMS_PL!$A$6:$A$49,0)) -> 2026.75
A4: Quarter looked up | B4: 2016-Q1 | C4: 2018-Q3 | D4: 2021-Q4 | E4: 2023-Q4 | F4: 2024-Q1 | G4: 2024-Q2 | H4: 2025-Q4 | I4: 2026-Q4
A5: Vial | B5: ASP 2016-Q1 | C5: ASP 2018-Q3 | D5: ASP 2021-Q4 | E5: ASP 2023-Q4 | F5: ASP 2024-Q1 | G5: ASP 2024-Q2 | H5: ASP 2025-Q4 | I5: ASP 2026-Q4 | J5: Peak ASP | K5: Peak quarter | L5: 1y change (Q4'25 to Q4'26) | M5: 3y CAGR (Q4'23 to Q4'26) | N5: 5y CAGR (Q4'21 to Q4'26) | O5: CAGR Q1'16 to Q4'26 | P5: Change Q1'16 to Q3'18 | Q5: Change Q2'24 to Q4'26 (new code) | R5: Note | S5: Peak, old code (to Q1 2024) | T5: Quarter of old-code peak | U5: Peak, new code (from Q2 2024) | V5: Quarter of new-code peak
A6: MPSS 40 mg | B6: =INDEX(ASP_per_vial!$E$6:$P$49,MATCH(B$4,ASP_per_vial!$A$6:$A$49,0),MATCH($A6,ASP_per_vial!$E$5:$P$5,0)) -> 2.7339623 | C6: =INDEX(ASP_per_vial!$E$6:$P$49,MATCH(C$4,ASP_per_vial!$A$6:$A$49,0),MATCH($A6,ASP_per_vial!$E$5:$P$5,0)) -> 4.5330189 | D6: =INDEX(ASP_per_vial!$E$6:$P$49,MATCH(D$4,ASP_per_vial!$A$6:$A$49,0),MATCH($A6,ASP_per_vial!$E$5:$P$5,0)) -> 3.8754717 | E6: =INDEX(ASP_per_vial!$E$6:$P$49,MATCH(E$4,ASP_per_vial!$A$6:$A$49,0),MATCH($A6,ASP_per_vial!$E$5:$P$5,0)) -> 3.2386792 | F6: =INDEX(ASP_per_vial!$E$6:$P$49,MATCH(F$4,ASP_per_vial!$A$6:$A$49,0),MATCH($A6,ASP_per_vial!$E$5:$P$5,0)) -> 3.9509434 | G6: =INDEX(ASP_per_vial!$E$6:$P$49,MATCH(G$4,ASP_per_vial!$A$6:$A$49,0),MATCH($A6,ASP_per_vial!$E$5:$P$5,0)) -> 2.0603774 | H6: =INDEX(ASP_per_vial!$E$6:$P$49,MATCH(H$4,ASP_per_vial!$A$6:$A$49,0),MATCH($A6,ASP_per_vial!$E$5:$P$5,0)) -> 1.5849057 | I6: =INDEX(ASP_per_vial!$E$6:$P$49,MATCH(I$4,ASP_per_vial!$A$6:$A$49,0),MATCH($A6,ASP_per_vial!$E$5:$P$5,0)) -> 1.9245283 | J6: =MAX(INDEX(ASP_per_vial!$E$6:$P$49,0,MATCH($A6,ASP_per_vial!$E$5:$P$5,0))) -> 4.5962264 | K6: =INDEX(ASP_per_vial!$A$6:$A$49,MATCH(J6,INDEX(ASP_per_vial!$E$6:$P$49,0,MATCH($A6,ASP_per_vial!$E$5:$P$5,0)),0)) -> 2019-Q1 | L6: =I6/H6-1 -> 0.21428571 | M6: =(I6/E6)^(1/(I$3-E$3))-1 -> -0.15927856 | N6: =(I6/D6)^(1/(I$3-D$3))-1 -> -0.13063941 | O6: =(I6/B6)^(1/(I$3-B$3))-1 -> -0.032130264 | P6: =C6/B6-1 -> 0.65804003 | Q6: =I6/G6-1 -> -0.065934066 | R6: Windows before Q2 2024 cross the code change | S6: =_xlfn.MAXIFS(INDEX(ASP_per_vial!$E$6:$P$49,0,MATCH($A6,ASP_per_vial!$E$5:$P$5,0)),ASP_per_vial!$C$6:$C$49,"<"&Assumptions!$B$8) -> 4.5962264 | T6: =INDEX(ASP_per_vial!$A$6:$A$49,MATCH(S6,INDEX(ASP_per_vial!$E$6:$P$49,0,MATCH($A6,ASP_per_vial!$E$5:$P$5,0)),0)) -> 2019-Q1 | U6: =_xlfn.MAXIFS(INDEX(ASP_per_vial!$E$6:$P$49,0,MATCH($A6,ASP_per_vial!$E$5:$P$5,0)),ASP_per_vial!$C$6:$C$49,">="&Assumptions!$B$8) -> 2.2943396 | V6: =INDEX(ASP_per_vial!$A$6:$A$49,MATCH(U6,INDEX(ASP_per_vial!$E$6:$P$49,0,MATCH($A6,ASP_per_vial!$E$5:$P$5,0)),0)) -> 2024-Q4
A7: MPSS 125 mg | B7: =INDEX(ASP_per_vial!$E$6:$P$49,MATCH(B$4,ASP_per_vial!$A$6:$A$49,0),MATCH($A7,ASP_per_vial!$E$5:$P$5,0)) -> 3.8726415 | C7: =INDEX(ASP_per_vial!$E$6:$P$49,MATCH(C$4,ASP_per_vial!$A$6:$A$49,0),MATCH($A7,ASP_per_vial!$E$5:$P$5,0)) -> 6.5707547 | D7: =INDEX(ASP_per_vial!$E$6:$P$49,MATCH(D$4,ASP_per_vial!$A$6:$A$49,0),MATCH($A7,ASP_per_vial!$E$5:$P$5,0)) -> 5.25 | E7: =INDEX(ASP_per_vial!$E$6:$P$49,MATCH(E$4,ASP_per_vial!$A$6:$A$49,0),MATCH($A7,ASP_per_vial!$E$5:$P$5,0)) -> 4.7028302 | F7: =INDEX(ASP_per_vial!$E$6:$P$49,MATCH(F$4,ASP_per_vial!$A$6:$A$49,0),MATCH($A7,ASP_per_vial!$E$5:$P$5,0)) -> 5.5490566 | G7: =INDEX(ASP_per_vial!$E$6:$P$49,MATCH(G$4,ASP_per_vial!$A$6:$A$49,0),MATCH($A7,ASP_per_vial!$E$5:$P$5,0)) -> 6.4386792 | H7: =INDEX(ASP_per_vial!$E$6:$P$49,MATCH(H$4,ASP_per_vial!$A$6:$A$49,0),MATCH($A7,ASP_per_vial!$E$5:$P$5,0)) -> 4.9528302 | I7: =INDEX(ASP_per_vial!$E$6:$P$49,MATCH(I$4,ASP_per_vial!$A$6:$A$49,0),MATCH($A7,ASP_per_vial!$E$5:$P$5,0)) -> 6.0141509 | J7: =MAX(INDEX(ASP_per_vial!$E$6:$P$49,0,MATCH($A7,ASP_per_vial!$E$5:$P$5,0))) -> 7.1698113 | K7: =INDEX(ASP_per_vial!$A$6:$A$49,MATCH(J7,INDEX(ASP_per_vial!$E$6:$P$49,0,MATCH($A7,ASP_per_vial!$E$5:$P$5,0)),0)) -> 2024-Q4 | L7: =I7/H7-1 -> 0.21428571 | M7: =(I7/E7)^(1/(I$3-E$3))-1 -> 0.085437968 | N7: =(I7/D7)^(1/(I$3-D$3))-1 -> 0.027550096 | O7: =(I7/B7)^(1/(I$3-B$3))-1 -> 0.041796705 | P7: =C7/B7-1 -> 0.69671133 | Q7: =I7/G7-1 -> -0.065934066 | R7: Windows before Q2 2024 cross the code change | S7: =_xlfn.MAXIFS(INDEX(ASP_per_vial!$E$6:$P$49,0,MATCH($A7,ASP_per_vial!$E$5:$P$5,0)),ASP_per_vial!$C$6:$C$49,"<"&Assumptions!$B$8) -> 6.5707547 | T7: =INDEX(ASP_per_vial!$A$6:$A$49,MATCH(S7,INDEX(ASP_per_vial!$E$6:$P$49,0,MATCH($A7,ASP_per_vial!$E$5:$P$5,0)),0)) -> 2018-Q3 | U7: =_xlfn.MAXIFS(INDEX(ASP_per_vial!$E$6:$P$49,0,MATCH($A7,ASP_per_vial!$E$5:$P$5,0)),ASP_per_vial!$C$6:$C$49,">="&Assumptions!$B$8) -> 7.1698113 | V7: =INDEX(ASP_per_vial!$A$6:$A$49,MATCH(U7,INDEX(ASP_per_vial!$E$6:$P$49,0,MATCH($A7,ASP_per_vial!$E$5:$P$5,0)),0)) -> 2024-Q4
A8: MPSS 500 mg | B8: =INDEX(ASP_per_vial!$E$6:$P$49,MATCH(B$4,ASP_per_vial!$A$6:$A$49,0),MATCH($A8,ASP_per_vial!$E$5:$P$5,0)) -> 15.490566 | C8: =INDEX(ASP_per_vial!$E$6:$P$49,MATCH(C$4,ASP_per_vial!$A$6:$A$49,0),MATCH($A8,ASP_per_vial!$E$5:$P$5,0)) -> 26.283019 | D8: =INDEX(ASP_per_vial!$E$6:$P$49,MATCH(D$4,ASP_per_vial!$A$6:$A$49,0),MATCH($A8,ASP_per_vial!$E$5:$P$5,0)) -> 21 | E8: =INDEX(ASP_per_vial!$E$6:$P$49,MATCH(E$4,ASP_per_vial!$A$6:$A$49,0),MATCH($A8,ASP_per_vial!$E$5:$P$5,0)) -> 18.811321 | F8: =INDEX(ASP_per_vial!$E$6:$P$49,MATCH(F$4,ASP_per_vial!$A$6:$A$49,0),MATCH($A8,ASP_per_vial!$E$5:$P$5,0)) -> 22.196226 | G8: =INDEX(ASP_per_vial!$E$6:$P$49,MATCH(G$4,ASP_per_vial!$A$6:$A$49,0),MATCH($A8,ASP_per_vial!$E$5:$P$5,0)) -> 25.754717 | H8: =INDEX(ASP_per_vial!$E$6:$P$49,MATCH(H$4,ASP_per_vial!$A$6:$A$49,0),MATCH($A8,ASP_per_vial!$E$5:$P$5,0)) -> 19.811321 | I8: =INDEX(ASP_per_vial!$E$6:$P$49,MATCH(I$4,ASP_per_vial!$A$6:$A$49,0),MATCH($A8,ASP_per_vial!$E$5:$P$5,0)) -> 24.056604 | J8: =MAX(INDEX(ASP_per_vial!$E$6:$P$49,0,MATCH($A8,ASP_per_vial!$E$5:$P$5,0))) -> 28.679245 | K8: =INDEX(ASP_per_vial!$A$6:$A$49,MATCH(J8,INDEX(ASP_per_vial!$E$6:$P$49,0,MATCH($A8,ASP_per_vial!$E$5:$P$5,0)),0)) -> 2024-Q4 | L8: =I8/H8-1 -> 0.21428571 | M8: =(I8/E8)^(1/(I$3-E$3))-1 -> 0.085437968 | N8: =(I8/D8)^(1/(I$3-D$3))-1 -> 0.027550096 | O8: =(I8/B8)^(1/(I$3-B$3))-1 -> 0.041796705 | P8: =C8/B8-1 -> 0.69671133 | Q8: =I8/G8-1 -> -0.065934066 | R8: Windows before Q2 2024 cross the code change | S8: =_xlfn.MAXIFS(INDEX(ASP_per_vial!$E$6:$P$49,0,MATCH($A8,ASP_per_vial!$E$5:$P$5,0)),ASP_per_vial!$C$6:$C$49,"<"&Assumptions!$B$8) -> 26.283019 | T8: =INDEX(ASP_per_vial!$A$6:$A$49,MATCH(S8,INDEX(ASP_per_vial!$E$6:$P$49,0,MATCH($A8,ASP_per_vial!$E$5:$P$5,0)),0)) -> 2018-Q3 | U8: =_xlfn.MAXIFS(INDEX(ASP_per_vial!$E$6:$P$49,0,MATCH($A8,ASP_per_vial!$E$5:$P$5,0)),ASP_per_vial!$C$6:$C$49,">="&Assumptions!$B$8) -> 28.679245 | V8: =INDEX(ASP_per_vial!$A$6:$A$49,MATCH(U8,INDEX(ASP_per_vial!$E$6:$P$49,0,MATCH($A8,ASP_per_vial!$E$5:$P$5,0)),0)) -> 2024-Q4
A9: MPSS 1 g | B9: =INDEX(ASP_per_vial!$E$6:$P$49,MATCH(B$4,ASP_per_vial!$A$6:$A$49,0),MATCH($A9,ASP_per_vial!$E$5:$P$5,0)) -> 30.981132 | C9: =INDEX(ASP_per_vial!$E$6:$P$49,MATCH(C$4,ASP_per_vial!$A$6:$A$49,0),MATCH($A9,ASP_per_vial!$E$5:$P$5,0)) -> 52.566038 | D9: =INDEX(ASP_per_vial!$E$6:$P$49,MATCH(D$4,ASP_per_vial!$A$6:$A$49,0),MATCH($A9,ASP_per_vial!$E$5:$P$5,0)) -> 42 | E9: =INDEX(ASP_per_vial!$E$6:$P$49,MATCH(E$4,ASP_per_vial!$A$6:$A$49,0),MATCH($A9,ASP_per_vial!$E$5:$P$5,0)) -> 37.622642 | F9: =INDEX(ASP_per_vial!$E$6:$P$49,MATCH(F$4,ASP_per_vial!$A$6:$A$49,0),MATCH($A9,ASP_per_vial!$E$5:$P$5,0)) -> 44.392453 | G9: =INDEX(ASP_per_vial!$E$6:$P$49,MATCH(G$4,ASP_per_vial!$A$6:$A$49,0),MATCH($A9,ASP_per_vial!$E$5:$P$5,0)) -> 51.509434 | H9: =INDEX(ASP_per_vial!$E$6:$P$49,MATCH(H$4,ASP_per_vial!$A$6:$A$49,0),MATCH($A9,ASP_per_vial!$E$5:$P$5,0)) -> 39.622642 | I9: =INDEX(ASP_per_vial!$E$6:$P$49,MATCH(I$4,ASP_per_vial!$A$6:$A$49,0),MATCH($A9,ASP_per_vial!$E$5:$P$5,0)) -> 48.113208 | J9: =MAX(INDEX(ASP_per_vial!$E$6:$P$49,0,MATCH($A9,ASP_per_vial!$E$5:$P$5,0))) -> 57.358491 | K9: =INDEX(ASP_per_vial!$A$6:$A$49,MATCH(J9,INDEX(ASP_per_vial!$E$6:$P$49,0,MATCH($A9,ASP_per_vial!$E$5:$P$5,0)),0)) -> 2024-Q4 | L9: =I9/H9-1 -> 0.21428571 | M9: =(I9/E9)^(1/(I$3-E$3))-1 -> 0.085437968 | N9: =(I9/D9)^(1/(I$3-D$3))-1 -> 0.027550096 | O9: =(I9/B9)^(1/(I$3-B$3))-1 -> 0.041796705 | P9: =C9/B9-1 -> 0.69671133 | Q9: =I9/G9-1 -> -0.065934066 | R9: Windows before Q2 2024 cross the code change | S9: =_xlfn.MAXIFS(INDEX(ASP_per_vial!$E$6:$P$49,0,MATCH($A9,ASP_per_vial!$E$5:$P$5,0)),ASP_per_vial!$C$6:$C$49,"<"&Assumptions!$B$8) -> 52.566038 | T9: =INDEX(ASP_per_vial!$A$6:$A$49,MATCH(S9,INDEX(ASP_per_vial!$E$6:$P$49,0,MATCH($A9,ASP_per_vial!$E$5:$P$5,0)),0)) -> 2018-Q3 | U9: =_xlfn.MAXIFS(INDEX(ASP_per_vial!$E$6:$P$49,0,MATCH($A9,ASP_per_vial!$E$5:$P$5,0)),ASP_per_vial!$C$6:$C$49,">="&Assumptions!$B$8) -> 57.358491 | V9: =INDEX(ASP_per_vial!$A$6:$A$49,MATCH(U9,INDEX(ASP_per_vial!$E$6:$P$49,0,MATCH($A9,ASP_per_vial!$E$5:$P$5,0)),0)) -> 2024-Q4
A10: MPSS 2 g | B10: =INDEX(ASP_per_vial!$E$6:$P$49,MATCH(B$4,ASP_per_vial!$A$6:$A$49,0),MATCH($A10,ASP_per_vial!$E$5:$P$5,0)) -> 61.962264 | C10: =INDEX(ASP_per_vial!$E$6:$P$49,MATCH(C$4,ASP_per_vial!$A$6:$A$49,0),MATCH($A10,ASP_per_vial!$E$5:$P$5,0)) -> 105.13208 | D10: =INDEX(ASP_per_vial!$E$6:$P$49,MATCH(D$4,ASP_per_vial!$A$6:$A$49,0),MATCH($A10,ASP_per_vial!$E$5:$P$5,0)) -> 84 | E10: =INDEX(ASP_per_vial!$E$6:$P$49,MATCH(E$4,ASP_per_vial!$A$6:$A$49,0),MATCH($A10,ASP_per_vial!$E$5:$P$5,0)) -> 75.245283 | F10: =INDEX(ASP_per_vial!$E$6:$P$49,MATCH(F$4,ASP_per_vial!$A$6:$A$49,0),MATCH($A10,ASP_per_vial!$E$5:$P$5,0)) -> 88.784906 | G10: =INDEX(ASP_per_vial!$E$6:$P$49,MATCH(G$4,ASP_per_vial!$A$6:$A$49,0),MATCH($A10,ASP_per_vial!$E$5:$P$5,0)) -> 103.01887 | H10: =INDEX(ASP_per_vial!$E$6:$P$49,MATCH(H$4,ASP_per_vial!$A$6:$A$49,0),MATCH($A10,ASP_per_vial!$E$5:$P$5,0)) -> 79.245283 | I10: =INDEX(ASP_per_vial!$E$6:$P$49,MATCH(I$4,ASP_per_vial!$A$6:$A$49,0),MATCH($A10,ASP_per_vial!$E$5:$P$5,0)) -> 96.226415 | J10: =MAX(INDEX(ASP_per_vial!$E$6:$P$49,0,MATCH($A10,ASP_per_vial!$E$5:$P$5,0))) -> 114.71698 | K10: =INDEX(ASP_per_vial!$A$6:$A$49,MATCH(J10,INDEX(ASP_per_vial!$E$6:$P$49,0,MATCH($A10,ASP_per_vial!$E$5:$P$5,0)),0)) -> 2024-Q4 | L10: =I10/H10-1 -> 0.21428571 | M10: =(I10/E10)^(1/(I$3-E$3))-1 -> 0.085437968 | N10: =(I10/D10)^(1/(I$3-D$3))-1 -> 0.027550096 | O10: =(I10/B10)^(1/(I$3-B$3))-1 -> 0.041796705 | P10: =C10/B10-1 -> 0.69671133 | Q10: =I10/G10-1 -> -0.065934066 | R10: Windows before Q2 2024 cross the code change | S10: =_xlfn.MAXIFS(INDEX(ASP_per_vial!$E$6:$P$49,0,MATCH($A10,ASP_per_vial!$E$5:$P$5,0)),ASP_per_vial!$C$6:$C$49,"<"&Assumptions!$B$8) -> 105.13208 | T10: =INDEX(ASP_per_vial!$A$6:$A$49,MATCH(S10,INDEX(ASP_per_vial!$E$6:$P$49,0,MATCH($A10,ASP_per_vial!$E$5:$P$5,0)),0)) -> 2018-Q3 | U10: =_xlfn.MAXIFS(INDEX(ASP_per_vial!$E$6:$P$49,0,MATCH($A10,ASP_per_vial!$E$5:$P$5,0)),ASP_per_vial!$C$6:$C$49,">="&Assumptions!$B$8) -> 114.71698 | V10: =INDEX(ASP_per_vial!$A$6:$A$49,MATCH(U10,INDEX(ASP_per_vial!$E$6:$P$49,0,MATCH($A10,ASP_per_vial!$E$5:$P$5,0)),0)) -> 2024-Q4
A11: HSS 100 mg | B11: =INDEX(ASP_per_vial!$E$6:$P$49,MATCH(B$4,ASP_per_vial!$A$6:$A$49,0),MATCH($A11,ASP_per_vial!$E$5:$P$5,0)) -> 7.0773585 | C11: =INDEX(ASP_per_vial!$E$6:$P$49,MATCH(C$4,ASP_per_vial!$A$6:$A$49,0),MATCH($A11,ASP_per_vial!$E$5:$P$5,0)) -> 12.431132 | D11: =INDEX(ASP_per_vial!$E$6:$P$49,MATCH(D$4,ASP_per_vial!$A$6:$A$49,0),MATCH($A11,ASP_per_vial!$E$5:$P$5,0)) -> 13.972642 | E11: =INDEX(ASP_per_vial!$E$6:$P$49,MATCH(E$4,ASP_per_vial!$A$6:$A$49,0),MATCH($A11,ASP_per_vial!$E$5:$P$5,0)) -> 16.671698 | F11: =INDEX(ASP_per_vial!$E$6:$P$49,MATCH(F$4,ASP_per_vial!$A$6:$A$49,0),MATCH($A11,ASP_per_vial!$E$5:$P$5,0)) -> 16.834906 | G11: =INDEX(ASP_per_vial!$E$6:$P$49,MATCH(G$4,ASP_per_vial!$A$6:$A$49,0),MATCH($A11,ASP_per_vial!$E$5:$P$5,0)) -> 17.414151 | H11: =INDEX(ASP_per_vial!$E$6:$P$49,MATCH(H$4,ASP_per_vial!$A$6:$A$49,0),MATCH($A11,ASP_per_vial!$E$5:$P$5,0)) -> 20.10566 | I11: =INDEX(ASP_per_vial!$E$6:$P$49,MATCH(I$4,ASP_per_vial!$A$6:$A$49,0),MATCH($A11,ASP_per_vial!$E$5:$P$5,0)) -> 21.838679 | J11: =MAX(INDEX(ASP_per_vial!$E$6:$P$49,0,MATCH($A11,ASP_per_vial!$E$5:$P$5,0))) -> 21.838679 | K11: =INDEX(ASP_per_vial!$A$6:$A$49,MATCH(J11,INDEX(ASP_per_vial!$E$6:$P$49,0,MATCH($A11,ASP_per_vial!$E$5:$P$5,0)),0)) -> 2026-Q4 | L11: =I11/H11-1 -> 0.086195571 | M11: =(I11/E11)^(1/(I$3-E$3))-1 -> 0.094163385 | N11: =(I11/D11)^(1/(I$3-D$3))-1 -> 0.093426438 | O11: =(I11/B11)^(1/(I$3-B$3))-1 -> 0.11050728 | P11: =C11/B11-1 -> 0.75646494 | Q11: =I11/G11-1 -> 0.2540766 | S11: =_xlfn.MAXIFS(INDEX(ASP_per_vial!$E$6:$P$49,0,MATCH($A11,ASP_per_vial!$E$5:$P$5,0)),ASP_per_vial!$C$6:$C$49,"<"&Assumptions!$B$8) -> 16.89717 | T11: =INDEX(ASP_per_vial!$A$6:$A$49,MATCH(S11,INDEX(ASP_per_vial!$E$6:$P$49,0,MATCH($A11,ASP_per_vial!$E$5:$P$5,0)),0)) -> 2023-Q2 | U11: =_xlfn.MAXIFS(INDEX(ASP_per_vial!$E$6:$P$49,0,MATCH($A11,ASP_per_vial!$E$5:$P$5,0)),ASP_per_vial!$C$6:$C$49,">="&Assumptions!$B$8) -> 21.838679 | V11: =INDEX(ASP_per_vial!$A$6:$A$49,MATCH(U11,INDEX(ASP_per_vial!$E$6:$P$49,0,MATCH($A11,ASP_per_vial!$E$5:$P$5,0)),0)) -> 2026-Q4
A12: HSS 250 mg (2.5 units) | B12: =INDEX(ASP_per_vial!$E$6:$P$49,MATCH(B$4,ASP_per_vial!$A$6:$A$49,0),MATCH($A12,ASP_per_vial!$E$5:$P$5,0)) -> 17.693396 | C12: =INDEX(ASP_per_vial!$E$6:$P$49,MATCH(C$4,ASP_per_vial!$A$6:$A$49,0),MATCH($A12,ASP_per_vial!$E$5:$P$5,0)) -> 31.07783 | D12: =INDEX(ASP_per_vial!$E$6:$P$49,MATCH(D$4,ASP_per_vial!$A$6:$A$49,0),MATCH($A12,ASP_per_vial!$E$5:$P$5,0)) -> 34.931604 | E12: =INDEX(ASP_per_vial!$E$6:$P$49,MATCH(E$4,ASP_per_vial!$A$6:$A$49,0),MATCH($A12,ASP_per_vial!$E$5:$P$5,0)) -> 41.679245 | F12: =INDEX(ASP_per_vial!$E$6:$P$49,MATCH(F$4,ASP_per_vial!$A$6:$A$49,0),MATCH($A12,ASP_per_vial!$E$5:$P$5,0)) -> 42.087264 | G12: =INDEX(ASP_per_vial!$E$6:$P$49,MATCH(G$4,ASP_per_vial!$A$6:$A$49,0),MATCH($A12,ASP_per_vial!$E$5:$P$5,0)) -> 43.535377 | H12: =INDEX(ASP_per_vial!$E$6:$P$49,MATCH(H$4,ASP_per_vial!$A$6:$A$49,0),MATCH($A12,ASP_per_vial!$E$5:$P$5,0)) -> 50.264151 | I12: =INDEX(ASP_per_vial!$E$6:$P$49,MATCH(I$4,ASP_per_vial!$A$6:$A$49,0),MATCH($A12,ASP_per_vial!$E$5:$P$5,0)) -> 54.596698 | J12: =MAX(INDEX(ASP_per_vial!$E$6:$P$49,0,MATCH($A12,ASP_per_vial!$E$5:$P$5,0))) -> 54.596698 | K12: =INDEX(ASP_per_vial!$A$6:$A$49,MATCH(J12,INDEX(ASP_per_vial!$E$6:$P$49,0,MATCH($A12,ASP_per_vial!$E$5:$P$5,0)),0)) -> 2026-Q4 | L12: =I12/H12-1 -> 0.086195571 | M12: =(I12/E12)^(1/(I$3-E$3))-1 -> 0.094163385 | N12: =(I12/D12)^(1/(I$3-D$3))-1 -> 0.093426438 | O12: =(I12/B12)^(1/(I$3-B$3))-1 -> 0.11050728 | P12: =C12/B12-1 -> 0.75646494 | Q12: =I12/G12-1 -> 0.2540766 | S12: =_xlfn.MAXIFS(INDEX(ASP_per_vial!$E$6:$P$49,0,MATCH($A12,ASP_per_vial!$E$5:$P$5,0)),ASP_per_vial!$C$6:$C$49,"<"&Assumptions!$B$8) -> 42.242925 | T12: =INDEX(ASP_per_vial!$A$6:$A$49,MATCH(S12,INDEX(ASP_per_vial!$E$6:$P$49,0,MATCH($A12,ASP_per_vial!$E$5:$P$5,0)),0)) -> 2023-Q2 | U12: =_xlfn.MAXIFS(INDEX(ASP_per_vial!$E$6:$P$49,0,MATCH($A12,ASP_per_vial!$E$5:$P$5,0)),ASP_per_vial!$C$6:$C$49,">="&Assumptions!$B$8) -> 54.596698 | V12: =INDEX(ASP_per_vial!$A$6:$A$49,MATCH(U12,INDEX(ASP_per_vial!$E$6:$P$49,0,MATCH($A12,ASP_per_vial!$E$5:$P$5,0)),0)) -> 2026-Q4
A13: HSS 250 mg (3 units) | B13: =INDEX(ASP_per_vial!$E$6:$P$49,MATCH(B$4,ASP_per_vial!$A$6:$A$49,0),MATCH($A13,ASP_per_vial!$E$5:$P$5,0)) -> 21.232075 | C13: =INDEX(ASP_per_vial!$E$6:$P$49,MATCH(C$4,ASP_per_vial!$A$6:$A$49,0),MATCH($A13,ASP_per_vial!$E$5:$P$5,0)) -> 37.293396 | D13: =INDEX(ASP_per_vial!$E$6:$P$49,MATCH(D$4,ASP_per_vial!$A$6:$A$49,0),MATCH($A13,ASP_per_vial!$E$5:$P$5,0)) -> 41.917925 | E13: =INDEX(ASP_per_vial!$E$6:$P$49,MATCH(E$4,ASP_per_vial!$A$6:$A$49,0),MATCH($A13,ASP_per_vial!$E$5:$P$5,0)) -> 50.015094 | F13: =INDEX(ASP_per_vial!$E$6:$P$49,MATCH(F$4,ASP_per_vial!$A$6:$A$49,0),MATCH($A13,ASP_per_vial!$E$5:$P$5,0)) -> 50.504717 | G13: =INDEX(ASP_per_vial!$E$6:$P$49,MATCH(G$4,ASP_per_vial!$A$6:$A$49,0),MATCH($A13,ASP_per_vial!$E$5:$P$5,0)) -> 52.242453 | H13: =INDEX(ASP_per_vial!$E$6:$P$49,MATCH(H$4,ASP_per_vial!$A$6:$A$49,0),MATCH($A13,ASP_per_vial!$E$5:$P$5,0)) -> 60.316981 | I13: =INDEX(ASP_per_vial!$E$6:$P$49,MATCH(I$4,ASP_per_vial!$A$6:$A$49,0),MATCH($A13,ASP_per_vial!$E$5:$P$5,0)) -> 65.516038 | J13: =MAX(INDEX(ASP_per_vial!$E$6:$P$49,0,MATCH($A13,ASP_per_vial!$E$5:$P$5,0))) -> 65.516038 | K13: =INDEX(ASP_per_vial!$A$6:$A$49,MATCH(J13,INDEX(ASP_per_vial!$E$6:$P$49,0,MATCH($A13,ASP_per_vial!$E$5:$P$5,0)),0)) -> 2026-Q4 | L13: =I13/H13-1 -> 0.086195571 | M13: =(I13/E13)^(1/(I$3-E$3))-1 -> 0.094163385 | N13: =(I13/D13)^(1/(I$3-D$3))-1 -> 0.093426438 | O13: =(I13/B13)^(1/(I$3-B$3))-1 -> 0.11050728 | P13: =C13/B13-1 -> 0.75646494 | Q13: =I13/G13-1 -> 0.2540766 | S13: =_xlfn.MAXIFS(INDEX(ASP_per_vial!$E$6:$P$49,0,MATCH($A13,ASP_per_vial!$E$5:$P$5,0)),ASP_per_vial!$C$6:$C$49,"<"&Assumptions!$B$8) -> 50.691509 | T13: =INDEX(ASP_per_vial!$A$6:$A$49,MATCH(S13,INDEX(ASP_per_vial!$E$6:$P$49,0,MATCH($A13,ASP_per_vial!$E$5:$P$5,0)),0)) -> 2023-Q2 | U13: =_xlfn.MAXIFS(INDEX(ASP_per_vial!$E$6:$P$49,0,MATCH($A13,ASP_per_vial!$E$5:$P$5,0)),ASP_per_vial!$C$6:$C$49,">="&Assumptions!$B$8) -> 65.516038 | V13: =INDEX(ASP_per_vial!$A$6:$A$49,MATCH(U13,INDEX(ASP_per_vial!$E$6:$P$49,0,MATCH($A13,ASP_per_vial!$E$5:$P$5,0)),0)) -> 2026-Q4
A14: HSS 500 mg | B14: =INDEX(ASP_per_vial!$E$6:$P$49,MATCH(B$4,ASP_per_vial!$A$6:$A$49,0),MATCH($A14,ASP_per_vial!$E$5:$P$5,0)) -> 35.386792 | C14: =INDEX(ASP_per_vial!$E$6:$P$49,MATCH(C$4,ASP_per_vial!$A$6:$A$49,0),MATCH($A14,ASP_per_vial!$E$5:$P$5,0)) -> 62.15566 | D14: =INDEX(ASP_per_vial!$E$6:$P$49,MATCH(D$4,ASP_per_vial!$A$6:$A$49,0),MATCH($A14,ASP_per_vial!$E$5:$P$5,0)) -> 69.863208 | E14: =INDEX(ASP_per_vial!$E$6:$P$49,MATCH(E$4,ASP_per_vial!$A$6:$A$49,0),MATCH($A14,ASP_per_vial!$E$5:$P$5,0)) -> 83.358491 | F14: =INDEX(ASP_per_vial!$E$6:$P$49,MATCH(F$4,ASP_per_vial!$A$6:$A$49,0),MATCH($A14,ASP_per_vial!$E$5:$P$5,0)) -> 84.174528 | G14: =INDEX(ASP_per_vial!$E$6:$P$49,MATCH(G$4,ASP_per_vial!$A$6:$A$49,0),MATCH($A14,ASP_per_vial!$E$5:$P$5,0)) -> 87.070755 | H14: =INDEX(ASP_per_vial!$E$6:$P$49,MATCH(H$4,ASP_per_vial!$A$6:$A$49,0),MATCH($A14,ASP_per_vial!$E$5:$P$5,0)) -> 100.5283 | I14: =INDEX(ASP_per_vial!$E$6:$P$49,MATCH(I$4,ASP_per_vial!$A$6:$A$49,0),MATCH($A14,ASP_per_vial!$E$5:$P$5,0)) -> 109.1934 | J14: =MAX(INDEX(ASP_per_vial!$E$6:$P$49,0,MATCH($A14,ASP_per_vial!$E$5:$P$5,0))) -> 109.1934 | K14: =INDEX(ASP_per_vial!$A$6:$A$49,MATCH(J14,INDEX(ASP_per_vial!$E$6:$P$49,0,MATCH($A14,ASP_per_vial!$E$5:$P$5,0)),0)) -> 2026-Q4 | L14: =I14/H14-1 -> 0.086195571 | M14: =(I14/E14)^(1/(I$3-E$3))-1 -> 0.094163385 | N14: =(I14/D14)^(1/(I$3-D$3))-1 -> 0.093426438 | O14: =(I14/B14)^(1/(I$3-B$3))-1 -> 0.11050728 | P14: =C14/B14-1 -> 0.75646494 | Q14: =I14/G14-1 -> 0.2540766 | S14: =_xlfn.MAXIFS(INDEX(ASP_per_vial!$E$6:$P$49,0,MATCH($A14,ASP_per_vial!$E$5:$P$5,0)),ASP_per_vial!$C$6:$C$49,"<"&Assumptions!$B$8) -> 84.485849 | T14: =INDEX(ASP_per_vial!$A$6:$A$49,MATCH(S14,INDEX(ASP_per_vial!$E$6:$P$49,0,MATCH($A14,ASP_per_vial!$E$5:$P$5,0)),0)) -> 2023-Q2 | U14: =_xlfn.MAXIFS(INDEX(ASP_per_vial!$E$6:$P$49,0,MATCH($A14,ASP_per_vial!$E$5:$P$5,0)),ASP_per_vial!$C$6:$C$49,">="&Assumptions!$B$8) -> 109.1934 | V14: =INDEX(ASP_per_vial!$A$6:$A$49,MATCH(U14,INDEX(ASP_per_vial!$E$6:$P$49,0,MATCH($A14,ASP_per_vial!$E$5:$P$5,0)),0)) -> 2026-Q4
A15: HSS 1 g | B15: =INDEX(ASP_per_vial!$E$6:$P$49,MATCH(B$4,ASP_per_vial!$A$6:$A$49,0),MATCH($A15,ASP_per_vial!$E$5:$P$5,0)) -> 70.773585 | C15: =INDEX(ASP_per_vial!$E$6:$P$49,MATCH(C$4,ASP_per_vial!$A$6:$A$49,0),MATCH($A15,ASP_per_vial!$E$5:$P$5,0)) -> 124.31132 | D15: =INDEX(ASP_per_vial!$E$6:$P$49,MATCH(D$4,ASP_per_vial!$A$6:$A$49,0),MATCH($A15,ASP_per_vial!$E$5:$P$5,0)) -> 139.72642 | E15: =INDEX(ASP_per_vial!$E$6:$P$49,MATCH(E$4,ASP_per_vial!$A$6:$A$49,0),MATCH($A15,ASP_per_vial!$E$5:$P$5,0)) -> 166.71698 | F15: =INDEX(ASP_per_vial!$E$6:$P$49,MATCH(F$4,ASP_per_vial!$A$6:$A$49,0),MATCH($A15,ASP_per_vial!$E$5:$P$5,0)) -> 168.34906 | G15: =INDEX(ASP_per_vial!$E$6:$P$49,MATCH(G$4,ASP_per_vial!$A$6:$A$49,0),MATCH($A15,ASP_per_vial!$E$5:$P$5,0)) -> 174.14151 | H15: =INDEX(ASP_per_vial!$E$6:$P$49,MATCH(H$4,ASP_per_vial!$A$6:$A$49,0),MATCH($A15,ASP_per_vial!$E$5:$P$5,0)) -> 201.0566 | I15: =INDEX(ASP_per_vial!$E$6:$P$49,MATCH(I$4,ASP_per_vial!$A$6:$A$49,0),MATCH($A15,ASP_per_vial!$E$5:$P$5,0)) -> 218.38679 | J15: =MAX(INDEX(ASP_per_vial!$E$6:$P$49,0,MATCH($A15,ASP_per_vial!$E$5:$P$5,0))) -> 218.38679 | K15: =INDEX(ASP_per_vial!$A$6:$A$49,MATCH(J15,INDEX(ASP_per_vial!$E$6:$P$49,0,MATCH($A15,ASP_per_vial!$E$5:$P$5,0)),0)) -> 2026-Q4 | L15: =I15/H15-1 -> 0.086195571 | M15: =(I15/E15)^(1/(I$3-E$3))-1 -> 0.094163385 | N15: =(I15/D15)^(1/(I$3-D$3))-1 -> 0.093426438 | O15: =(I15/B15)^(1/(I$3-B$3))-1 -> 0.11050728 | P15: =C15/B15-1 -> 0.75646494 | Q15: =I15/G15-1 -> 0.2540766 | S15: =_xlfn.MAXIFS(INDEX(ASP_per_vial!$E$6:$P$49,0,MATCH($A15,ASP_per_vial!$E$5:$P$5,0)),ASP_per_vial!$C$6:$C$49,"<"&Assumptions!$B$8) -> 168.9717 | T15: =INDEX(ASP_per_vial!$A$6:$A$49,MATCH(S15,INDEX(ASP_per_vial!$E$6:$P$49,0,MATCH($A15,ASP_per_vial!$E$5:$P$5,0)),0)) -> 2023-Q2 | U15: =_xlfn.MAXIFS(INDEX(ASP_per_vial!$E$6:$P$49,0,MATCH($A15,ASP_per_vial!$E$5:$P$5,0)),ASP_per_vial!$C$6:$C$49,">="&Assumptions!$B$8) -> 218.38679 | V15: =INDEX(ASP_per_vial!$A$6:$A$49,MATCH(U15,INDEX(ASP_per_vial!$E$6:$P$49,0,MATCH($A15,ASP_per_vial!$E$5:$P$5,0)),0)) -> 2026-Q4
A16: MPA 40 mg/mL 1 mL | B16: =INDEX(ASP_per_vial!$E$6:$P$49,MATCH(B$4,ASP_per_vial!$A$6:$A$49,0),MATCH($A16,ASP_per_vial!$E$5:$P$5,0)) -> 4.0641509 | C16: =INDEX(ASP_per_vial!$E$6:$P$49,MATCH(C$4,ASP_per_vial!$A$6:$A$49,0),MATCH($A16,ASP_per_vial!$E$5:$P$5,0)) -> 6.604717 | D16: =INDEX(ASP_per_vial!$E$6:$P$49,MATCH(D$4,ASP_per_vial!$A$6:$A$49,0),MATCH($A16,ASP_per_vial!$E$5:$P$5,0)) -> 5.3066038 | E16: =INDEX(ASP_per_vial!$E$6:$P$49,MATCH(E$4,ASP_per_vial!$A$6:$A$49,0),MATCH($A16,ASP_per_vial!$E$5:$P$5,0)) -> 6.7943396 | F16: =INDEX(ASP_per_vial!$E$6:$P$49,MATCH(F$4,ASP_per_vial!$A$6:$A$49,0),MATCH($A16,ASP_per_vial!$E$5:$P$5,0)) -> 6.0556604 | G16: =INDEX(ASP_per_vial!$E$6:$P$49,MATCH(G$4,ASP_per_vial!$A$6:$A$49,0),MATCH($A16,ASP_per_vial!$E$5:$P$5,0)) -> 5.0566038 | H16: =INDEX(ASP_per_vial!$E$6:$P$49,MATCH(H$4,ASP_per_vial!$A$6:$A$49,0),MATCH($A16,ASP_per_vial!$E$5:$P$5,0)) -> 4.490566 | I16: =INDEX(ASP_per_vial!$E$6:$P$49,MATCH(I$4,ASP_per_vial!$A$6:$A$49,0),MATCH($A16,ASP_per_vial!$E$5:$P$5,0)) -> 4.6415094 | J16: =MAX(INDEX(ASP_per_vial!$E$6:$P$49,0,MATCH($A16,ASP_per_vial!$E$5:$P$5,0))) -> 7.6264151 | K16: =INDEX(ASP_per_vial!$A$6:$A$49,MATCH(J16,INDEX(ASP_per_vial!$E$6:$P$49,0,MATCH($A16,ASP_per_vial!$E$5:$P$5,0)),0)) -> 2023-Q2 | L16: =I16/H16-1 -> 0.033613445 | M16: =(I16/E16)^(1/(I$3-E$3))-1 -> -0.11928108 | N16: =(I16/D16)^(1/(I$3-D$3))-1 -> -0.026427013 | O16: =(I16/B16)^(1/(I$3-B$3))-1 -> 0.012433383 | P16: =C16/B16-1 -> 0.62511606 | Q16: =I16/G16-1 -> -0.082089552 | R16: Windows before Q2 2024 cross the code change | S16: =_xlfn.MAXIFS(INDEX(ASP_per_vial!$E$6:$P$49,0,MATCH($A16,ASP_per_vial!$E$5:$P$5,0)),ASP_per_vial!$C$6:$C$49,"<"&Assumptions!$B$8) -> 7.6264151 | T16: =INDEX(ASP_per_vial!$A$6:$A$49,MATCH(S16,INDEX(ASP_per_vial!$E$6:$P$49,0,MATCH($A16,ASP_per_vial!$E$5:$P$5,0)),0)) -> 2023-Q2 | U16: =_xlfn.MAXIFS(INDEX(ASP_per_vial!$E$6:$P$49,0,MATCH($A16,ASP_per_vial!$E$5:$P$5,0)),ASP_per_vial!$C$6:$C$49,">="&Assumptions!$B$8) -> 5.2075472 | V16: =INDEX(ASP_per_vial!$A$6:$A$49,MATCH(U16,INDEX(ASP_per_vial!$E$6:$P$49,0,MATCH($A16,ASP_per_vial!$E$5:$P$5,0)),0)) -> 2024-Q3
A17: MPA 80 mg/mL 1 mL | B17: =INDEX(ASP_per_vial!$E$6:$P$49,MATCH(B$4,ASP_per_vial!$A$6:$A$49,0),MATCH($A17,ASP_per_vial!$E$5:$P$5,0)) -> 7.8622642 | C17: =INDEX(ASP_per_vial!$E$6:$P$49,MATCH(C$4,ASP_per_vial!$A$6:$A$49,0),MATCH($A17,ASP_per_vial!$E$5:$P$5,0)) -> 12.745283 | D17: =INDEX(ASP_per_vial!$E$6:$P$49,MATCH(D$4,ASP_per_vial!$A$6:$A$49,0),MATCH($A17,ASP_per_vial!$E$5:$P$5,0)) -> 10.071698 | E17: =INDEX(ASP_per_vial!$E$6:$P$49,MATCH(E$4,ASP_per_vial!$A$6:$A$49,0),MATCH($A17,ASP_per_vial!$E$5:$P$5,0)) -> 10.148113 | F17: =INDEX(ASP_per_vial!$E$6:$P$49,MATCH(F$4,ASP_per_vial!$A$6:$A$49,0),MATCH($A17,ASP_per_vial!$E$5:$P$5,0)) -> 9.2481132 | G17: =INDEX(ASP_per_vial!$E$6:$P$49,MATCH(G$4,ASP_per_vial!$A$6:$A$49,0),MATCH($A17,ASP_per_vial!$E$5:$P$5,0)) -> 10.113208 | H17: =INDEX(ASP_per_vial!$E$6:$P$49,MATCH(H$4,ASP_per_vial!$A$6:$A$49,0),MATCH($A17,ASP_per_vial!$E$5:$P$5,0)) -> 8.9811321 | I17: =INDEX(ASP_per_vial!$E$6:$P$49,MATCH(I$4,ASP_per_vial!$A$6:$A$49,0),MATCH($A17,ASP_per_vial!$E$5:$P$5,0)) -> 9.2830189 | J17: =MAX(INDEX(ASP_per_vial!$E$6:$P$49,0,MATCH($A17,ASP_per_vial!$E$5:$P$5,0))) -> 12.745283 | K17: =INDEX(ASP_per_vial!$A$6:$A$49,MATCH(J17,INDEX(ASP_per_vial!$E$6:$P$49,0,MATCH($A17,ASP_per_vial!$E$5:$P$5,0)),0)) -> 2018-Q3 | L17: =I17/H17-1 -> 0.033613445 | M17: =(I17/E17)^(1/(I$3-E$3))-1 -> -0.029263611 | N17: =(I17/D17)^(1/(I$3-D$3))-1 -> -0.01617624 | O17: =(I17/B17)^(1/(I$3-B$3))-1 -> 0.0155723 | P17: =C17/B17-1 -> 0.62107031 | Q17: =I17/G17-1 -> -0.082089552 | R17: Windows before Q2 2024 cross the code change | S17: =_xlfn.MAXIFS(INDEX(ASP_per_vial!$E$6:$P$49,0,MATCH($A17,ASP_per_vial!$E$5:$P$5,0)),ASP_per_vial!$C$6:$C$49,"<"&Assumptions!$B$8) -> 12.745283 | T17: =INDEX(ASP_per_vial!$A$6:$A$49,MATCH(S17,INDEX(ASP_per_vial!$E$6:$P$49,0,MATCH($A17,ASP_per_vial!$E$5:$P$5,0)),0)) -> 2018-Q3 | U17: =_xlfn.MAXIFS(INDEX(ASP_per_vial!$E$6:$P$49,0,MATCH($A17,ASP_per_vial!$E$5:$P$5,0)),ASP_per_vial!$C$6:$C$49,">="&Assumptions!$B$8) -> 10.415094 | V17: =INDEX(ASP_per_vial!$A$6:$A$49,MATCH(U17,INDEX(ASP_per_vial!$E$6:$P$49,0,MATCH($A17,ASP_per_vial!$E$5:$P$5,0)),0)) -> 2024-Q3
A20: Quarter-on-quarter change in payment limit per billing unit (links to CMS_PL)
A21: Quarter | B21: J1720 PL | C21: J1720 QoQ | D21: J2930 PL | E21: J2930 QoQ | F21: J2919 PL | G21: J2919 QoQ | H21: J1010 PL | I21: J1010 QoQ
A22: =CMS_PL!A6 -> 2016-Q1 | B22: =IF(CMS_PL!H6="","",CMS_PL!H6) -> 7.502 | D22: =IF(CMS_PL!F6="","",CMS_PL!F6) -> 4.105 | F22: =IF(CMS_PL!G6="","",CMS_PL!G6) | H22: =IF(CMS_PL!K6="","",CMS_PL!K6)
A23: =CMS_PL!A7 -> 2016-Q2 | B23: =IF(CMS_PL!H7="","",CMS_PL!H7) -> 7.462 | C23: =IF(OR(B23="",B22=""),"",B23/B22-1) -> -0.0053319115 | D23: =IF(CMS_PL!F7="","",CMS_PL!F7) -> 4.213 | E23: =IF(OR(D23="",D22=""),"",D23/D22-1) -> 0.026309379 | F23: =IF(CMS_PL!G7="","",CMS_PL!G7) | G23: =IF(OR(F23="",F22=""),"",F23/F22-1) | H23: =IF(CMS_PL!K7="","",CMS_PL!K7) | I23: =IF(OR(H23="",H22=""),"",H23/H22-1)
A24: =CMS_PL!A8 -> 2016-Q3 | B24: =IF(CMS_PL!H8="","",CMS_PL!H8) -> 8.163 | C24: =IF(OR(B24="",B23=""),"",B24/B23-1) -> 0.093942643 | D24: =IF(CMS_PL!F8="","",CMS_PL!F8) -> 4.964 | E24: =IF(OR(D24="",D23=""),"",D24/D23-1) -> 0.17825777 | F24: =IF(CMS_PL!G8="","",CMS_PL!G8) | G24: =IF(OR(F24="",F23=""),"",F24/F23-1) | H24: =IF(CMS_PL!K8="","",CMS_PL!K8) | I24: =IF(OR(H24="",H23=""),"",H24/H23-1)
A25: =CMS_PL!A9 -> 2016-Q4 | B25: =IF(CMS_PL!H9="","",CMS_PL!H9) -> 8.531 | C25: =IF(OR(B25="",B24=""),"",B25/B24-1) -> 0.045081465 | D25: =IF(CMS_PL!F9="","",CMS_PL!F9) -> 5.126 | E25: =IF(OR(D25="",D24=""),"",D25/D24-1) -> 0.032634972 | F25: =IF(CMS_PL!G9="","",CMS_PL!G9) | G25: =IF(OR(F25="",F24=""),"",F25/F24-1) | H25: =IF(CMS_PL!K9="","",CMS_PL!K9) | I25: =IF(OR(H25="",H24=""),"",H25/H24-1)
A26: =CMS_PL!A10 -> 2017-Q1 | B26: =IF(CMS_PL!H10="","",CMS_PL!H10) -> 9.118 | C26: =IF(OR(B26="",B25=""),"",B26/B25-1) -> 0.068807877 | D26: =IF(CMS_PL!F10="","",CMS_PL!F10) -> 5.498 | E26: =IF(OR(D26="",D25=""),"",D26/D25-1) -> 0.072571206 | F26: =IF(CMS_PL!G10="","",CMS_PL!G10) | G26: =IF(OR(F26="",F25=""),"",F26/F25-1) | H26: =IF(CMS_PL!K10="","",CMS_PL!K10) | I26: =IF(OR(H26="",H25=""),"",H26/H25-1)
A27: =CMS_PL!A11 -> 2017-Q2 | B27: =IF(CMS_PL!H11="","",CMS_PL!H11) -> 9.034 | C27: =IF(OR(B27="",B26=""),"",B27/B26-1) -> -0.0092125466 | D27: =IF(CMS_PL!F11="","",CMS_PL!F11) -> 5.568 | E27: =IF(OR(D27="",D26=""),"",D27/D26-1) -> 0.012731903 | F27: =IF(CMS_PL!G11="","",CMS_PL!G11) | G27: =IF(OR(F27="",F26=""),"",F27/F26-1) | H27: =IF(CMS_PL!K11="","",CMS_PL!K11) | I27: =IF(OR(H27="",H26=""),"",H27/H26-1)
A28: =CMS_PL!A12 -> 2017-Q3 | B28: =IF(CMS_PL!H12="","",CMS_PL!H12) -> 10.852 | C28: =IF(OR(B28="",B27=""),"",B28/B27-1) -> 0.20123976 | D28: =IF(CMS_PL!F12="","",CMS_PL!F12) -> 6.033 | E28: =IF(OR(D28="",D27=""),"",D28/D27-1) -> 0.083512931 | F28: =IF(CMS_PL!G12="","",CMS_PL!G12) | G28: =IF(OR(F28="",F27=""),"",F28/F27-1) | H28: =IF(CMS_PL!K12="","",CMS_PL!K12) | I28: =IF(OR(H28="",H27=""),"",H28/H27-1)
A29: =CMS_PL!A13 -> 2017-Q4 | B29: =IF(CMS_PL!H13="","",CMS_PL!H13) -> 11.279 | C29: =IF(OR(B29="",B28=""),"",B29/B28-1) -> 0.039347586 | D29: =IF(CMS_PL!F13="","",CMS_PL!F13) -> 6.093 | E29: =IF(OR(D29="",D28=""),"",D29/D28-1) -> 0.0099453008 | F29: =IF(CMS_PL!G13="","",CMS_PL!G13) | G29: =IF(OR(F29="",F28=""),"",F29/F28-1) | H29: =IF(CMS_PL!K13="","",CMS_PL!K13) | I29: =IF(OR(H29="",H28=""),"",H29/H28-1)
A30: =CMS_PL!A14 -> 2018-Q1 | B30: =IF(CMS_PL!H14="","",CMS_PL!H14) -> 11.931 | C30: =IF(OR(B30="",B29=""),"",B30/B29-1) -> 0.057806543 | D30: =IF(CMS_PL!F14="","",CMS_PL!F14) -> 5.985 | E30: =IF(OR(D30="",D29=""),"",D30/D29-1) -> -0.017725258 | F30: =IF(CMS_PL!G14="","",CMS_PL!G14) | G30: =IF(OR(F30="",F29=""),"",F30/F29-1) | H30: =IF(CMS_PL!K14="","",CMS_PL!K14) | I30: =IF(OR(H30="",H29=""),"",H30/H29-1)
A31: =CMS_PL!A15 -> 2018-Q2 | B31: =IF(CMS_PL!H15="","",CMS_PL!H15) -> 12.05 | C31: =IF(OR(B31="",B30=""),"",B31/B30-1) -> 0.0099740173 | D31: =IF(CMS_PL!F15="","",CMS_PL!F15) -> 6.672 | E31: =IF(OR(D31="",D30=""),"",D31/D30-1) -> 0.11478697 | F31: =IF(CMS_PL!G15="","",CMS_PL!G15) | G31: =IF(OR(F31="",F30=""),"",F31/F30-1) | H31: =IF(CMS_PL!K15="","",CMS_PL!K15) | I31: =IF(OR(H31="",H30=""),"",H31/H30-1)
A32: =CMS_PL!A16 -> 2018-Q3 | B32: =IF(CMS_PL!H16="","",CMS_PL!H16) -> 13.177 | C32: =IF(OR(B32="",B31=""),"",B32/B31-1) -> 0.093526971 | D32: =IF(CMS_PL!F16="","",CMS_PL!F16) -> 6.965 | E32: =IF(OR(D32="",D31=""),"",D32/D31-1) -> 0.043914868 | F32: =IF(CMS_PL!G16="","",CMS_PL!G16) | G32: =IF(OR(F32="",F31=""),"",F32/F31-1) | H32: =IF(CMS_PL!K16="","",CMS_PL!K16) | I32: =IF(OR(H32="",H31=""),"",H32/H31-1)
A33: =CMS_PL!A17 -> 2018-Q4 | B33: =IF(CMS_PL!H17="","",CMS_PL!H17) -> 13.051 | C33: =IF(OR(B33="",B32=""),"",B33/B32-1) -> -0.0095621158 | D33: =IF(CMS_PL!F17="","",CMS_PL!F17) -> 6.942 | E33: =IF(OR(D33="",D32=""),"",D33/D32-1) -> -0.0033022254 | F33: =IF(CMS_PL!G17="","",CMS_PL!G17) | G33: =IF(OR(F33="",F32=""),"",F33/F32-1) | H33: =IF(CMS_PL!K17="","",CMS_PL!K17) | I33: =IF(OR(H33="",H32=""),"",H33/H32-1)
A34: =CMS_PL!A18 -> 2019-Q1 | B34: =IF(CMS_PL!H18="","",CMS_PL!H18) -> 12.993 | C34: =IF(OR(B34="",B33=""),"",B34/B33-1) -> -0.0044441039 | D34: =IF(CMS_PL!F18="","",CMS_PL!F18) -> 6.928 | E34: =IF(OR(D34="",D33=""),"",D34/D33-1) -> -0.0020167099 | F34: =IF(CMS_PL!G18="","",CMS_PL!G18) | G34: =IF(OR(F34="",F33=""),"",F34/F33-1) | H34: =IF(CMS_PL!K18="","",CMS_PL!K18) | I34: =IF(OR(H34="",H33=""),"",H34/H33-1)
... A65: =CMS_PL!A49 -> 2026-Q4 | B65: =IF(CMS_PL!H49="","",CMS_PL!H49) -> 23.149 | C65: =IF(OR(B65="",B64=""),"",B65/B64-1) -> 0.0040336572 | D65: =IF(CMS_PL!F49="","",CMS_PL!F49) | E65: =IF(OR(D65="",D64=""),"",D65/D64-1) | F65: =IF(CMS_PL!G49="","",CMS_PL!G49) -> 0.255 | G65: =IF(OR(F65="",F64=""),"",F65/F64-1) -> 0.13839286 | H65: =IF(CMS_PL!K49="","",CMS_PL!K49) -> 0.123 | I65: =IF(OR(H65="",H64=""),"",H65/H64-1) -> 0.051282051
A67: Summary of quarterly moves
A68: Measure | B68: Value | C68: Quarter
A69: J1720 largest quarterly fall | B69: =MIN(C23:C65) -> -0.022968821 | C69: =INDEX(A22:A65,MATCH(B69,C22:C65,0)) -> 2024-Q4
A70: J1720 largest quarterly rise | B70: =MAX(C23:C65) -> 0.20123976 | C70: =INDEX(A22:A65,MATCH(B70,C22:C65,0)) -> 2017-Q3
A71: J1720 change in 2017-Q3 | B71: =INDEX(C22:C65,MATCH("2017-Q3",A22:A65,0)) -> 0.20123976 | C71: 2017-Q3
A72: J1720 change in 2022-Q3 | B72: =INDEX(C22:C65,MATCH("2022-Q3",A22:A65,0)) -> 0.19202333 | C72: 2022-Q3
A73: J2919 change in 2025-Q4 | B73: =INDEX(G22:G65,MATCH("2025-Q4",A22:A65,0)) -> -0.18918919 | C73: 2025-Q4
A74: J2919 change in 2026-Q1 | B74: =INDEX(G22:G65,MATCH("2026-Q1",A22:A65,0)) -> 0.25714286 | C74: 2026-Q1
A75: J2919 implied ASP per 5 mg, 2025 average | B75: =AVERAGEIFS(CMS_PL!$G$6:$G$49,CMS_PL!$B$6:$B$49,"2025")/Assumptions!$B$5 -> 0.23301887 | C75: 2025
A76: J2919 implied ASP per 5 mg, 2026 average | B76: =AVERAGEIFS(CMS_PL!$G$6:$G$49,CMS_PL!$B$6:$B$49,"2026")/Assumptions!$B$5 -> 0.23207547 | C76: 2026
A77: J1720 payment-limit CAGR Q1'16 to Q4'26 | B77: =(INDEX(B22:B65,MATCH("2026-Q4",A22:A65,0))/INDEX(B22:B65,MATCH("2016-Q1",A22:A65,0)))^(1/($I$3-$B$3))-1 -> 0.11050728 | C77: 2016-Q1 to 2026-Q4

Sheet Pfizer_WAC
A1: Pfizer list price (WAC) per vial, Connecticut price disclosures
A2: Line keys follow the order of presentations in each disclosure (the PDFs give no NDCs). WAC per vial = pack WAC / pack size.
J4: WAC per vial by line and date (AVERAGEIFS on the table at left) | K4: 45482 | L4: 45744 | M4: 45866 | N4: 45933 | O4: 46031 | P4: 46209
A5: Brand | B5: Disclosure date | C5: Presentation as listed | D5: Line key | E5: Pack WAC (US$) | F5: Pack size | G5: WAC per vial (US$) | H5: Source | J5: Line key | K5: 09-Jul-2024 | L5: 28-Mar-2025 | M5: 28-Jul-2025 | N5: 03-Oct-2025 | O5: 09-Jan-2026 | P5: 06-Jul-2026 | Q5: Change Jul-24 to Jul-26 | R5: Change Mar-25 to Jul-25
A6: SOLU-CORTEF | B6: 45482 | C6: SOLU-CORTEF 1000 MG ACT-O-VL | D6: HSS 1 g Act-O-Vial | E6: 158.57 | F6: 1 | G6: =E6/F6 -> 158.57 | H6: PDF | J6: HSS 1 g Act-O-Vial | K6: =IFERROR(AVERAGEIFS($G$6:$G$119,$D$6:$D$119,$J6,$B$6:$B$119,K$4),"") -> 158.57 | L6: =IFERROR(AVERAGEIFS($G$6:$G$119,$D$6:$D$119,$J6,$B$6:$B$119,L$4),"") -> 166.5 | M6: =IFERROR(AVERAGEIFS($G$6:$G$119,$D$6:$D$119,$J6,$B$6:$B$119,M$4),"") -> 174.83 | N6: =IFERROR(AVERAGEIFS($G$6:$G$119,$D$6:$D$119,$J6,$B$6:$B$119,N$4),"") -> 174.83 | O6: =IFERROR(AVERAGEIFS($G$6:$G$119,$D$6:$D$119,$J6,$B$6:$B$119,O$4),"") -> 201.05 | P6: =IFERROR(AVERAGEIFS($G$6:$G$119,$D$6:$D$119,$J6,$B$6:$B$119,P$4),"") -> 201.05 | Q6: =IF(OR(K6="",P6=""),"",P6/K6-1) -> 0.26789431 | R6: =IF(OR(L6="",M6=""),"",M6/L6-1) -> 0.05003003
A7: SOLU-CORTEF | B7: 45744 | C7: SOLU-CORTEF 1 gm/8 mL ACT-O-VIAL® | D7: HSS 1 g Act-O-Vial | E7: 166.5 | F7: 1 | G7: =E7/F7 -> 166.5 | H7: PDF | J7: HSS 100 mg Act-O-Vial (25-pack) | K7: =IFERROR(AVERAGEIFS($G$6:$G$119,$D$6:$D$119,$J7,$B$6:$B$119,K$4),"") -> 21.43 | L7: =IFERROR(AVERAGEIFS($G$6:$G$119,$D$6:$D$119,$J7,$B$6:$B$119,L$4),"") -> 22.5 | M7: =IFERROR(AVERAGEIFS($G$6:$G$119,$D$6:$D$119,$J7,$B$6:$B$119,M$4),"") -> 23.6252 | N7: =IFERROR(AVERAGEIFS($G$6:$G$119,$D$6:$D$119,$J7,$B$6:$B$119,N$4),"") -> 23.6252 | O7: =IFERROR(AVERAGEIFS($G$6:$G$119,$D$6:$D$119,$J7,$B$6:$B$119,O$4),"") -> 24.8064 | P7: =IFERROR(AVERAGEIFS($G$6:$G$119,$D$6:$D$119,$J7,$B$6:$B$119,P$4),"") -> 24.8064 | Q7: =IF(OR(K7="",P7=""),"",P7/K7-1) -> 0.15755483 | R7: =IF(OR(L7="",M7=""),"",M7/L7-1) -> 0.050008889
A8: SOLU-CORTEF | B8: 45866 | C8: SOLU-CORTEF 1 gm/8 mL ACT-O-VIAL® | D8: HSS 1 g Act-O-Vial | E8: 174.83 | F8: 1 | G8: =E8/F8 -> 174.83 | H8: PDF | J8: HSS 100 mg Act-O-Vial (single) | K8: =IFERROR(AVERAGEIFS($G$6:$G$119,$D$6:$D$119,$J8,$B$6:$B$119,K$4),"") -> 21.42 | L8: =IFERROR(AVERAGEIFS($G$6:$G$119,$D$6:$D$119,$J8,$B$6:$B$119,L$4),"") -> 22.92 | M8: =IFERROR(AVERAGEIFS($G$6:$G$119,$D$6:$D$119,$J8,$B$6:$B$119,M$4),"") -> 24.07 | N8: =IFERROR(AVERAGEIFS($G$6:$G$119,$D$6:$D$119,$J8,$B$6:$B$119,N$4),"") -> 24.07 | O8: =IFERROR(AVERAGEIFS($G$6:$G$119,$D$6:$D$119,$J8,$B$6:$B$119,O$4),"") -> 25.27 | P8: =IFERROR(AVERAGEIFS($G$6:$G$119,$D$6:$D$119,$J8,$B$6:$B$119,P$4),"") -> 25.27 | Q8: =IF(OR(K8="",P8=""),"",P8/K8-1) -> 0.17973856 | R8: =IF(OR(L8="",M8=""),"",M8/L8-1) -> 0.05017452
A9: SOLU-CORTEF | B9: 45933 | C9: SOLU-CORTEF 1 gm/8 mL ACT-O-VIAL® | D9: HSS 1 g Act-O-Vial | E9: 174.83 | F9: 1 | G9: =E9/F9 -> 174.83 | H9: PDF | J9: HSS 100 mg plain vial | K9: =IFERROR(AVERAGEIFS($G$6:$G$119,$D$6:$D$119,$J9,$B$6:$B$119,K$4),"") -> 15.86 | L9: =IFERROR(AVERAGEIFS($G$6:$G$119,$D$6:$D$119,$J9,$B$6:$B$119,L$4),"") -> 18.24 | M9: =IFERROR(AVERAGEIFS($G$6:$G$119,$D$6:$D$119,$J9,$B$6:$B$119,M$4),"") -> 19.15 | N9: =IFERROR(AVERAGEIFS($G$6:$G$119,$D$6:$D$119,$J9,$B$6:$B$119,N$4),"") -> 19.15 | O9: =IFERROR(AVERAGEIFS($G$6:$G$119,$D$6:$D$119,$J9,$B$6:$B$119,O$4),"") -> 20.11 | P9: =IFERROR(AVERAGEIFS($G$6:$G$119,$D$6:$D$119,$J9,$B$6:$B$119,P$4),"") -> 20.11 | Q9: =IF(OR(K9="",P9=""),"",P9/K9-1) -> 0.26796974 | R9: =IF(OR(L9="",M9=""),"",M9/L9-1) -> 0.049890351
A10: SOLU-CORTEF | B10: 46031 | C10: SOLU-CORTEF 1 gm/8 mL ACT-O-VIAL® | D10: HSS 1 g Act-O-Vial | E10: 201.05 | F10: 1 | G10: =E10/F10 -> 201.05 | H10: PDF | J10: HSS 250 mg Act-O-Vial (25-pack) | K10: =IFERROR(AVERAGEIFS($G$6:$G$119,$D$6:$D$119,$J10,$B$6:$B$119,K$4),"") -> 39.64 | L10: =IFERROR(AVERAGEIFS($G$6:$G$119,$D$6:$D$119,$J10,$B$6:$B$119,L$4),"") -> 41.6172 | M10: =IFERROR(AVERAGEIFS($G$6:$G$119,$D$6:$D$119,$J10,$B$6:$B$119,M$4),"") -> 43.698 | N10: =IFERROR(AVERAGEIFS($G$6:$G$119,$D$6:$D$119,$J10,$B$6:$B$119,N$4),"") -> 43.698 | O10: =IFERROR(AVERAGEIFS($G$6:$G$119,$D$6:$D$119,$J10,$B$6:$B$119,O$4),"") -> 48.068 | P10: =IFERROR(AVERAGEIFS($G$6:$G$119,$D$6:$D$119,$J10,$B$6:$B$119,P$4),"") -> 48.068 | Q10: =IF(OR(K10="",P10=""),"",P10/K10-1) -> 0.21261352 | R10: =IF(OR(L10="",M10=""),"",M10/L10-1) -> 0.049998558
A11: SOLU-CORTEF | B11: 46209 | C11: SOLU-CORTEF 1 gm/8 mL ACT-O-VIAL® | D11: HSS 1 g Act-O-Vial | E11: 201.05 | F11: 1 | G11: =E11/F11 -> 201.05 | H11: PDF | J11: HSS 250 mg Act-O-Vial (single) | K11: =IFERROR(AVERAGEIFS($G$6:$G$119,$D$6:$D$119,$J11,$B$6:$B$119,K$4),"") -> 39.64 | L11: =IFERROR(AVERAGEIFS($G$6:$G$119,$D$6:$D$119,$J11,$B$6:$B$119,L$4),"") -> 42.41 | M11: =IFERROR(AVERAGEIFS($G$6:$G$119,$D$6:$D$119,$J11,$B$6:$B$119,M$4),"") -> 44.53 | N11: =IFERROR(AVERAGEIFS($G$6:$G$119,$D$6:$D$119,$J11,$B$6:$B$119,N$4),"") -> 44.53 | O11: =IFERROR(AVERAGEIFS($G$6:$G$119,$D$6:$D$119,$J11,$B$6:$B$119,O$4),"") -> 51.21 | P11: =IFERROR(AVERAGEIFS($G$6:$G$119,$D$6:$D$119,$J11,$B$6:$B$119,P$4),"") -> 51.21 | Q11: =IF(OR(K11="",P11=""),"",P11/K11-1) -> 0.29187689 | R11: =IF(OR(L11="",M11=""),"",M11/L11-1) -> 0.04998821
A12: SOLU-CORTEF | B12: 45482 | C12: SOLU-CORTEF 100 MG ACT-O-VIAL | D12: HSS 100 mg Act-O-Vial (25-pack) | E12: 21.43 | F12: 1 | G12: =E12/F12 -> 21.43 | H12: PDF | J12: HSS 500 mg Act-O-Vial | K12: =IFERROR(AVERAGEIFS($G$6:$G$119,$D$6:$D$119,$J12,$B$6:$B$119,K$4),"") -> 79.31 | L12: =IFERROR(AVERAGEIFS($G$6:$G$119,$D$6:$D$119,$J12,$B$6:$B$119,L$4),"") -> 83.28 | M12: =IFERROR(AVERAGEIFS($G$6:$G$119,$D$6:$D$119,$J12,$B$6:$B$119,M$4),"") -> 87.44 | N12: =IFERROR(AVERAGEIFS($G$6:$G$119,$D$6:$D$119,$J12,$B$6:$B$119,N$4),"") -> 87.44 | O12: =IFERROR(AVERAGEIFS($G$6:$G$119,$D$6:$D$119,$J12,$B$6:$B$119,O$4),"") -> 100.56 | P12: =IFERROR(AVERAGEIFS($G$6:$G$119,$D$6:$D$119,$J12,$B$6:$B$119,P$4),"") -> 100.56 | Q12: =IF(OR(K12="",P12=""),"",P12/K12-1) -> 0.26793595 | R12: =IF(OR(L12="",M12=""),"",M12/L12-1) -> 0.049951969
A13: SOLU-CORTEF | B13: 45744 | C13: SOLU-CORTEF 100 mg/2 mL ACT-O-VIAL® | D13: HSS 100 mg Act-O-Vial (25-pack) | E13: 562.5 | F13: 25 | G13: =E13/F13 -> 22.5 | H13: PDF | J13: MPSS 1 g Act-O-Vial | K13: =IFERROR(AVERAGEIFS($G$6:$G$119,$D$6:$D$119,$J13,$B$6:$B$119,K$4),"") -> 68.92 | L13: =IFERROR(AVERAGEIFS($G$6:$G$119,$D$6:$D$119,$J13,$B$6:$B$119,L$4),"") -> 68.92 | M13: =IFERROR(AVERAGEIFS($G$6:$G$119,$D$6:$D$119,$J13,$B$6:$B$119,M$4),"") -> 68.92 | N13: =IFERROR(AVERAGEIFS($G$6:$G$119,$D$6:$D$119,$J13,$B$6:$B$119,N$4),"") -> 68.92 | O13: =IFERROR(AVERAGEIFS($G$6:$G$119,$D$6:$D$119,$J13,$B$6:$B$119,O$4),"") -> 68.92 | P13: =IFERROR(AVERAGEIFS($G$6:$G$119,$D$6:$D$119,$J13,$B$6:$B$119,P$4),"") -> 68.92 | Q13: =IF(OR(K13="",P13=""),"",P13/K13-1) -> 0 | R13: =IF(OR(L13="",M13=""),"",M13/L13-1) -> 0
A14: SOLU-CORTEF | B14: 45866 | C14: SOLU-CORTEF 100 mg/2 mL ACT-O-VIAL® | D14: HSS 100 mg Act-O-Vial (25-pack) | E14: 590.63 | F14: 25 | G14: =E14/F14 -> 23.6252 | H14: PDF | J14: MPSS 1 g multi-dose vial | K14: =IFERROR(AVERAGEIFS($G$6:$G$119,$D$6:$D$119,$J14,$B$6:$B$119,K$4),"") -> 43.98 | L14: =IFERROR(AVERAGEIFS($G$6:$G$119,$D$6:$D$119,$J14,$B$6:$B$119,L$4),"") -> 43.98 | M14: =IFERROR(AVERAGEIFS($G$6:$G$119,$D$6:$D$119,$J14,$B$6:$B$119,M$4),"") -> 25.35 | N14: =IFERROR(AVERAGEIFS($G$6:$G$119,$D$6:$D$119,$J14,$B$6:$B$119,N$4),"") -> 25.35 | O14: =IFERROR(AVERAGEIFS($G$6:$G$119,$D$6:$D$119,$J14,$B$6:$B$119,O$4),"") -> 25.35 | P14: =IFERROR(AVERAGEIFS($G$6:$G$119,$D$6:$D$119,$J14,$B$6:$B$119,P$4),"") -> 25.35 | Q14: =IF(OR(K14="",P14=""),"",P14/K14-1) -> -0.42360164 | R14: =IF(OR(L14="",M14=""),"",M14/L14-1) -> -0.42360164
A15: SOLU-CORTEF | B15: 45933 | C15: SOLU-CORTEF 100 mg/2 mL ACT-O-VIAL® | D15: HSS 100 mg Act-O-Vial (25-pack) | E15: 590.63 | F15: 25 | G15: =E15/F15 -> 23.6252 | H15: PDF | J15: MPSS 1 g vial | K15: =IFERROR(AVERAGEIFS($G$6:$G$119,$D$6:$D$119,$J15,$B$6:$B$119,K$4),"") -> 43.98 | L15: =IFERROR(AVERAGEIFS($G$6:$G$119,$D$6:$D$119,$J15,$B$6:$B$119,L$4),"") -> 43.98 | M15: =IFERROR(AVERAGEIFS($G$6:$G$119,$D$6:$D$119,$J15,$B$6:$B$119,M$4),"") -> 43.98 | N15: =IFERROR(AVERAGEIFS($G$6:$G$119,$D$6:$D$119,$J15,$B$6:$B$119,N$4),"") -> 43.98 | O15: =IFERROR(AVERAGEIFS($G$6:$G$119,$D$6:$D$119,$J15,$B$6:$B$119,O$4),"") -> 43.98 | P15: =IFERROR(AVERAGEIFS($G$6:$G$119,$D$6:$D$119,$J15,$B$6:$B$119,P$4),"") -> 43.98 | Q15: =IF(OR(K15="",P15=""),"",P15/K15-1) -> 0 | R15: =IF(OR(L15="",M15=""),"",M15/L15-1) -> 0
A16: SOLU-CORTEF | B16: 46031 | C16: SOLU-CORTEF 100 mg/2 mL ACT-O-VIAL® | D16: HSS 100 mg Act-O-Vial (25-pack) | E16: 620.16 | F16: 25 | G16: =E16/F16 -> 24.8064 | H16: PDF | J16: MPSS 125 mg Act-O-Vial line A | K16: =IFERROR(AVERAGEIFS($G$6:$G$119,$D$6:$D$119,$J16,$B$6:$B$119,K$4),"") -> 10.88 | L16: =IFERROR(AVERAGEIFS($G$6:$G$119,$D$6:$D$119,$J16,$B$6:$B$119,L$4),"") -> 10.884 | M16: =IFERROR(AVERAGEIFS($G$6:$G$119,$D$6:$D$119,$J16,$B$6:$B$119,M$4),"") -> 8.1376 | N16: =IFERROR(AVERAGEIFS($G$6:$G$119,$D$6:$D$119,$J16,$B$6:$B$119,N$4),"") -> 8.1376 | O16: =IFERROR(AVERAGEIFS($G$6:$G$119,$D$6:$D$119,$J16,$B$6:$B$119,O$4),"") -> 8.1376 | P16: =IFERROR(AVERAGEIFS($G$6:$G$119,$D$6:$D$119,$J16,$B$6:$B$119,P$4),"") -> 8.1376 | Q16: =IF(OR(K16="",P16=""),"",P16/K16-1) -> -0.25205882 | R16: =IF(OR(L16="",M16=""),"",M16/L16-1) -> -0.2523337
A17: SOLU-CORTEF | B17: 46209 | C17: SOLU-CORTEF 100 mg/2 mL ACT-O-VIAL® | D17: HSS 100 mg Act-O-Vial (25-pack) | E17: 620.16 | F17: 25 | G17: =E17/F17 -> 24.8064 | H17: PDF | J17: MPSS 125 mg Act-O-Vial line B | K17: =IFERROR(AVERAGEIFS($G$6:$G$119,$D$6:$D$119,$J17,$B$6:$B$119,K$4),"") -> 10.42 | L17: =IFERROR(AVERAGEIFS($G$6:$G$119,$D$6:$D$119,$J17,$B$6:$B$119,L$4),"") -> 10.4176 | M17: =IFERROR(AVERAGEIFS($G$6:$G$119,$D$6:$D$119,$J17,$B$6:$B$119,M$4),"") -> 10.4176 | N17: =IFERROR(AVERAGEIFS($G$6:$G$119,$D$6:$D$119,$J17,$B$6:$B$119,N$4),"") -> 10.4176 | O17: =IFERROR(AVERAGEIFS($G$6:$G$119,$D$6:$D$119,$J17,$B$6:$B$119,O$4),"") -> 10.4176 | P17: =IFERROR(AVERAGEIFS($G$6:$G$119,$D$6:$D$119,$J17,$B$6:$B$119,P$4),"") -> 10.4176 | Q17: =IF(OR(K17="",P17=""),"",P17/K17-1) -> -0.0002303263 | R17: =IF(OR(L17="",M17=""),"",M17/L17-1) -> 0
... A24: SOLU-CORTEF | B24: 45482 | C24: SOLU-CORTEF 100 MG VIAL | D24: HSS 100 mg plain vial | E24: 15.86 | F24: 1 | G24: =E24/F24 -> 15.86 | H24: PDF | J24: MPSS 500 mg vial | K24: =IFERROR(AVERAGEIFS($G$6:$G$119,$D$6:$D$119,$J24,$B$6:$B$119,K$4),"") -> 24.28 | L24: =IFERROR(AVERAGEIFS($G$6:$G$119,$D$6:$D$119,$J24,$B$6:$B$119,L$4),"") -> 24.28 | M24: =IFERROR(AVERAGEIFS($G$6:$G$119,$D$6:$D$119,$J24,$B$6:$B$119,M$4),"") -> 24.28 | N24: =IFERROR(AVERAGEIFS($G$6:$G$119,$D$6:$D$119,$J24,$B$6:$B$119,N$4),"") -> 24.28 | O24: =IFERROR(AVERAGEIFS($G$6:$G$119,$D$6:$D$119,$J24,$B$6:$B$119,O$4),"") -> 24.28 | P24: =IFERROR(AVERAGEIFS($G$6:$G$119,$D$6:$D$119,$J24,$B$6:$B$119,P$4),"") -> 24.28 | Q24: =IF(OR(K24="",P24=""),"",P24/K24-1) -> 0 | R24: =IF(OR(L24="",M24=""),"",M24/L24-1) -> 0
A25: SOLU-CORTEF | B25: 45744 | C25: SOLU-CORTEF 100 mg Vial | D25: HSS 100 mg plain vial | E25: 18.24 | F25: 1 | G25: =E25/F25 -> 18.24 | H25: PDF
A26: SOLU-CORTEF | B26: 45866 | C26: SOLU-CORTEF 100 mg Vial | D26: HSS 100 mg plain vial | E26: 19.15 | F26: 1 | G26: =E26/F26 -> 19.15 | H26: PDF
A27: SOLU-CORTEF | B27: 45933 | C27: SOLU-CORTEF 100 mg Vial | D27: HSS 100 mg plain vial | E27: 19.15 | F27: 1 | G27: =E27/F27 -> 19.15 | H27: PDF | J27: Ratios used in the report
A28: SOLU-CORTEF | B28: 46031 | C28: SOLU-CORTEF 100 mg Vial | D28: HSS 100 mg plain vial | E28: 20.11 | F28: 1 | G28: =E28/F28 -> 20.11 | H28: PDF | J28: Measure | K28: Value | L28: Formula basis
A29: SOLU-CORTEF | B29: 46209 | C29: SOLU-CORTEF 100 mg Vial | D29: HSS 100 mg plain vial | E29: 20.11 | F29: 1 | G29: =E29/F29 -> 20.11 | H29: PDF | J29: Solu-Cortef: smallest Jul-24 to Jul-26 WAC change (single vials) | K29: =MIN(Q9,Q8,Q11,Q12,Q6) -> 0.17973856 | L29: Min of the five single-vial lines
A30: SOLU-CORTEF | B30: 45482 | C30: SOLU-CORTEF 250 MG ACT-O-VIAL | D30: HSS 250 mg Act-O-Vial (25-pack) | E30: 39.64 | F30: 1 | G30: =E30/F30 -> 39.64 | H30: PDF | J30: Solu-Cortef: largest Jul-24 to Jul-26 WAC change (single vials) | K30: =MAX(Q9,Q8,Q11,Q12,Q6) -> 0.29187689 | L30: Max of the five single-vial lines
A31: SOLU-CORTEF | B31: 45744 | C31: SOLU-CORTEF 250 mg/2 mL ACT-O-VIAL® | D31: HSS 250 mg Act-O-Vial (25-pack) | E31: 1040.43 | F31: 25 | G31: =E31/F31 -> 41.6172 | H31: PDF | J31: Solu-Cortef: smallest Jul-24 to Jul-26 change (25-pack lines) | K31: =MIN(Q7,Q10) -> 0.15755483 | L31: 2024 lists two NDCs per strength at per-vial prices; mapping to 25-pack lines assumed
A32: SOLU-CORTEF | B32: 45866 | C32: SOLU-CORTEF 250 mg/2 mL ACT-O-VIAL® | D32: HSS 250 mg Act-O-Vial (25-pack) | E32: 1092.45 | F32: 25 | G32: =E32/F32 -> 43.698 | H32: PDF | J32: Solu-Medrol: largest Mar-25 to Jul-25 cut | K32: =MIN(R13:R24) -> -0.42360164 | L32: Min of MPSS lines
A33: SOLU-CORTEF | B33: 45933 | C33: SOLU-CORTEF 250 mg/2 mL ACT-O-VIAL® | D33: HSS 250 mg Act-O-Vial (25-pack) | E33: 1092.45 | F33: 25 | G33: =E33/F33 -> 43.698 | H33: PDF | J33: Solu-Medrol: smallest Mar-25 to Jul-25 cut (lines that changed) | K33: =_xlfn.MAXIFS(R13:R24,R13:R24,"<0") -> -0.16998516 | L33: Largest negative change (MAXIFS)
A34: SOLU-CORTEF | B34: 46031 | C34: SOLU-CORTEF 250 mg/2 mL ACT-O-VIAL® | D34: HSS 250 mg Act-O-Vial (25-pack) | E34: 1201.7 | F34: 25 | G34: =E34/F34 -> 48.068 | H34: PDF | J34: Solu-Medrol: number of lines cut Mar-25 to Jul-25 | K34: =COUNTIF(R13:R24,"<0") -> 5 | L34: Count of negative changes
A35: SOLU-CORTEF | B35: 46209 | C35: SOLU-CORTEF 250 mg/2 mL ACT-O-VIAL® | D35: HSS 250 mg Act-O-Vial (25-pack) | E35: 1201.7 | F35: 25 | G35: =E35/F35 -> 48.068 | H35: PDF | J35: Solu-Medrol: 40 mg Act-O-Vial line A cut | K35: =R20 -> -0.24337121 | L35: Mar-25 to Jul-25
A36: SOLU-CORTEF | B36: 45482 | C36: SOLU-CORTEF 250 MG ACT-O-VIAL | D36: HSS 250 mg Act-O-Vial (single) | E36: 39.64 | F36: 1 | G36: =E36/F36 -> 39.64 | H36: PDF | J36: Solu-Medrol: 40 mg Act-O-Vial line C cut | K36: =R22 -> -0.16998516 | L36: Mar-25 to Jul-25
A37: SOLU-CORTEF | B37: 45744 | C37: SOLU-CORTEF 250 mg/2 mL ACT-O-VIAL® | D37: HSS 250 mg Act-O-Vial (single) | E37: 42.41 | F37: 1 | G37: =E37/F37 -> 42.41 | H37: PDF | J37: Solu-Medrol: 125 mg Act-O-Vial line A cut | K37: =R16 -> -0.2523337 | L37: Mar-25 to Jul-25
A38: SOLU-CORTEF | B38: 45866 | C38: SOLU-CORTEF 250 mg/2 mL ACT-O-VIAL® | D38: HSS 250 mg Act-O-Vial (single) | E38: 44.53 | F38: 1 | G38: =E38/F38 -> 44.53 | H38: PDF | J38: Solu-Medrol: 125 mg Act-O-Vial line C cut | K38: =R18 -> -0.17981109 | L38: Mar-25 to Jul-25
A39: SOLU-CORTEF | B39: 45933 | C39: SOLU-CORTEF 250 mg/2 mL ACT-O-VIAL® | D39: HSS 250 mg Act-O-Vial (single) | E39: 44.53 | F39: 1 | G39: =E39/F39 -> 44.53 | H39: PDF | J39: Solu-Medrol: 1 g multi-dose vial cut | K39: =R14 -> -0.42360164 | L39: Mar-25 to Jul-25
A40: SOLU-CORTEF | B40: 46031 | C40: SOLU-CORTEF 250 mg/2 mL ACT-O-VIAL® | D40: HSS 250 mg Act-O-Vial (single) | E40: 51.21 | F40: 1 | G40: =E40/F40 -> 51.21 | H40: PDF | J40: J1720 Q4'26 ASP / 100 mg Act-O-Vial WAC | K40: =ASP_growth!$I$11/P8 -> 0.86421366 | L40: ASP_growth / WAC Jul-26
A41: SOLU-CORTEF | B41: 46209 | C41: SOLU-CORTEF 250 mg/2 mL ACT-O-VIAL® | D41: HSS 250 mg Act-O-Vial (single) | E41: 51.21 | F41: 1 | G41: =E41/F41 -> 51.21 | H41: PDF | J41: J1720 Q4'26 ASP / 100 mg plain vial WAC | K41: =ASP_growth!$I$11/P9 -> 1.0859612 | L41: ASP_growth / WAC Jul-26
A42: SOLU-CORTEF | B42: 45482 | C42: SOLU-CORTEF 500 MG ACT-O-VIAL | D42: HSS 500 mg Act-O-Vial | E42: 79.31 | F42: 1 | G42: =E42/F42 -> 79.31 | H42: PDF | J42: Implied ASP / WAC, HSS 250 mg (2.5 units) | K42: =ASP_growth!$I$12/P11 -> 1.0661335 | L42: Shows blended-ASP artefact
A43: SOLU-CORTEF | B43: 45744 | C43: SOLU-CORTEF 500 mg/4 mL ACT-O-VIAL® | D43: HSS 500 mg Act-O-Vial | E43: 83.28 | F43: 1 | G43: =E43/F43 -> 83.28 | H43: PDF | J43: Implied ASP / WAC, HSS 500 mg | K43: =ASP_growth!$I$14/P12 -> 1.0858532 | L43: Shows blended-ASP artefact
A44: SOLU-CORTEF | B44: 45866 | C44: SOLU-CORTEF 500 mg/4 mL ACT-O-VIAL® | D44: HSS 500 mg Act-O-Vial | E44: 87.44 | F44: 1 | G44: =E44/F44 -> 87.44 | H44: PDF | J44: Implied ASP / WAC, HSS 1 g | K44: =ASP_growth!$I$15/P6 -> 1.0862312 | L44: Shows blended-ASP artefact
A45: SOLU-CORTEF | B45: 45933 | C45: SOLU-CORTEF 500 mg/4 mL ACT-O-VIAL® | D45: HSS 500 mg Act-O-Vial | E45: 87.44 | F45: 1 | G45: =E45/F45 -> 87.44 | H45: PDF | J45: HSS 250 mg WAC / 100 mg plain vial WAC | K45: =P11/P9 -> 2.5464943 | L45: Jul-26
A46: SOLU-CORTEF | B46: 46031 | C46: SOLU-CORTEF 500 mg/4 mL ACT-O-VIAL® | D46: HSS 500 mg Act-O-Vial | E46: 100.56 | F46: 1 | G46: =E46/F46 -> 100.56 | H46: PDF | J46: HSS 1 g WAC / 100 mg plain vial WAC | K46: =P6/P9 -> 9.9975137 | L46: Jul-26
A47: SOLU-CORTEF | B47: 46209 | C47: SOLU-CORTEF 500 mg/4 mL ACT-O-VIAL® | D47: HSS 500 mg Act-O-Vial | E47: 100.56 | F47: 1 | G47: =E47/F47 -> 100.56 | H47: PDF
A48: SOLU-MEDROL | B48: 45482 | C48: SOLU-MEDROL 1000 MG VIAL | D48: MPSS 1 g Act-O-Vial | E48: 68.92 | F48: 1 | G48: =E48/F48 -> 68.92 | H48: PDF
A49: SOLU-MEDROL | B49: 45744 | C49: SOLU-MEDROL 1 gm/8 mL ACT-O-VIAL® | D49: MPSS 1 g Act-O-Vial | E49: 68.92 | F49: 1 | G49: =E49/F49 -> 68.92 | H49: PDF
A50: SOLU-MEDROL | B50: 45866 | C50: SOLU-MEDROL 1 gm/8 mL ACT-O-VIAL® | D50: MPSS 1 g Act-O-Vial | E50: 68.92 | F50: 1 | G50: =E50/F50 -> 68.92 | H50: PDF
A51: SOLU-MEDROL | B51: 45933 | C51: SOLU-MEDROL 1 gm/8 mL ACT-O-VIAL® | D51: MPSS 1 g Act-O-Vial | E51: 68.92 | F51: 1 | G51: =E51/F51 -> 68.92 | H51: PDF
A52: SOLU-MEDROL | B52: 46031 | C52: SOLU-MEDROL 1 gm/8 mL ACT-O-VIAL® | D52: MPSS 1 g Act-O-Vial | E52: 68.92 | F52: 1 | G52: =E52/F52 -> 68.92 | H52: PDF
A53: SOLU-MEDROL | B53: 46209 | C53: SOLU-MEDROL 1 gm/8 mL ACT-O-VIAL® | D53: MPSS 1 g Act-O-Vial | E53: 68.92 | F53: 1 | G53: =E53/F53 -> 68.92 | H53: PDF
A54: SOLU-MEDROL | B54: 45482 | C54: SOLU-MEDROL 1 GRAM VIAL | D54: MPSS 1 g multi-dose vial | E54: 43.98 | F54: 1 | G54: =E54/F54 -> 43.98 | H54: PDF
A55: SOLU-MEDROL | B55: 45744 | C55: SOLU-MEDROL 1 gm/16 mL Multi-dose Vial | D55: MPSS 1 g multi-dose vial | E55: 43.98 | F55: 1 | G55: =E55/F55 -> 43.98 | H55: PDF
A56: SOLU-MEDROL | B56: 45866 | C56: SOLU-MEDROL 1 gm/16 mL Multi-dose Vial | D56: MPSS 1 g multi-dose vial | E56: 25.35 | F56: 1 | G56: =E56/F56 -> 25.35 | H56: PDF
A57: SOLU-MEDROL | B57: 45933 | C57: SOLU-MEDROL 1 gm/16 mL Multi-dose Vial | D57: MPSS 1 g multi-dose vial | E57: 25.35 | F57: 1 | G57: =E57/F57 -> 25.35 | H57: PDF
A58: SOLU-MEDROL | B58: 46031 | C58: SOLU-MEDROL 1 gm/16 mL Multi-dose Vial | D58: MPSS 1 g multi-dose vial | E58: 25.35 | F58: 1 | G58: =E58/F58 -> 25.35 | H58: PDF
... A119: SOLU-MEDROL | B119: 46209 | C119: SOLU-MEDROL 500 mg/8 mL Vial | D119: MPSS 500 mg vial | E119: 24.28 | F119: 1 | G119: =E119/F119 -> 24.28 | H119: PDF

Sheet NADAC
A1: NADAC per unit, latest effective rates at 21 Oct 2026
A2: Source S19. B = brand, G = generic. HSS and MPSS priced per vial (EA); MPA per mL.
A5: NDC description | B5: NDC | C5: Pricing unit | D5: Brand / generic | E5: NADAC per unit (US$) | F5: Effective date | G5: Source
A6: DEPO-MEDROL 40 MG/ML VIAL | B6: 00009307322 | C6: ML | D6: B | E6: 6.9022 | F6: 46316 | G6: S19
A7: DEPO-MEDROL 40 MG/ML VIAL | B7: 00009307301 | C7: ML | D7: B | E7: 6.9022 | F7: 46316 | G7: S19
A8: DEPO-MEDROL 80 MG/ML VIAL | B8: 00009347501 | C8: ML | D8: B | E8: 11.64531 | F8: 46316 | G8: S19
A9: HYDROCORTISONE SS 100 MG VIAL | B9: 70710190701 | C9: EA | D9: G | E9: 14.45933 | F9: 46316 | G9: S19
A10: HYDROCORTISONE SS 100 MG VIAL | B10: 69097000467 | C10: EA | D10: G | E10: 14.45933 | F10: 46316 | G10: S19
A11: HYDROCORTISONE SS 100 MG VIAL | B11: 60505641100 | C11: EA | D11: G | E11: 14.45933 | F11: 46316 | G11: S19
A12: METHYLPREDNISOLONE 40 MG/ML VL | B12: 60219157301 | C12: ML | D12: G | E12: 7.49 | F12: 46316 | G12: S19
A13: METHYLPREDNISOLONE 40 MG/ML VL | B13: 70121157301 | C13: ML | D13: G | E13: 7.49 | F13: 46316 | G13: S19
A14: METHYLPREDNISOLONE 400 MG/10 ML | B14: 00781352270 | C14: ML | D14: G | E14: 5.5662 | F14: 46316 | G14: S19
A15: METHYLPREDNISOLONE 400 MG/10 ML | B15: 55150031301 | C15: ML | D15: G | E15: 5.5662 | F15: 46316 | G15: S19
A16: METHYLPREDNISOLONE 400 MG/10 ML | B16: 25021082010 | C16: ML | D16: G | E16: 5.5662 | F16: 46316 | G16: S19
A17: METHYLPREDNISOLONE 400 MG/10 ML | B17: 70121160901 | C17: ML | D17: G | E17: 5.5662 | F17: 46316 | G17: S19
... A32: SOLU-MEDROL 40 MG VIAL | B32: 00009003932 | C32: EA | D32: B | E32: 6.28128 | F32: 46253 | G32: S19
A35: Generic vs brand
A36: Measure | E36: Value
A37: Generic MPSS 125 mg / Solu-Medrol 125 mg | E37: =E22/E29 -> 0.32523707
A38: Generic HSS 100 mg / Solu-Cortef 100 mg Act-O-Vial (00009001103) | E38: =E9/E25 -> 0.56643746
A39: Generic HSS 100 mg / Solu-Cortef 100 mg plain vial | E39: =E9/E27 -> 0.56203528
A40: Generic MPA 40 mg/mL / Depo-Medrol 40 mg/mL (per mL) | E40: =E12/E6 -> 1.0851613

Sheet SDUD_NDC_data
A1: Input: Medicaid SDUD national totals by NDC and year
A2: Sources S10-S18. Aggregated in Python from the national ('XX') rows for every NDC RxNorm links to these molecules. 2026 = Q1 only. Dollars are pre-rebate.
A5: NDC | B5: Year | C5: Company | D5: Molecule | E5: Strength | F5: Units reimbursed | G5: Prescriptions | H5: Amount reimbursed (US$) | I5: Source
A6: 00009000302 | B6: 2018 | C6: Pfizer (Pharmacia & Upjohn) - brand | D6: MPSS | E6: 500 mg | F6: 2010.9 | G6: 2544 | H6: 148091.13 | I6: S10
A7: 00009000302 | B7: 2019 | C7: Pfizer (Pharmacia & Upjohn) - brand | D7: MPSS | E7: 500 mg | F7: 1715.1 | G7: 2788 | H7: 119413.91 | I7: S11
A8: 00009000302 | B8: 2020 | C8: Pfizer (Pharmacia & Upjohn) - brand | D8: MPSS | E8: 500 mg | F8: 1721 | G8: 1921 | H8: 58967.35 | I8: S12
A9: 00009000302 | B9: 2021 | C9: Pfizer (Pharmacia & Upjohn) - brand | D9: MPSS | E9: 500 mg | F9: 1579.7 | G9: 1843 | H9: 92092.28 | I9: S13
A10: 00009000302 | B10: 2022 | C10: Pfizer (Pharmacia & Upjohn) - brand | D10: MPSS | E10: 500 mg | F10: 1412.4 | G10: 1631 | H10: 85188.79 | I10: S14
A11: 00009000302 | B11: 2023 | C11: Pfizer (Pharmacia & Upjohn) - brand | D11: MPSS | E11: 500 mg | F11: 877.1 | G11: 1509 | H11: 57815.14 | I11: S15
A12: 00009000302 | B12: 2024 | C12: Pfizer (Pharmacia & Upjohn) - brand | D12: MPSS | E12: 500 mg | F12: 3093.2 | G12: 1150 | H12: 42268.17 | I12: S16
A13: 00009000302 | B13: 2025 | C13: Pfizer (Pharmacia & Upjohn) - brand | D13: MPSS | E13: 500 mg | F13: 11424.3 | G13: 1551 | H13: 104068.14 | I13: S17
A14: 00009000302 | B14: 2026 | C14: Pfizer (Pharmacia & Upjohn) - brand | D14: MPSS | E14: 500 mg | F14: 500.9 | G14: 242 | H14: 42499.71 | I14: S18
A15: 00009000501 | B15: 2018 | C15: Pfizer (Pharmacia & Upjohn) - brand | D15: HSS | E15: 1000 mg | F15: 52.7 | G15: 163 | H15: 301782.16 | I15: S10
A16: 00009000501 | B16: 2019 | C16: Pfizer (Pharmacia & Upjohn) - brand | D16: HSS | E16: 1000 mg | F16: 43.9 | G16: 107 | H16: 122810.69 | I16: S11
A17: 00009000501 | B17: 2020 | C17: Pfizer (Pharmacia & Upjohn) - brand | D17: HSS | E17: 1000 mg | F17: 61.2 | G17: 129 | H17: 6132.43 | I17: S12
... A742: 72572009825 | B742: 2026 | C742: Civica (Hikma-made, ANDA203125) | D742: MPSS | E742: 125 mg | F742: 164.3 | G742: 21 | H742: 246.9 | I742: S18

Sheet Medicaid_SDUD
A1: Medicaid prescription shares by labeler (SUMIFS on SDUD_NDC_data)
A2: 2026 = Q1 only. Shares are of prescriptions (claims) unless stated.
A4: MPSS (Solu-Medrol and generics): prescriptions by labeler
A5: Labeler | B5: 2018 | C5: 2019 | D5: 2020 | E5: 2021 | F5: 2022 | G5: 2023 | H5: 2024 | I5: 2025 | J5: 2026
A6: Pfizer (Pharmacia & Upjohn) - brand | B6: =SUMIFS(SDUD_NDC_data!$G$6:$G$742,SDUD_NDC_data!$D$6:$D$742,"MPSS",SDUD_NDC_data!$C$6:$C$742,$A6,SDUD_NDC_data!$B$6:$B$742,"2018") -> 367337 | C6: =SUMIFS(SDUD_NDC_data!$G$6:$G$742,SDUD_NDC_data!$D$6:$D$742,"MPSS",SDUD_NDC_data!$C$6:$C$742,$A6,SDUD_NDC_data!$B$6:$B$742,"2019") -> 360827 | D6: =SUMIFS(SDUD_NDC_data!$G$6:$G$742,SDUD_NDC_data!$D$6:$D$742,"MPSS",SDUD_NDC_data!$C$6:$C$742,$A6,SDUD_NDC_data!$B$6:$B$742,"2020") -> 282664 | E6: =SUMIFS(SDUD_NDC_data!$G$6:$G$742,SDUD_NDC_data!$D$6:$D$742,"MPSS",SDUD_NDC_data!$C$6:$C$742,$A6,SDUD_NDC_data!$B$6:$B$742,"2021") -> 288572 | F6: =SUMIFS(SDUD_NDC_data!$G$6:$G$742,SDUD_NDC_data!$D$6:$D$742,"MPSS",SDUD_NDC_data!$C$6:$C$742,$A6,SDUD_NDC_data!$B$6:$B$742,"2022") -> 327272 | G6: =SUMIFS(SDUD_NDC_data!$G$6:$G$742,SDUD_NDC_data!$D$6:$D$742,"MPSS",SDUD_NDC_data!$C$6:$C$742,$A6,SDUD_NDC_data!$B$6:$B$742,"2023") -> 317625 | H6: =SUMIFS(SDUD_NDC_data!$G$6:$G$742,SDUD_NDC_data!$D$6:$D$742,"MPSS",SDUD_NDC_data!$C$6:$C$742,$A6,SDUD_NDC_data!$B$6:$B$742,"2024") -> 256676 | I6: =SUMIFS(SDUD_NDC_data!$G$6:$G$742,SDUD_NDC_data!$D$6:$D$742,"MPSS",SDUD_NDC_data!$C$6:$C$742,$A6,SDUD_NDC_data!$B$6:$B$742,"2025") -> 277730 | J6: =SUMIFS(SDUD_NDC_data!$G$6:$G$742,SDUD_NDC_data!$D$6:$D$742,"MPSS",SDUD_NDC_data!$C$6:$C$742,$A6,SDUD_NDC_data!$B$6:$B$742,"2026") -> 52341
A7: Fresenius Kabi | B7: =SUMIFS(SDUD_NDC_data!$G$6:$G$742,SDUD_NDC_data!$D$6:$D$742,"MPSS",SDUD_NDC_data!$C$6:$C$742,$A7,SDUD_NDC_data!$B$6:$B$742,"2018") -> 35667 | C7: =SUMIFS(SDUD_NDC_data!$G$6:$G$742,SDUD_NDC_data!$D$6:$D$742,"MPSS",SDUD_NDC_data!$C$6:$C$742,$A7,SDUD_NDC_data!$B$6:$B$742,"2019") -> 37454 | D7: =SUMIFS(SDUD_NDC_data!$G$6:$G$742,SDUD_NDC_data!$D$6:$D$742,"MPSS",SDUD_NDC_data!$C$6:$C$742,$A7,SDUD_NDC_data!$B$6:$B$742,"2020") -> 31167 | E7: =SUMIFS(SDUD_NDC_data!$G$6:$G$742,SDUD_NDC_data!$D$6:$D$742,"MPSS",SDUD_NDC_data!$C$6:$C$742,$A7,SDUD_NDC_data!$B$6:$B$742,"2021") -> 41796 | F7: =SUMIFS(SDUD_NDC_data!$G$6:$G$742,SDUD_NDC_data!$D$6:$D$742,"MPSS",SDUD_NDC_data!$C$6:$C$742,$A7,SDUD_NDC_data!$B$6:$B$742,"2022") -> 44073 | G7: =SUMIFS(SDUD_NDC_data!$G$6:$G$742,SDUD_NDC_data!$D$6:$D$742,"MPSS",SDUD_NDC_data!$C$6:$C$742,$A7,SDUD_NDC_data!$B$6:$B$742,"2023") -> 48597 | H7: =SUMIFS(SDUD_NDC_data!$G$6:$G$742,SDUD_NDC_data!$D$6:$D$742,"MPSS",SDUD_NDC_data!$C$6:$C$742,$A7,SDUD_NDC_data!$B$6:$B$742,"2024") -> 36515 | I7: =SUMIFS(SDUD_NDC_data!$G$6:$G$742,SDUD_NDC_data!$D$6:$D$742,"MPSS",SDUD_NDC_data!$C$6:$C$742,$A7,SDUD_NDC_data!$B$6:$B$742,"2025") -> 32295 | J7: =SUMIFS(SDUD_NDC_data!$G$6:$G$742,SDUD_NDC_data!$D$6:$D$742,"MPSS",SDUD_NDC_data!$C$6:$C$742,$A7,SDUD_NDC_data!$B$6:$B$742,"2026") -> 4300
A8: Dr. Reddy's | B8: =SUMIFS(SDUD_NDC_data!$G$6:$G$742,SDUD_NDC_data!$D$6:$D$742,"MPSS",SDUD_NDC_data!$C$6:$C$742,$A8,SDUD_NDC_data!$B$6:$B$742,"2018") -> 0 | C8: =SUMIFS(SDUD_NDC_data!$G$6:$G$742,SDUD_NDC_data!$D$6:$D$742,"MPSS",SDUD_NDC_data!$C$6:$C$742,$A8,SDUD_NDC_data!$B$6:$B$742,"2019") -> 0 | D8: =SUMIFS(SDUD_NDC_data!$G$6:$G$742,SDUD_NDC_data!$D$6:$D$742,"MPSS",SDUD_NDC_data!$C$6:$C$742,$A8,SDUD_NDC_data!$B$6:$B$742,"2020") -> 0 | E8: =SUMIFS(SDUD_NDC_data!$G$6:$G$742,SDUD_NDC_data!$D$6:$D$742,"MPSS",SDUD_NDC_data!$C$6:$C$742,$A8,SDUD_NDC_data!$B$6:$B$742,"2021") -> 0 | F8: =SUMIFS(SDUD_NDC_data!$G$6:$G$742,SDUD_NDC_data!$D$6:$D$742,"MPSS",SDUD_NDC_data!$C$6:$C$742,$A8,SDUD_NDC_data!$B$6:$B$742,"2022") -> 1385 | G8: =SUMIFS(SDUD_NDC_data!$G$6:$G$742,SDUD_NDC_data!$D$6:$D$742,"MPSS",SDUD_NDC_data!$C$6:$C$742,$A8,SDUD_NDC_data!$B$6:$B$742,"2023") -> 16685 | H8: =SUMIFS(SDUD_NDC_data!$G$6:$G$742,SDUD_NDC_data!$D$6:$D$742,"MPSS",SDUD_NDC_data!$C$6:$C$742,$A8,SDUD_NDC_data!$B$6:$B$742,"2024") -> 24609 | I8: =SUMIFS(SDUD_NDC_data!$G$6:$G$742,SDUD_NDC_data!$D$6:$D$742,"MPSS",SDUD_NDC_data!$C$6:$C$742,$A8,SDUD_NDC_data!$B$6:$B$742,"2025") -> 45597 | J8: =SUMIFS(SDUD_NDC_data!$G$6:$G$742,SDUD_NDC_data!$D$6:$D$742,"MPSS",SDUD_NDC_data!$C$6:$C$742,$A8,SDUD_NDC_data!$B$6:$B$742,"2026") -> 11976
A9: Hikma (West-Ward) | B9: =SUMIFS(SDUD_NDC_data!$G$6:$G$742,SDUD_NDC_data!$D$6:$D$742,"MPSS",SDUD_NDC_data!$C$6:$C$742,$A9,SDUD_NDC_data!$B$6:$B$742,"2018") -> 0 | C9: =SUMIFS(SDUD_NDC_data!$G$6:$G$742,SDUD_NDC_data!$D$6:$D$742,"MPSS",SDUD_NDC_data!$C$6:$C$742,$A9,SDUD_NDC_data!$B$6:$B$742,"2019") -> 0 | D9: =SUMIFS(SDUD_NDC_data!$G$6:$G$742,SDUD_NDC_data!$D$6:$D$742,"MPSS",SDUD_NDC_data!$C$6:$C$742,$A9,SDUD_NDC_data!$B$6:$B$742,"2020") -> 604 | E9: =SUMIFS(SDUD_NDC_data!$G$6:$G$742,SDUD_NDC_data!$D$6:$D$742,"MPSS",SDUD_NDC_data!$C$6:$C$742,$A9,SDUD_NDC_data!$B$6:$B$742,"2021") -> 811 | F9: =SUMIFS(SDUD_NDC_data!$G$6:$G$742,SDUD_NDC_data!$D$6:$D$742,"MPSS",SDUD_NDC_data!$C$6:$C$742,$A9,SDUD_NDC_data!$B$6:$B$742,"2022") -> 807 | G9: =SUMIFS(SDUD_NDC_data!$G$6:$G$742,SDUD_NDC_data!$D$6:$D$742,"MPSS",SDUD_NDC_data!$C$6:$C$742,$A9,SDUD_NDC_data!$B$6:$B$742,"2023") -> 3338 | H9: =SUMIFS(SDUD_NDC_data!$G$6:$G$742,SDUD_NDC_data!$D$6:$D$742,"MPSS",SDUD_NDC_data!$C$6:$C$742,$A9,SDUD_NDC_data!$B$6:$B$742,"2024") -> 6922 | I9: =SUMIFS(SDUD_NDC_data!$G$6:$G$742,SDUD_NDC_data!$D$6:$D$742,"MPSS",SDUD_NDC_data!$C$6:$C$742,$A9,SDUD_NDC_data!$B$6:$B$742,"2025") -> 14590 | J9: =SUMIFS(SDUD_NDC_data!$G$6:$G$742,SDUD_NDC_data!$D$6:$D$742,"MPSS",SDUD_NDC_data!$C$6:$C$742,$A9,SDUD_NDC_data!$B$6:$B$742,"2026") -> 2253
A10: Amneal | B10: =SUMIFS(SDUD_NDC_data!$G$6:$G$742,SDUD_NDC_data!$D$6:$D$742,"MPSS",SDUD_NDC_data!$C$6:$C$742,$A10,SDUD_NDC_data!$B$6:$B$742,"2018") -> 1052 | C10: =SUMIFS(SDUD_NDC_data!$G$6:$G$742,SDUD_NDC_data!$D$6:$D$742,"MPSS",SDUD_NDC_data!$C$6:$C$742,$A10,SDUD_NDC_data!$B$6:$B$742,"2019") -> 992 | D10: =SUMIFS(SDUD_NDC_data!$G$6:$G$742,SDUD_NDC_data!$D$6:$D$742,"MPSS",SDUD_NDC_data!$C$6:$C$742,$A10,SDUD_NDC_data!$B$6:$B$742,"2020") -> 773 | E10: =SUMIFS(SDUD_NDC_data!$G$6:$G$742,SDUD_NDC_data!$D$6:$D$742,"MPSS",SDUD_NDC_data!$C$6:$C$742,$A10,SDUD_NDC_data!$B$6:$B$742,"2021") -> 715 | F10: =SUMIFS(SDUD_NDC_data!$G$6:$G$742,SDUD_NDC_data!$D$6:$D$742,"MPSS",SDUD_NDC_data!$C$6:$C$742,$A10,SDUD_NDC_data!$B$6:$B$742,"2022") -> 898 | G10: =SUMIFS(SDUD_NDC_data!$G$6:$G$742,SDUD_NDC_data!$D$6:$D$742,"MPSS",SDUD_NDC_data!$C$6:$C$742,$A10,SDUD_NDC_data!$B$6:$B$742,"2023") -> 1886 | H10: =SUMIFS(SDUD_NDC_data!$G$6:$G$742,SDUD_NDC_data!$D$6:$D$742,"MPSS",SDUD_NDC_data!$C$6:$C$742,$A10,SDUD_NDC_data!$B$6:$B$742,"2024") -> 389 | I10: =SUMIFS(SDUD_NDC_data!$G$6:$G$742,SDUD_NDC_data!$D$6:$D$742,"MPSS",SDUD_NDC_data!$C$6:$C$742,$A10,SDUD_NDC_data!$B$6:$B$742,"2025") -> 26 | J10: =SUMIFS(SDUD_NDC_data!$G$6:$G$742,SDUD_NDC_data!$D$6:$D$742,"MPSS",SDUD_NDC_data!$C$6:$C$742,$A10,SDUD_NDC_data!$B$6:$B$742,"2026") -> 13
A11: Sagent | B11: =SUMIFS(SDUD_NDC_data!$G$6:$G$742,SDUD_NDC_data!$D$6:$D$742,"MPSS",SDUD_NDC_data!$C$6:$C$742,$A11,SDUD_NDC_data!$B$6:$B$742,"2018") -> 1339 | C11: =SUMIFS(SDUD_NDC_data!$G$6:$G$742,SDUD_NDC_data!$D$6:$D$742,"MPSS",SDUD_NDC_data!$C$6:$C$742,$A11,SDUD_NDC_data!$B$6:$B$742,"2019") -> 1288 | D11: =SUMIFS(SDUD_NDC_data!$G$6:$G$742,SDUD_NDC_data!$D$6:$D$742,"MPSS",SDUD_NDC_data!$C$6:$C$742,$A11,SDUD_NDC_data!$B$6:$B$742,"2020") -> 897 | E11: =SUMIFS(SDUD_NDC_data!$G$6:$G$742,SDUD_NDC_data!$D$6:$D$742,"MPSS",SDUD_NDC_data!$C$6:$C$742,$A11,SDUD_NDC_data!$B$6:$B$742,"2021") -> 685 | F11: =SUMIFS(SDUD_NDC_data!$G$6:$G$742,SDUD_NDC_data!$D$6:$D$742,"MPSS",SDUD_NDC_data!$C$6:$C$742,$A11,SDUD_NDC_data!$B$6:$B$742,"2022") -> 653 | G11: =SUMIFS(SDUD_NDC_data!$G$6:$G$742,SDUD_NDC_data!$D$6:$D$742,"MPSS",SDUD_NDC_data!$C$6:$C$742,$A11,SDUD_NDC_data!$B$6:$B$742,"2023") -> 430 | H11: =SUMIFS(SDUD_NDC_data!$G$6:$G$742,SDUD_NDC_data!$D$6:$D$742,"MPSS",SDUD_NDC_data!$C$6:$C$742,$A11,SDUD_NDC_data!$B$6:$B$742,"2024") -> 322 | I11: =SUMIFS(SDUD_NDC_data!$G$6:$G$742,SDUD_NDC_data!$D$6:$D$742,"MPSS",SDUD_NDC_data!$C$6:$C$742,$A11,SDUD_NDC_data!$B$6:$B$742,"2025") -> 30 | J11: =SUMIFS(SDUD_NDC_data!$G$6:$G$742,SDUD_NDC_data!$D$6:$D$742,"MPSS",SDUD_NDC_data!$C$6:$C$742,$A11,SDUD_NDC_data!$B$6:$B$742,"2026") -> 0
A12: Pfizer/Hospira (A-Methapred/A-Hydrocort ANDA) | B12: =SUMIFS(SDUD_NDC_data!$G$6:$G$742,SDUD_NDC_data!$D$6:$D$742,"MPSS",SDUD_NDC_data!$C$6:$C$742,$A12,SDUD_NDC_data!$B$6:$B$742,"2018") -> 141 | C12: =SUMIFS(SDUD_NDC_data!$G$6:$G$742,SDUD_NDC_data!$D$6:$D$742,"MPSS",SDUD_NDC_data!$C$6:$C$742,$A12,SDUD_NDC_data!$B$6:$B$742,"2019") -> 111 | D12: =SUMIFS(SDUD_NDC_data!$G$6:$G$742,SDUD_NDC_data!$D$6:$D$742,"MPSS",SDUD_NDC_data!$C$6:$C$742,$A12,SDUD_NDC_data!$B$6:$B$742,"2020") -> 46 | E12: =SUMIFS(SDUD_NDC_data!$G$6:$G$742,SDUD_NDC_data!$D$6:$D$742,"MPSS",SDUD_NDC_data!$C$6:$C$742,$A12,SDUD_NDC_data!$B$6:$B$742,"2021") -> 0 | F12: =SUMIFS(SDUD_NDC_data!$G$6:$G$742,SDUD_NDC_data!$D$6:$D$742,"MPSS",SDUD_NDC_data!$C$6:$C$742,$A12,SDUD_NDC_data!$B$6:$B$742,"2022") -> 0 | G12: =SUMIFS(SDUD_NDC_data!$G$6:$G$742,SDUD_NDC_data!$D$6:$D$742,"MPSS",SDUD_NDC_data!$C$6:$C$742,$A12,SDUD_NDC_data!$B$6:$B$742,"2023") -> 0 | H12: =SUMIFS(SDUD_NDC_data!$G$6:$G$742,SDUD_NDC_data!$D$6:$D$742,"MPSS",SDUD_NDC_data!$C$6:$C$742,$A12,SDUD_NDC_data!$B$6:$B$742,"2024") -> 0 | I12: =SUMIFS(SDUD_NDC_data!$G$6:$G$742,SDUD_NDC_data!$D$6:$D$742,"MPSS",SDUD_NDC_data!$C$6:$C$742,$A12,SDUD_NDC_data!$B$6:$B$742,"2025") -> 0 | J12: =SUMIFS(SDUD_NDC_data!$G$6:$G$742,SDUD_NDC_data!$D$6:$D$742,"MPSS",SDUD_NDC_data!$C$6:$C$742,$A12,SDUD_NDC_data!$B$6:$B$742,"2026") -> 0
A13: Civica (Hikma-made, ANDA203125) | B13: =SUMIFS(SDUD_NDC_data!$G$6:$G$742,SDUD_NDC_data!$D$6:$D$742,"MPSS",SDUD_NDC_data!$C$6:$C$742,$A13,SDUD_NDC_data!$B$6:$B$742,"2018") -> 0 | C13: =SUMIFS(SDUD_NDC_data!$G$6:$G$742,SDUD_NDC_data!$D$6:$D$742,"MPSS",SDUD_NDC_data!$C$6:$C$742,$A13,SDUD_NDC_data!$B$6:$B$742,"2019") -> 0 | D13: =SUMIFS(SDUD_NDC_data!$G$6:$G$742,SDUD_NDC_data!$D$6:$D$742,"MPSS",SDUD_NDC_data!$C$6:$C$742,$A13,SDUD_NDC_data!$B$6:$B$742,"2020") -> 0 | E13: =SUMIFS(SDUD_NDC_data!$G$6:$G$742,SDUD_NDC_data!$D$6:$D$742,"MPSS",SDUD_NDC_data!$C$6:$C$742,$A13,SDUD_NDC_data!$B$6:$B$742,"2021") -> 0 | F13: =SUMIFS(SDUD_NDC_data!$G$6:$G$742,SDUD_NDC_data!$D$6:$D$742,"MPSS",SDUD_NDC_data!$C$6:$C$742,$A13,SDUD_NDC_data!$B$6:$B$742,"2022") -> 0 | G13: =SUMIFS(SDUD_NDC_data!$G$6:$G$742,SDUD_NDC_data!$D$6:$D$742,"MPSS",SDUD_NDC_data!$C$6:$C$742,$A13,SDUD_NDC_data!$B$6:$B$742,"2023") -> 0 | H13: =SUMIFS(SDUD_NDC_data!$G$6:$G$742,SDUD_NDC_data!$D$6:$D$742,"MPSS",SDUD_NDC_data!$C$6:$C$742,$A13,SDUD_NDC_data!$B$6:$B$742,"2024") -> 0 | I13: =SUMIFS(SDUD_NDC_data!$G$6:$G$742,SDUD_NDC_data!$D$6:$D$742,"MPSS",SDUD_NDC_data!$C$6:$C$742,$A13,SDUD_NDC_data!$B$6:$B$742,"2025") -> 0 | J13: =SUMIFS(SDUD_NDC_data!$G$6:$G$742,SDUD_NDC_data!$D$6:$D$742,"MPSS",SDUD_NDC_data!$C$6:$C$742,$A13,SDUD_NDC_data!$B$6:$B$742,"2026") -> 48
A14: Total (all NDCs for molecule) | B14: =SUMIFS(SDUD_NDC_data!$G$6:$G$742,SDUD_NDC_data!$D$6:$D$742,"MPSS",SDUD_NDC_data!$B$6:$B$742,"2018") -> 405536 | C14: =SUMIFS(SDUD_NDC_data!$G$6:$G$742,SDUD_NDC_data!$D$6:$D$742,"MPSS",SDUD_NDC_data!$B$6:$B$742,"2019") -> 400672 | D14: =SUMIFS(SDUD_NDC_data!$G$6:$G$742,SDUD_NDC_data!$D$6:$D$742,"MPSS",SDUD_NDC_data!$B$6:$B$742,"2020") -> 316151 | E14: =SUMIFS(SDUD_NDC_data!$G$6:$G$742,SDUD_NDC_data!$D$6:$D$742,"MPSS",SDUD_NDC_data!$B$6:$B$742,"2021") -> 332579 | F14: =SUMIFS(SDUD_NDC_data!$G$6:$G$742,SDUD_NDC_data!$D$6:$D$742,"MPSS",SDUD_NDC_data!$B$6:$B$742,"2022") -> 375088 | G14: =SUMIFS(SDUD_NDC_data!$G$6:$G$742,SDUD_NDC_data!$D$6:$D$742,"MPSS",SDUD_NDC_data!$B$6:$B$742,"2023") -> 388561 | H14: =SUMIFS(SDUD_NDC_data!$G$6:$G$742,SDUD_NDC_data!$D$6:$D$742,"MPSS",SDUD_NDC_data!$B$6:$B$742,"2024") -> 325433 | I14: =SUMIFS(SDUD_NDC_data!$G$6:$G$742,SDUD_NDC_data!$D$6:$D$742,"MPSS",SDUD_NDC_data!$B$6:$B$742,"2025") -> 370268 | J14: =SUMIFS(SDUD_NDC_data!$G$6:$G$742,SDUD_NDC_data!$D$6:$D$742,"MPSS",SDUD_NDC_data!$B$6:$B$742,"2026") -> 70931
A15: Check: listed labelers minus total (should be 0) | B15: =SUM(B6:B13)-B14 -> 0 | C15: =SUM(C6:C13)-C14 -> 0 | D15: =SUM(D6:D13)-D14 -> 0 | E15: =SUM(E6:E13)-E14 -> 0 | F15: =SUM(F6:F13)-F14 -> 0 | G15: =SUM(G6:G13)-G14 -> 0 | H15: =SUM(H6:H13)-H14 -> 0 | I15: =SUM(I6:I13)-I14 -> 0 | J15: =SUM(J6:J13)-J14 -> 0
A16: MPSS (Solu-Medrol and generics): share of prescriptions
A17: Labeler | B17: 2018 | C17: 2019 | D17: 2020 | E17: 2021 | F17: 2022 | G17: 2023 | H17: 2024 | I17: 2025 | J17: 2026
A18: Pfizer (Pharmacia & Upjohn) - brand | B18: =IF(B$14=0,0,B6/B$14) -> 0.90580614 | C18: =IF(C$14=0,0,C6/C$14) -> 0.90055457 | D18: =IF(D$14=0,0,D6/D$14) -> 0.8940791 | E18: =IF(E$14=0,0,E6/E$14) -> 0.86767956 | F18: =IF(F$14=0,0,F6/F$14) -> 0.87252058 | G18: =IF(G$14=0,0,G6/G$14) -> 0.81743922 | H18: =IF(H$14=0,0,H6/H$14) -> 0.78872149 | I18: =IF(I$14=0,0,I6/I$14) -> 0.75007832 | J18: =IF(J$14=0,0,J6/J$14) -> 0.73791431
A19: Fresenius Kabi | B19: =IF(B$14=0,0,B7/B$14) -> 0.087950268 | C19: =IF(C$14=0,0,C7/C$14) -> 0.093477957 | D19: =IF(D$14=0,0,D7/D$14) -> 0.098582639 | E19: =IF(E$14=0,0,E7/E$14) -> 0.1256724 | F19: =IF(F$14=0,0,F7/F$14) -> 0.11750043 | G19: =IF(G$14=0,0,G7/G$14) -> 0.12506917 | H19: =IF(H$14=0,0,H7/H$14) -> 0.11220436 | I19: =IF(I$14=0,0,I7/I$14) -> 0.087220608 | J19: =IF(J$14=0,0,J7/J$14) -> 0.060622295
A20: Dr. Reddy's | B20: =IF(B$14=0,0,B8/B$14) -> 0 | C20: =IF(C$14=0,0,C8/C$14) -> 0 | D20: =IF(D$14=0,0,D8/D$14) -> 0 | E20: =IF(E$14=0,0,E8/E$14) -> 0 | F20: =IF(F$14=0,0,F8/F$14) -> 0.0036924668 | G20: =IF(G$14=0,0,G8/G$14) -> 0.042940491 | H20: =IF(H$14=0,0,H8/H$14) -> 0.075619252 | I20: =IF(I$14=0,0,I8/I$14) -> 0.12314594 | J20: =IF(J$14=0,0,J8/J$14) -> 0.16884014
A21: Hikma (West-Ward) | B21: =IF(B$14=0,0,B9/B$14) -> 0 | C21: =IF(C$14=0,0,C9/C$14) -> 0 | D21: =IF(D$14=0,0,D9/D$14) -> 0.0019104795 | E21: =IF(E$14=0,0,E9/E$14) -> 0.0024385184 | F21: =IF(F$14=0,0,F9/F$14) -> 0.0021514951 | G21: =IF(G$14=0,0,G9/G$14) -> 0.0085906717 | H21: =IF(H$14=0,0,H9/H$14) -> 0.021270123 | I21: =IF(I$14=0,0,I9/I$14) -> 0.039403891 | J21: =IF(J$14=0,0,J9/J$14) -> 0.031763263
A22: Amneal | B22: =IF(B$14=0,0,B10/B$14) -> 0.0025940977 | C22: =IF(C$14=0,0,C10/C$14) -> 0.0024758406 | D22: =IF(D$14=0,0,D10/D$14) -> 0.0024450342 | E22: =IF(E$14=0,0,E10/E$14) -> 0.0021498651 | F22: =IF(F$14=0,0,F10/F$14) -> 0.0023941049 | G22: =IF(G$14=0,0,G10/G$14) -> 0.0048538067 | H22: =IF(H$14=0,0,H10/H$14) -> 0.0011953305 | I22: =IF(I$14=0,0,I10/I$14) -> 7.0219409e-05 | J22: =IF(J$14=0,0,J10/J$14) -> 0.00018327671
A23: Sagent | B23: =IF(B$14=0,0,B11/B$14) -> 0.003301803 | C23: =IF(C$14=0,0,C11/C$14) -> 0.0032145995 | D23: =IF(D$14=0,0,D11/D$14) -> 0.0028372518 | E23: =IF(E$14=0,0,E11/E$14) -> 0.002059661 | F23: =IF(F$14=0,0,F11/F$14) -> 0.0017409248 | G23: =IF(G$14=0,0,G11/G$14) -> 0.0011066473 | H23: =IF(H$14=0,0,H11/H$14) -> 0.00098945098 | I23: =IF(I$14=0,0,I11/I$14) -> 8.1022395e-05 | J23: =IF(J$14=0,0,J11/J$14) -> 0
A24: Pfizer/Hospira (A-Methapred/A-Hydrocort ANDA) | B24: =IF(B$14=0,0,B12/B$14) -> 0.000347688 | C24: =IF(C$14=0,0,C12/C$14) -> 0.00027703458 | D24: =IF(D$14=0,0,D12/D$14) -> 0.00014550009 | E24: =IF(E$14=0,0,E12/E$14) -> 0 | F24: =IF(F$14=0,0,F12/F$14) -> 0 | G24: =IF(G$14=0,0,G12/G$14) -> 0 | H24: =IF(H$14=0,0,H12/H$14) -> 0 | I24: =IF(I$14=0,0,I12/I$14) -> 0 | J24: =IF(J$14=0,0,J12/J$14) -> 0
A25: Civica (Hikma-made, ANDA203125) | B25: =IF(B$14=0,0,B13/B$14) -> 0 | C25: =IF(C$14=0,0,C13/C$14) -> 0 | D25: =IF(D$14=0,0,D13/D$14) -> 0 | E25: =IF(E$14=0,0,E13/E$14) -> 0 | F25: =IF(F$14=0,0,F13/F$14) -> 0 | G25: =IF(G$14=0,0,G13/G$14) -> 0 | H25: =IF(H$14=0,0,H13/H$14) -> 0 | I25: =IF(I$14=0,0,I13/I$14) -> 0 | J25: =IF(J$14=0,0,J13/J$14) -> 0.00067671399
A28: HSS (Solu-Cortef and generics): prescriptions by labeler
A29: Labeler | B29: 2018 | C29: 2019 | D29: 2020 | E29: 2021 | F29: 2022 | G29: 2023 | H29: 2024 | I29: 2025 | J29: 2026
A30: Pfizer (Pharmacia & Upjohn) - brand | B30: =SUMIFS(SDUD_NDC_data!$G$6:$G$742,SDUD_NDC_data!$D$6:$D$742,"HSS",SDUD_NDC_data!$C$6:$C$742,$A30,SDUD_NDC_data!$B$6:$B$742,"2018") -> 34702 | C30: =SUMIFS(SDUD_NDC_data!$G$6:$G$742,SDUD_NDC_data!$D$6:$D$742,"HSS",SDUD_NDC_data!$C$6:$C$742,$A30,SDUD_NDC_data!$B$6:$B$742,"2019") -> 38160 | D30: =SUMIFS(SDUD_NDC_data!$G$6:$G$742,SDUD_NDC_data!$D$6:$D$742,"HSS",SDUD_NDC_data!$C$6:$C$742,$A30,SDUD_NDC_data!$B$6:$B$742,"2020") -> 37053 | E30: =SUMIFS(SDUD_NDC_data!$G$6:$G$742,SDUD_NDC_data!$D$6:$D$742,"HSS",SDUD_NDC_data!$C$6:$C$742,$A30,SDUD_NDC_data!$B$6:$B$742,"2021") -> 40478 | F30: =SUMIFS(SDUD_NDC_data!$G$6:$G$742,SDUD_NDC_data!$D$6:$D$742,"HSS",SDUD_NDC_data!$C$6:$C$742,$A30,SDUD_NDC_data!$B$6:$B$742,"2022") -> 42706 | G30: =SUMIFS(SDUD_NDC_data!$G$6:$G$742,SDUD_NDC_data!$D$6:$D$742,"HSS",SDUD_NDC_data!$C$6:$C$742,$A30,SDUD_NDC_data!$B$6:$B$742,"2023") -> 35759 | H30: =SUMIFS(SDUD_NDC_data!$G$6:$G$742,SDUD_NDC_data!$D$6:$D$742,"HSS",SDUD_NDC_data!$C$6:$C$742,$A30,SDUD_NDC_data!$B$6:$B$742,"2024") -> 37111 | I30: =SUMIFS(SDUD_NDC_data!$G$6:$G$742,SDUD_NDC_data!$D$6:$D$742,"HSS",SDUD_NDC_data!$C$6:$C$742,$A30,SDUD_NDC_data!$B$6:$B$742,"2025") -> 35293 | J30: =SUMIFS(SDUD_NDC_data!$G$6:$G$742,SDUD_NDC_data!$D$6:$D$742,"HSS",SDUD_NDC_data!$C$6:$C$742,$A30,SDUD_NDC_data!$B$6:$B$742,"2026") -> 7327
A31: Cipla | B31: =SUMIFS(SDUD_NDC_data!$G$6:$G$742,SDUD_NDC_data!$D$6:$D$742,"HSS",SDUD_NDC_data!$C$6:$C$742,$A31,SDUD_NDC_data!$B$6:$B$742,"2018") -> 0 | C31: =SUMIFS(SDUD_NDC_data!$G$6:$G$742,SDUD_NDC_data!$D$6:$D$742,"HSS",SDUD_NDC_data!$C$6:$C$742,$A31,SDUD_NDC_data!$B$6:$B$742,"2019") -> 0 | D31: =SUMIFS(SDUD_NDC_data!$G$6:$G$742,SDUD_NDC_data!$D$6:$D$742,"HSS",SDUD_NDC_data!$C$6:$C$742,$A31,SDUD_NDC_data!$B$6:$B$742,"2020") -> 0 | E31: =SUMIFS(SDUD_NDC_data!$G$6:$G$742,SDUD_NDC_data!$D$6:$D$742,"HSS",SDUD_NDC_data!$C$6:$C$742,$A31,SDUD_NDC_data!$B$6:$B$742,"2021") -> 0 | F31: =SUMIFS(SDUD_NDC_data!$G$6:$G$742,SDUD_NDC_data!$D$6:$D$742,"HSS",SDUD_NDC_data!$C$6:$C$742,$A31,SDUD_NDC_data!$B$6:$B$742,"2022") -> 0 | G31: =SUMIFS(SDUD_NDC_data!$G$6:$G$742,SDUD_NDC_data!$D$6:$D$742,"HSS",SDUD_NDC_data!$C$6:$C$742,$A31,SDUD_NDC_data!$B$6:$B$742,"2023") -> 0 | H31: =SUMIFS(SDUD_NDC_data!$G$6:$G$742,SDUD_NDC_data!$D$6:$D$742,"HSS",SDUD_NDC_data!$C$6:$C$742,$A31,SDUD_NDC_data!$B$6:$B$742,"2024") -> 131 | I31: =SUMIFS(SDUD_NDC_data!$G$6:$G$742,SDUD_NDC_data!$D$6:$D$742,"HSS",SDUD_NDC_data!$C$6:$C$742,$A31,SDUD_NDC_data!$B$6:$B$742,"2025") -> 2010 | J31: =SUMIFS(SDUD_NDC_data!$G$6:$G$742,SDUD_NDC_data!$D$6:$D$742,"HSS",SDUD_NDC_data!$C$6:$C$742,$A31,SDUD_NDC_data!$B$6:$B$742,"2026") -> 533
A32: Pfizer/Hospira (A-Methapred/A-Hydrocort ANDA) | B32: =SUMIFS(SDUD_NDC_data!$G$6:$G$742,SDUD_NDC_data!$D$6:$D$742,"HSS",SDUD_NDC_data!$C$6:$C$742,$A32,SDUD_NDC_data!$B$6:$B$742,"2018") -> 64 | C32: =SUMIFS(SDUD_NDC_data!$G$6:$G$742,SDUD_NDC_data!$D$6:$D$742,"HSS",SDUD_NDC_data!$C$6:$C$742,$A32,SDUD_NDC_data!$B$6:$B$742,"2019") -> 25 | D32: =SUMIFS(SDUD_NDC_data!$G$6:$G$742,SDUD_NDC_data!$D$6:$D$742,"HSS",SDUD_NDC_data!$C$6:$C$742,$A32,SDUD_NDC_data!$B$6:$B$742,"2020") -> 58 | E32: =SUMIFS(SDUD_NDC_data!$G$6:$G$742,SDUD_NDC_data!$D$6:$D$742,"HSS",SDUD_NDC_data!$C$6:$C$742,$A32,SDUD_NDC_data!$B$6:$B$742,"2021") -> 13 | F32: =SUMIFS(SDUD_NDC_data!$G$6:$G$742,SDUD_NDC_data!$D$6:$D$742,"HSS",SDUD_NDC_data!$C$6:$C$742,$A32,SDUD_NDC_data!$B$6:$B$742,"2022") -> 0 | G32: =SUMIFS(SDUD_NDC_data!$G$6:$G$742,SDUD_NDC_data!$D$6:$D$742,"HSS",SDUD_NDC_data!$C$6:$C$742,$A32,SDUD_NDC_data!$B$6:$B$742,"2023") -> 0 | H32: =SUMIFS(SDUD_NDC_data!$G$6:$G$742,SDUD_NDC_data!$D$6:$D$742,"HSS",SDUD_NDC_data!$C$6:$C$742,$A32,SDUD_NDC_data!$B$6:$B$742,"2024") -> 0 | I32: =SUMIFS(SDUD_NDC_data!$G$6:$G$742,SDUD_NDC_data!$D$6:$D$742,"HSS",SDUD_NDC_data!$C$6:$C$742,$A32,SDUD_NDC_data!$B$6:$B$742,"2025") -> 0 | J32: =SUMIFS(SDUD_NDC_data!$G$6:$G$742,SDUD_NDC_data!$D$6:$D$742,"HSS",SDUD_NDC_data!$C$6:$C$742,$A32,SDUD_NDC_data!$B$6:$B$742,"2026") -> 0
A33: Total (all NDCs for molecule) | B33: =SUMIFS(SDUD_NDC_data!$G$6:$G$742,SDUD_NDC_data!$D$6:$D$742,"HSS",SDUD_NDC_data!$B$6:$B$742,"2018") -> 34766 | C33: =SUMIFS(SDUD_NDC_data!$G$6:$G$742,SDUD_NDC_data!$D$6:$D$742,"HSS",SDUD_NDC_data!$B$6:$B$742,"2019") -> 38185 | D33: =SUMIFS(SDUD_NDC_data!$G$6:$G$742,SDUD_NDC_data!$D$6:$D$742,"HSS",SDUD_NDC_data!$B$6:$B$742,"2020") -> 37111 | E33: =SUMIFS(SDUD_NDC_data!$G$6:$G$742,SDUD_NDC_data!$D$6:$D$742,"HSS",SDUD_NDC_data!$B$6:$B$742,"2021") -> 40491 | F33: =SUMIFS(SDUD_NDC_data!$G$6:$G$742,SDUD_NDC_data!$D$6:$D$742,"HSS",SDUD_NDC_data!$B$6:$B$742,"2022") -> 42706 | G33: =SUMIFS(SDUD_NDC_data!$G$6:$G$742,SDUD_NDC_data!$D$6:$D$742,"HSS",SDUD_NDC_data!$B$6:$B$742,"2023") -> 35759 | H33: =SUMIFS(SDUD_NDC_data!$G$6:$G$742,SDUD_NDC_data!$D$6:$D$742,"HSS",SDUD_NDC_data!$B$6:$B$742,"2024") -> 37242 | I33: =SUMIFS(SDUD_NDC_data!$G$6:$G$742,SDUD_NDC_data!$D$6:$D$742,"HSS",SDUD_NDC_data!$B$6:$B$742,"2025") -> 37303 | J33: =SUMIFS(SDUD_NDC_data!$G$6:$G$742,SDUD_NDC_data!$D$6:$D$742,"HSS",SDUD_NDC_data!$B$6:$B$742,"2026") -> 7860
A34: Check: listed labelers minus total (should be 0) | B34: =SUM(B30:B32)-B33 -> 0 | C34: =SUM(C30:C32)-C33 -> 0 | D34: =SUM(D30:D32)-D33 -> 0 | E34: =SUM(E30:E32)-E33 -> 0 | F34: =SUM(F30:F32)-F33 -> 0 | G34: =SUM(G30:G32)-G33 -> 0 | H34: =SUM(H30:H32)-H33 -> 0 | I34: =SUM(I30:I32)-I33 -> 0 | J34: =SUM(J30:J32)-J33 -> 0
A35: HSS (Solu-Cortef and generics): share of prescriptions
A36: Labeler | B36: 2018 | C36: 2019 | D36: 2020 | E36: 2021 | F36: 2022 | G36: 2023 | H36: 2024 | I36: 2025 | J36: 2026
A37: Pfizer (Pharmacia & Upjohn) - brand | B37: =IF(B$33=0,0,B30/B$33) -> 0.99815912 | C37: =IF(C$33=0,0,C30/C$33) -> 0.99934529 | D37: =IF(D$33=0,0,D30/D$33) -> 0.99843712 | E37: =IF(E$33=0,0,E30/E$33) -> 0.99967894 | F37: =IF(F$33=0,0,F30/F$33) -> 1 | G37: =IF(G$33=0,0,G30/G$33) -> 1 | H37: =IF(H$33=0,0,H30/H$33) -> 0.99648247 | I37: =IF(I$33=0,0,I30/I$33) -> 0.94611693 | J37: =IF(J$33=0,0,J30/J$33) -> 0.9321883
A38: Cipla | B38: =IF(B$33=0,0,B31/B$33) -> 0 | C38: =IF(C$33=0,0,C31/C$33) -> 0 | D38: =IF(D$33=0,0,D31/D$33) -> 0 | E38: =IF(E$33=0,0,E31/E$33) -> 0 | F38: =IF(F$33=0,0,F31/F$33) -> 0 | G38: =IF(G$33=0,0,G31/G$33) -> 0 | H38: =IF(H$33=0,0,H31/H$33) -> 0.003517534 | I38: =IF(I$33=0,0,I31/I$33) -> 0.053883066 | J38: =IF(J$33=0,0,J31/J$33) -> 0.067811705
A39: Pfizer/Hospira (A-Methapred/A-Hydrocort ANDA) | B39: =IF(B$33=0,0,B32/B$33) -> 0.001840879 | C39: =IF(C$33=0,0,C32/C$33) -> 0.00065470735 | D39: =IF(D$33=0,0,D32/D$33) -> 0.0015628789 | E39: =IF(E$33=0,0,E32/E$33) -> 0.000321059 | F39: =IF(F$33=0,0,F32/F$33) -> 0 | G39: =IF(G$33=0,0,G32/G$33) -> 0 | H39: =IF(H$33=0,0,H32/H$33) -> 0 | I39: =IF(I$33=0,0,I32/I$33) -> 0 | J39: =IF(J$33=0,0,J32/J$33) -> 0
A42: MPA (Depo-Medrol and generics): prescriptions by labeler
A43: Labeler | B43: 2018 | C43: 2019 | D43: 2020 | E43: 2021 | F43: 2022 | G43: 2023 | H43: 2024 | I43: 2025 | J43: 2026
A44: Pfizer (Pharmacia & Upjohn) - brand | B44: =SUMIFS(SDUD_NDC_data!$G$6:$G$742,SDUD_NDC_data!$D$6:$D$742,"MPA",SDUD_NDC_data!$C$6:$C$742,$A44,SDUD_NDC_data!$B$6:$B$742,"2018") -> 809490 | C44: =SUMIFS(SDUD_NDC_data!$G$6:$G$742,SDUD_NDC_data!$D$6:$D$742,"MPA",SDUD_NDC_data!$C$6:$C$742,$A44,SDUD_NDC_data!$B$6:$B$742,"2019") -> 729236 | D44: =SUMIFS(SDUD_NDC_data!$G$6:$G$742,SDUD_NDC_data!$D$6:$D$742,"MPA",SDUD_NDC_data!$C$6:$C$742,$A44,SDUD_NDC_data!$B$6:$B$742,"2020") -> 616634 | E44: =SUMIFS(SDUD_NDC_data!$G$6:$G$742,SDUD_NDC_data!$D$6:$D$742,"MPA",SDUD_NDC_data!$C$6:$C$742,$A44,SDUD_NDC_data!$B$6:$B$742,"2021") -> 584491 | F44: =SUMIFS(SDUD_NDC_data!$G$6:$G$742,SDUD_NDC_data!$D$6:$D$742,"MPA",SDUD_NDC_data!$C$6:$C$742,$A44,SDUD_NDC_data!$B$6:$B$742,"2022") -> 342286 | G44: =SUMIFS(SDUD_NDC_data!$G$6:$G$742,SDUD_NDC_data!$D$6:$D$742,"MPA",SDUD_NDC_data!$C$6:$C$742,$A44,SDUD_NDC_data!$B$6:$B$742,"2023") -> 398075 | H44: =SUMIFS(SDUD_NDC_data!$G$6:$G$742,SDUD_NDC_data!$D$6:$D$742,"MPA",SDUD_NDC_data!$C$6:$C$742,$A44,SDUD_NDC_data!$B$6:$B$742,"2024") -> 300636 | I44: =SUMIFS(SDUD_NDC_data!$G$6:$G$742,SDUD_NDC_data!$D$6:$D$742,"MPA",SDUD_NDC_data!$C$6:$C$742,$A44,SDUD_NDC_data!$B$6:$B$742,"2025") -> 319559 | J44: =SUMIFS(SDUD_NDC_data!$G$6:$G$742,SDUD_NDC_data!$D$6:$D$742,"MPA",SDUD_NDC_data!$C$6:$C$742,$A44,SDUD_NDC_data!$B$6:$B$742,"2026") -> 62980
A45: Teva | B45: =SUMIFS(SDUD_NDC_data!$G$6:$G$742,SDUD_NDC_data!$D$6:$D$742,"MPA",SDUD_NDC_data!$C$6:$C$742,$A45,SDUD_NDC_data!$B$6:$B$742,"2018") -> 100556 | C45: =SUMIFS(SDUD_NDC_data!$G$6:$G$742,SDUD_NDC_data!$D$6:$D$742,"MPA",SDUD_NDC_data!$C$6:$C$742,$A45,SDUD_NDC_data!$B$6:$B$742,"2019") -> 177921 | D45: =SUMIFS(SDUD_NDC_data!$G$6:$G$742,SDUD_NDC_data!$D$6:$D$742,"MPA",SDUD_NDC_data!$C$6:$C$742,$A45,SDUD_NDC_data!$B$6:$B$742,"2020") -> 192916 | E45: =SUMIFS(SDUD_NDC_data!$G$6:$G$742,SDUD_NDC_data!$D$6:$D$742,"MPA",SDUD_NDC_data!$C$6:$C$742,$A45,SDUD_NDC_data!$B$6:$B$742,"2021") -> 234736 | F45: =SUMIFS(SDUD_NDC_data!$G$6:$G$742,SDUD_NDC_data!$D$6:$D$742,"MPA",SDUD_NDC_data!$C$6:$C$742,$A45,SDUD_NDC_data!$B$6:$B$742,"2022") -> 107225 | G45: =SUMIFS(SDUD_NDC_data!$G$6:$G$742,SDUD_NDC_data!$D$6:$D$742,"MPA",SDUD_NDC_data!$C$6:$C$742,$A45,SDUD_NDC_data!$B$6:$B$742,"2023") -> 59479 | H45: =SUMIFS(SDUD_NDC_data!$G$6:$G$742,SDUD_NDC_data!$D$6:$D$742,"MPA",SDUD_NDC_data!$C$6:$C$742,$A45,SDUD_NDC_data!$B$6:$B$742,"2024") -> 4094 | I45: =SUMIFS(SDUD_NDC_data!$G$6:$G$742,SDUD_NDC_data!$D$6:$D$742,"MPA",SDUD_NDC_data!$C$6:$C$742,$A45,SDUD_NDC_data!$B$6:$B$742,"2025") -> 263 | J45: =SUMIFS(SDUD_NDC_data!$G$6:$G$742,SDUD_NDC_data!$D$6:$D$742,"MPA",SDUD_NDC_data!$C$6:$C$742,$A45,SDUD_NDC_data!$B$6:$B$742,"2026") -> 43
A46: Amneal | B46: =SUMIFS(SDUD_NDC_data!$G$6:$G$742,SDUD_NDC_data!$D$6:$D$742,"MPA",SDUD_NDC_data!$C$6:$C$742,$A46,SDUD_NDC_data!$B$6:$B$742,"2018") -> 0 | C46: =SUMIFS(SDUD_NDC_data!$G$6:$G$742,SDUD_NDC_data!$D$6:$D$742,"MPA",SDUD_NDC_data!$C$6:$C$742,$A46,SDUD_NDC_data!$B$6:$B$742,"2019") -> 0 | D46: =SUMIFS(SDUD_NDC_data!$G$6:$G$742,SDUD_NDC_data!$D$6:$D$742,"MPA",SDUD_NDC_data!$C$6:$C$742,$A46,SDUD_NDC_data!$B$6:$B$742,"2020") -> 417 | E46: =SUMIFS(SDUD_NDC_data!$G$6:$G$742,SDUD_NDC_data!$D$6:$D$742,"MPA",SDUD_NDC_data!$C$6:$C$742,$A46,SDUD_NDC_data!$B$6:$B$742,"2021") -> 11536 | F46: =SUMIFS(SDUD_NDC_data!$G$6:$G$742,SDUD_NDC_data!$D$6:$D$742,"MPA",SDUD_NDC_data!$C$6:$C$742,$A46,SDUD_NDC_data!$B$6:$B$742,"2022") -> 101150 | G46: =SUMIFS(SDUD_NDC_data!$G$6:$G$742,SDUD_NDC_data!$D$6:$D$742,"MPA",SDUD_NDC_data!$C$6:$C$742,$A46,SDUD_NDC_data!$B$6:$B$742,"2023") -> 143171 | H46: =SUMIFS(SDUD_NDC_data!$G$6:$G$742,SDUD_NDC_data!$D$6:$D$742,"MPA",SDUD_NDC_data!$C$6:$C$742,$A46,SDUD_NDC_data!$B$6:$B$742,"2024") -> 140100 | I46: =SUMIFS(SDUD_NDC_data!$G$6:$G$742,SDUD_NDC_data!$D$6:$D$742,"MPA",SDUD_NDC_data!$C$6:$C$742,$A46,SDUD_NDC_data!$B$6:$B$742,"2025") -> 178095 | J46: =SUMIFS(SDUD_NDC_data!$G$6:$G$742,SDUD_NDC_data!$D$6:$D$742,"MPA",SDUD_NDC_data!$C$6:$C$742,$A46,SDUD_NDC_data!$B$6:$B$742,"2026") -> 37873
A47: Sagent | B47: =SUMIFS(SDUD_NDC_data!$G$6:$G$742,SDUD_NDC_data!$D$6:$D$742,"MPA",SDUD_NDC_data!$C$6:$C$742,$A47,SDUD_NDC_data!$B$6:$B$742,"2018") -> 0 | C47: =SUMIFS(SDUD_NDC_data!$G$6:$G$742,SDUD_NDC_data!$D$6:$D$742,"MPA",SDUD_NDC_data!$C$6:$C$742,$A47,SDUD_NDC_data!$B$6:$B$742,"2019") -> 0 | D47: =SUMIFS(SDUD_NDC_data!$G$6:$G$742,SDUD_NDC_data!$D$6:$D$742,"MPA",SDUD_NDC_data!$C$6:$C$742,$A47,SDUD_NDC_data!$B$6:$B$742,"2020") -> 0 | E47: =SUMIFS(SDUD_NDC_data!$G$6:$G$742,SDUD_NDC_data!$D$6:$D$742,"MPA",SDUD_NDC_data!$C$6:$C$742,$A47,SDUD_NDC_data!$B$6:$B$742,"2021") -> 0 | F47: =SUMIFS(SDUD_NDC_data!$G$6:$G$742,SDUD_NDC_data!$D$6:$D$742,"MPA",SDUD_NDC_data!$C$6:$C$742,$A47,SDUD_NDC_data!$B$6:$B$742,"2022") -> 7675 | G47: =SUMIFS(SDUD_NDC_data!$G$6:$G$742,SDUD_NDC_data!$D$6:$D$742,"MPA",SDUD_NDC_data!$C$6:$C$742,$A47,SDUD_NDC_data!$B$6:$B$742,"2023") -> 19780 | H47: =SUMIFS(SDUD_NDC_data!$G$6:$G$742,SDUD_NDC_data!$D$6:$D$742,"MPA",SDUD_NDC_data!$C$6:$C$742,$A47,SDUD_NDC_data!$B$6:$B$742,"2024") -> 28478 | I47: =SUMIFS(SDUD_NDC_data!$G$6:$G$742,SDUD_NDC_data!$D$6:$D$742,"MPA",SDUD_NDC_data!$C$6:$C$742,$A47,SDUD_NDC_data!$B$6:$B$742,"2025") -> 26593 | J47: =SUMIFS(SDUD_NDC_data!$G$6:$G$742,SDUD_NDC_data!$D$6:$D$742,"MPA",SDUD_NDC_data!$C$6:$C$742,$A47,SDUD_NDC_data!$B$6:$B$742,"2026") -> 6182
A48: Northstar Rx (Teva-made ANDAs) | B48: =SUMIFS(SDUD_NDC_data!$G$6:$G$742,SDUD_NDC_data!$D$6:$D$742,"MPA",SDUD_NDC_data!$C$6:$C$742,$A48,SDUD_NDC_data!$B$6:$B$742,"2018") -> 0 | C48: =SUMIFS(SDUD_NDC_data!$G$6:$G$742,SDUD_NDC_data!$D$6:$D$742,"MPA",SDUD_NDC_data!$C$6:$C$742,$A48,SDUD_NDC_data!$B$6:$B$742,"2019") -> 0 | D48: =SUMIFS(SDUD_NDC_data!$G$6:$G$742,SDUD_NDC_data!$D$6:$D$742,"MPA",SDUD_NDC_data!$C$6:$C$742,$A48,SDUD_NDC_data!$B$6:$B$742,"2020") -> 0 | E48: =SUMIFS(SDUD_NDC_data!$G$6:$G$742,SDUD_NDC_data!$D$6:$D$742,"MPA",SDUD_NDC_data!$C$6:$C$742,$A48,SDUD_NDC_data!$B$6:$B$742,"2021") -> 3217 | F48: =SUMIFS(SDUD_NDC_data!$G$6:$G$742,SDUD_NDC_data!$D$6:$D$742,"MPA",SDUD_NDC_data!$C$6:$C$742,$A48,SDUD_NDC_data!$B$6:$B$742,"2022") -> 21433 | G48: =SUMIFS(SDUD_NDC_data!$G$6:$G$742,SDUD_NDC_data!$D$6:$D$742,"MPA",SDUD_NDC_data!$C$6:$C$742,$A48,SDUD_NDC_data!$B$6:$B$742,"2023") -> 2588 | H48: =SUMIFS(SDUD_NDC_data!$G$6:$G$742,SDUD_NDC_data!$D$6:$D$742,"MPA",SDUD_NDC_data!$C$6:$C$742,$A48,SDUD_NDC_data!$B$6:$B$742,"2024") -> 16 | I48: =SUMIFS(SDUD_NDC_data!$G$6:$G$742,SDUD_NDC_data!$D$6:$D$742,"MPA",SDUD_NDC_data!$C$6:$C$742,$A48,SDUD_NDC_data!$B$6:$B$742,"2025") -> 76 | J48: =SUMIFS(SDUD_NDC_data!$G$6:$G$742,SDUD_NDC_data!$D$6:$D$742,"MPA",SDUD_NDC_data!$C$6:$C$742,$A48,SDUD_NDC_data!$B$6:$B$742,"2026") -> 0
A49: Endo/Par Sterile | B49: =SUMIFS(SDUD_NDC_data!$G$6:$G$742,SDUD_NDC_data!$D$6:$D$742,"MPA",SDUD_NDC_data!$C$6:$C$742,$A49,SDUD_NDC_data!$B$6:$B$742,"2018") -> 0 | C49: =SUMIFS(SDUD_NDC_data!$G$6:$G$742,SDUD_NDC_data!$D$6:$D$742,"MPA",SDUD_NDC_data!$C$6:$C$742,$A49,SDUD_NDC_data!$B$6:$B$742,"2019") -> 0 | D49: =SUMIFS(SDUD_NDC_data!$G$6:$G$742,SDUD_NDC_data!$D$6:$D$742,"MPA",SDUD_NDC_data!$C$6:$C$742,$A49,SDUD_NDC_data!$B$6:$B$742,"2020") -> 0 | E49: =SUMIFS(SDUD_NDC_data!$G$6:$G$742,SDUD_NDC_data!$D$6:$D$742,"MPA",SDUD_NDC_data!$C$6:$C$742,$A49,SDUD_NDC_data!$B$6:$B$742,"2021") -> 0 | F49: =SUMIFS(SDUD_NDC_data!$G$6:$G$742,SDUD_NDC_data!$D$6:$D$742,"MPA",SDUD_NDC_data!$C$6:$C$742,$A49,SDUD_NDC_data!$B$6:$B$742,"2022") -> 285 | G49: =SUMIFS(SDUD_NDC_data!$G$6:$G$742,SDUD_NDC_data!$D$6:$D$742,"MPA",SDUD_NDC_data!$C$6:$C$742,$A49,SDUD_NDC_data!$B$6:$B$742,"2023") -> 2129 | H49: =SUMIFS(SDUD_NDC_data!$G$6:$G$742,SDUD_NDC_data!$D$6:$D$742,"MPA",SDUD_NDC_data!$C$6:$C$742,$A49,SDUD_NDC_data!$B$6:$B$742,"2024") -> 7388 | I49: =SUMIFS(SDUD_NDC_data!$G$6:$G$742,SDUD_NDC_data!$D$6:$D$742,"MPA",SDUD_NDC_data!$C$6:$C$742,$A49,SDUD_NDC_data!$B$6:$B$742,"2025") -> 6989 | J49: =SUMIFS(SDUD_NDC_data!$G$6:$G$742,SDUD_NDC_data!$D$6:$D$742,"MPA",SDUD_NDC_data!$C$6:$C$742,$A49,SDUD_NDC_data!$B$6:$B$742,"2026") -> 1251
A50: Sandoz | B50: =SUMIFS(SDUD_NDC_data!$G$6:$G$742,SDUD_NDC_data!$D$6:$D$742,"MPA",SDUD_NDC_data!$C$6:$C$742,$A50,SDUD_NDC_data!$B$6:$B$742,"2018") -> 2668 | C50: =SUMIFS(SDUD_NDC_data!$G$6:$G$742,SDUD_NDC_data!$D$6:$D$742,"MPA",SDUD_NDC_data!$C$6:$C$742,$A50,SDUD_NDC_data!$B$6:$B$742,"2019") -> 1917 | D50: =SUMIFS(SDUD_NDC_data!$G$6:$G$742,SDUD_NDC_data!$D$6:$D$742,"MPA",SDUD_NDC_data!$C$6:$C$742,$A50,SDUD_NDC_data!$B$6:$B$742,"2020") -> 1129 | E50: =SUMIFS(SDUD_NDC_data!$G$6:$G$742,SDUD_NDC_data!$D$6:$D$742,"MPA",SDUD_NDC_data!$C$6:$C$742,$A50,SDUD_NDC_data!$B$6:$B$742,"2021") -> 1191 | F50: =SUMIFS(SDUD_NDC_data!$G$6:$G$742,SDUD_NDC_data!$D$6:$D$742,"MPA",SDUD_NDC_data!$C$6:$C$742,$A50,SDUD_NDC_data!$B$6:$B$742,"2022") -> 217 | G50: =SUMIFS(SDUD_NDC_data!$G$6:$G$742,SDUD_NDC_data!$D$6:$D$742,"MPA",SDUD_NDC_data!$C$6:$C$742,$A50,SDUD_NDC_data!$B$6:$B$742,"2023") -> 268 | H50: =SUMIFS(SDUD_NDC_data!$G$6:$G$742,SDUD_NDC_data!$D$6:$D$742,"MPA",SDUD_NDC_data!$C$6:$C$742,$A50,SDUD_NDC_data!$B$6:$B$742,"2024") -> 2053 | I50: =SUMIFS(SDUD_NDC_data!$G$6:$G$742,SDUD_NDC_data!$D$6:$D$742,"MPA",SDUD_NDC_data!$C$6:$C$742,$A50,SDUD_NDC_data!$B$6:$B$742,"2025") -> 6017 | J50: =SUMIFS(SDUD_NDC_data!$G$6:$G$742,SDUD_NDC_data!$D$6:$D$742,"MPA",SDUD_NDC_data!$C$6:$C$742,$A50,SDUD_NDC_data!$B$6:$B$742,"2026") -> 1107
A51: Eugia (Aurobindo) | B51: =SUMIFS(SDUD_NDC_data!$G$6:$G$742,SDUD_NDC_data!$D$6:$D$742,"MPA",SDUD_NDC_data!$C$6:$C$742,$A51,SDUD_NDC_data!$B$6:$B$742,"2018") -> 0 | C51: =SUMIFS(SDUD_NDC_data!$G$6:$G$742,SDUD_NDC_data!$D$6:$D$742,"MPA",SDUD_NDC_data!$C$6:$C$742,$A51,SDUD_NDC_data!$B$6:$B$742,"2019") -> 0 | D51: =SUMIFS(SDUD_NDC_data!$G$6:$G$742,SDUD_NDC_data!$D$6:$D$742,"MPA",SDUD_NDC_data!$C$6:$C$742,$A51,SDUD_NDC_data!$B$6:$B$742,"2020") -> 0 | E51: =SUMIFS(SDUD_NDC_data!$G$6:$G$742,SDUD_NDC_data!$D$6:$D$742,"MPA",SDUD_NDC_data!$C$6:$C$742,$A51,SDUD_NDC_data!$B$6:$B$742,"2021") -> 0 | F51: =SUMIFS(SDUD_NDC_data!$G$6:$G$742,SDUD_NDC_data!$D$6:$D$742,"MPA",SDUD_NDC_data!$C$6:$C$742,$A51,SDUD_NDC_data!$B$6:$B$742,"2022") -> 0 | G51: =SUMIFS(SDUD_NDC_data!$G$6:$G$742,SDUD_NDC_data!$D$6:$D$742,"MPA",SDUD_NDC_data!$C$6:$C$742,$A51,SDUD_NDC_data!$B$6:$B$742,"2023") -> 225 | H51: =SUMIFS(SDUD_NDC_data!$G$6:$G$742,SDUD_NDC_data!$D$6:$D$742,"MPA",SDUD_NDC_data!$C$6:$C$742,$A51,SDUD_NDC_data!$B$6:$B$742,"2024") -> 3706 | I51: =SUMIFS(SDUD_NDC_data!$G$6:$G$742,SDUD_NDC_data!$D$6:$D$742,"MPA",SDUD_NDC_data!$C$6:$C$742,$A51,SDUD_NDC_data!$B$6:$B$742,"2025") -> 4655 | J51: =SUMIFS(SDUD_NDC_data!$G$6:$G$742,SDUD_NDC_data!$D$6:$D$742,"MPA",SDUD_NDC_data!$C$6:$C$742,$A51,SDUD_NDC_data!$B$6:$B$742,"2026") -> 494
A52: Total (all NDCs for molecule) | B52: =SUMIFS(SDUD_NDC_data!$G$6:$G$742,SDUD_NDC_data!$D$6:$D$742,"MPA",SDUD_NDC_data!$B$6:$B$742,"2018") -> 912714 | C52: =SUMIFS(SDUD_NDC_data!$G$6:$G$742,SDUD_NDC_data!$D$6:$D$742,"MPA",SDUD_NDC_data!$B$6:$B$742,"2019") -> 909074 | D52: =SUMIFS(SDUD_NDC_data!$G$6:$G$742,SDUD_NDC_data!$D$6:$D$742,"MPA",SDUD_NDC_data!$B$6:$B$742,"2020") -> 811096 | E52: =SUMIFS(SDUD_NDC_data!$G$6:$G$742,SDUD_NDC_data!$D$6:$D$742,"MPA",SDUD_NDC_data!$B$6:$B$742,"2021") -> 835171 | F52: =SUMIFS(SDUD_NDC_data!$G$6:$G$742,SDUD_NDC_data!$D$6:$D$742,"MPA",SDUD_NDC_data!$B$6:$B$742,"2022") -> 580271 | G52: =SUMIFS(SDUD_NDC_data!$G$6:$G$742,SDUD_NDC_data!$D$6:$D$742,"MPA",SDUD_NDC_data!$B$6:$B$742,"2023") -> 625715 | H52: =SUMIFS(SDUD_NDC_data!$G$6:$G$742,SDUD_NDC_data!$D$6:$D$742,"MPA",SDUD_NDC_data!$B$6:$B$742,"2024") -> 486471 | I52: =SUMIFS(SDUD_NDC_data!$G$6:$G$742,SDUD_NDC_data!$D$6:$D$742,"MPA",SDUD_NDC_data!$B$6:$B$742,"2025") -> 542247 | J52: =SUMIFS(SDUD_NDC_data!$G$6:$G$742,SDUD_NDC_data!$D$6:$D$742,"MPA",SDUD_NDC_data!$B$6:$B$742,"2026") -> 109930
A53: Check: listed labelers minus total (should be 0) | B53: =SUM(B44:B51)-B52 -> 0 | C53: =SUM(C44:C51)-C52 -> 0 | D53: =SUM(D44:D51)-D52 -> 0 | E53: =SUM(E44:E51)-E52 -> 0 | F53: =SUM(F44:F51)-F52 -> 0 | G53: =SUM(G44:G51)-G52 -> 0 | H53: =SUM(H44:H51)-H52 -> 0 | I53: =SUM(I44:I51)-I52 -> 0 | J53: =SUM(J44:J51)-J52 -> 0
A54: MPA (Depo-Medrol and generics): share of prescriptions
A55: Labeler | B55: 2018 | C55: 2019 | D55: 2020 | E55: 2021 | F55: 2022 | G55: 2023 | H55: 2024 | I55: 2025 | J55: 2026
A56: Pfizer (Pharmacia & Upjohn) - brand | B56: =IF(B$52=0,0,B44/B$52) -> 0.88690433 | C56: =IF(C$52=0,0,C44/C$52) -> 0.80217452 | D56: =IF(D$52=0,0,D44/D$52) -> 0.76024786 | E56: =IF(E$52=0,0,E44/E$52) -> 0.6998459 | F56: =IF(F$52=0,0,F44/F$52) -> 0.58987266 | G56: =IF(G$52=0,0,G44/G$52) -> 0.6361922 | H56: =IF(H$52=0,0,H44/H$52) -> 0.61799367 | I56: =IF(I$52=0,0,I44/I$52) -> 0.58932368 | J56: =IF(J$52=0,0,J44/J$52) -> 0.57291003
A57: Teva | B57: =IF(B$52=0,0,B45/B$52) -> 0.11017252 | C57: =IF(C$52=0,0,C45/C$52) -> 0.19571674 | D57: =IF(D$52=0,0,D45/D$52) -> 0.23784607 | E57: =IF(E$52=0,0,E45/E$52) -> 0.2810634 | F57: =IF(F$52=0,0,F45/F$52) -> 0.18478435 | G57: =IF(G$52=0,0,G45/G$52) -> 0.095057654 | H57: =IF(H$52=0,0,H45/H$52) -> 0.0084157123 | I57: =IF(I$52=0,0,I45/I$52) -> 0.00048501882 | J57: =IF(J$52=0,0,J45/J$52) -> 0.00039115801
A58: Amneal | B58: =IF(B$52=0,0,B46/B$52) -> 0 | C58: =IF(C$52=0,0,C46/C$52) -> 0 | D58: =IF(D$52=0,0,D46/D$52) -> 0.00051411917 | E58: =IF(E$52=0,0,E46/E$52) -> 0.01381274 | F58: =IF(F$52=0,0,F46/F$52) -> 0.1743151 | G58: =IF(G$52=0,0,G46/G$52) -> 0.22881184 | H58: =IF(H$52=0,0,H46/H$52) -> 0.2879925 | I58: =IF(I$52=0,0,I46/I$52) -> 0.32843888 | J58: =IF(J$52=0,0,J46/J$52) -> 0.34451924
A59: Sagent | B59: =IF(B$52=0,0,B47/B$52) -> 0 | C59: =IF(C$52=0,0,C47/C$52) -> 0 | D59: =IF(D$52=0,0,D47/D$52) -> 0 | E59: =IF(E$52=0,0,E47/E$52) -> 0 | F59: =IF(F$52=0,0,F47/F$52) -> 0.013226579 | G59: =IF(G$52=0,0,G47/G$52) -> 0.031611836 | H59: =IF(H$52=0,0,H47/H$52) -> 0.058539975 | I59: =IF(I$52=0,0,I47/I$52) -> 0.049042226 | J59: =IF(J$52=0,0,J47/J$52) -> 0.056235786
A60: Northstar Rx (Teva-made ANDAs) | B60: =IF(B$52=0,0,B48/B$52) -> 0 | C60: =IF(C$52=0,0,C48/C$52) -> 0 | D60: =IF(D$52=0,0,D48/D$52) -> 0 | E60: =IF(E$52=0,0,E48/E$52) -> 0.0038519058 | F60: =IF(F$52=0,0,F48/F$52) -> 0.03693619 | G60: =IF(G$52=0,0,G48/G$52) -> 0.0041360683 | H60: =IF(H$52=0,0,H48/H$52) -> 3.2889936e-05 | I60: =IF(I$52=0,0,I48/I$52) -> 0.00014015753 | J60: =IF(J$52=0,0,J48/J$52) -> 0
A61: Endo/Par Sterile | B61: =IF(B$52=0,0,B49/B$52) -> 0 | C61: =IF(C$52=0,0,C49/C$52) -> 0 | D61: =IF(D$52=0,0,D49/D$52) -> 0 | E61: =IF(E$52=0,0,E49/E$52) -> 0 | F61: =IF(F$52=0,0,F49/F$52) -> 0.00049114982 | G61: =IF(G$52=0,0,G49/G$52) -> 0.0034025075 | H61: =IF(H$52=0,0,H49/H$52) -> 0.015186928 | I61: =IF(I$52=0,0,I49/I$52) -> 0.01288896 | J61: =IF(J$52=0,0,J49/J$52) -> 0.011379969
A62: Sandoz | B62: =IF(B$52=0,0,B50/B$52) -> 0.0029231501 | C62: =IF(C$52=0,0,C50/C$52) -> 0.0021087392 | D62: =IF(D$52=0,0,D50/D$52) -> 0.0013919437 | E62: =IF(E$52=0,0,E50/E$52) -> 0.0014260553 | F62: =IF(F$52=0,0,F50/F$52) -> 0.0003739632 | G62: =IF(G$52=0,0,G50/G$52) -> 0.00042831001 | H62: =IF(H$52=0,0,H50/H$52) -> 0.0042201899 | I62: =IF(I$52=0,0,I50/I$52) -> 0.011096419 | J62: =IF(J$52=0,0,J50/J$52) -> 0.010070045
A63: Eugia (Aurobindo) | B63: =IF(B$52=0,0,B51/B$52) -> 0 | C63: =IF(C$52=0,0,C51/C$52) -> 0 | D63: =IF(D$52=0,0,D51/D$52) -> 0 | E63: =IF(E$52=0,0,E51/E$52) -> 0 | F63: =IF(F$52=0,0,F51/F$52) -> 0 | G63: =IF(G$52=0,0,G51/G$52) -> 0.00035958863 | H63: =IF(H$52=0,0,H51/H$52) -> 0.0076181314 | I63: =IF(I$52=0,0,I51/I$52) -> 0.0085846487 | J63: =IF(J$52=0,0,J51/J$52) -> 0.0044937688
A66: Brand share of Medicaid dollars (pre-rebate)
A67: Molecule | B67: 2018 | C67: 2019 | D67: 2020 | E67: 2021 | F67: 2022 | G67: 2023 | H67: 2024 | I67: 2025 | J67: 2026
A68: MPSS | B68: =SUMIFS(SDUD_NDC_data!$H$6:$H$742,SDUD_NDC_data!$D$6:$D$742,"MPSS",SDUD_NDC_data!$C$6:$C$742,"Pfizer (Pharmacia & Upjohn) - brand",SDUD_NDC_data!$B$6:$B$742,"2018")/SUMIFS(SDUD_NDC_data!$H$6:$H$742,SDUD_NDC_data!$D$6:$D$742,"MPSS",SDUD_NDC_data!$B$6:$B$742,"2018") -> 0.8728107 | C68: =SUMIFS(SDUD_NDC_data!$H$6:$H$742,SDUD_NDC_data!$D$6:$D$742,"MPSS",SDUD_NDC_data!$C$6:$C$742,"Pfizer (Pharmacia & Upjohn) - brand",SDUD_NDC_data!$B$6:$B$742,"2019")/SUMIFS(SDUD_NDC_data!$H$6:$H$742,SDUD_NDC_data!$D$6:$D$742,"MPSS",SDUD_NDC_data!$B$6:$B$742,"2019") -> 0.92924776 | D68: =SUMIFS(SDUD_NDC_data!$H$6:$H$742,SDUD_NDC_data!$D$6:$D$742,"MPSS",SDUD_NDC_data!$C$6:$C$742,"Pfizer (Pharmacia & Upjohn) - brand",SDUD_NDC_data!$B$6:$B$742,"2020")/SUMIFS(SDUD_NDC_data!$H$6:$H$742,SDUD_NDC_data!$D$6:$D$742,"MPSS",SDUD_NDC_data!$B$6:$B$742,"2020") -> 0.92442428 | E68: =SUMIFS(SDUD_NDC_data!$H$6:$H$742,SDUD_NDC_data!$D$6:$D$742,"MPSS",SDUD_NDC_data!$C$6:$C$742,"Pfizer (Pharmacia & Upjohn) - brand",SDUD_NDC_data!$B$6:$B$742,"2021")/SUMIFS(SDUD_NDC_data!$H$6:$H$742,SDUD_NDC_data!$D$6:$D$742,"MPSS",SDUD_NDC_data!$B$6:$B$742,"2021") -> 0.90454082 | F68: =SUMIFS(SDUD_NDC_data!$H$6:$H$742,SDUD_NDC_data!$D$6:$D$742,"MPSS",SDUD_NDC_data!$C$6:$C$742,"Pfizer (Pharmacia & Upjohn) - brand",SDUD_NDC_data!$B$6:$B$742,"2022")/SUMIFS(SDUD_NDC_data!$H$6:$H$742,SDUD_NDC_data!$D$6:$D$742,"MPSS",SDUD_NDC_data!$B$6:$B$742,"2022") -> 0.93354851 | G68: =SUMIFS(SDUD_NDC_data!$H$6:$H$742,SDUD_NDC_data!$D$6:$D$742,"MPSS",SDUD_NDC_data!$C$6:$C$742,"Pfizer (Pharmacia & Upjohn) - brand",SDUD_NDC_data!$B$6:$B$742,"2023")/SUMIFS(SDUD_NDC_data!$H$6:$H$742,SDUD_NDC_data!$D$6:$D$742,"MPSS",SDUD_NDC_data!$B$6:$B$742,"2023") -> 0.80768533 | H68: =SUMIFS(SDUD_NDC_data!$H$6:$H$742,SDUD_NDC_data!$D$6:$D$742,"MPSS",SDUD_NDC_data!$C$6:$C$742,"Pfizer (Pharmacia & Upjohn) - brand",SDUD_NDC_data!$B$6:$B$742,"2024")/SUMIFS(SDUD_NDC_data!$H$6:$H$742,SDUD_NDC_data!$D$6:$D$742,"MPSS",SDUD_NDC_data!$B$6:$B$742,"2024") -> 0.76057642 | I68: =SUMIFS(SDUD_NDC_data!$H$6:$H$742,SDUD_NDC_data!$D$6:$D$742,"MPSS",SDUD_NDC_data!$C$6:$C$742,"Pfizer (Pharmacia & Upjohn) - brand",SDUD_NDC_data!$B$6:$B$742,"2025")/SUMIFS(SDUD_NDC_data!$H$6:$H$742,SDUD_NDC_data!$D$6:$D$742,"MPSS",SDUD_NDC_data!$B$6:$B$742,"2025") -> 0.76620324 | J68: =SUMIFS(SDUD_NDC_data!$H$6:$H$742,SDUD_NDC_data!$D$6:$D$742,"MPSS",SDUD_NDC_data!$C$6:$C$742,"Pfizer (Pharmacia & Upjohn) - brand",SDUD_NDC_data!$B$6:$B$742,"2026")/SUMIFS(SDUD_NDC_data!$H$6:$H$742,SDUD_NDC_data!$D$6:$D$742,"MPSS",SDUD_NDC_data!$B$6:$B$742,"2026") -> 0.70846485
A69: HSS | B69: =SUMIFS(SDUD_NDC_data!$H$6:$H$742,SDUD_NDC_data!$D$6:$D$742,"HSS",SDUD_NDC_data!$C$6:$C$742,"Pfizer (Pharmacia & Upjohn) - brand",SDUD_NDC_data!$B$6:$B$742,"2018")/SUMIFS(SDUD_NDC_data!$H$6:$H$742,SDUD_NDC_data!$D$6:$D$742,"HSS",SDUD_NDC_data!$B$6:$B$742,"2018") -> 0.99659922 | C69: =SUMIFS(SDUD_NDC_data!$H$6:$H$742,SDUD_NDC_data!$D$6:$D$742,"HSS",SDUD_NDC_data!$C$6:$C$742,"Pfizer (Pharmacia & Upjohn) - brand",SDUD_NDC_data!$B$6:$B$742,"2019")/SUMIFS(SDUD_NDC_data!$H$6:$H$742,SDUD_NDC_data!$D$6:$D$742,"HSS",SDUD_NDC_data!$B$6:$B$742,"2019") -> 0.99970972 | D69: =SUMIFS(SDUD_NDC_data!$H$6:$H$742,SDUD_NDC_data!$D$6:$D$742,"HSS",SDUD_NDC_data!$C$6:$C$742,"Pfizer (Pharmacia & Upjohn) - brand",SDUD_NDC_data!$B$6:$B$742,"2020")/SUMIFS(SDUD_NDC_data!$H$6:$H$742,SDUD_NDC_data!$D$6:$D$742,"HSS",SDUD_NDC_data!$B$6:$B$742,"2020") -> 0.99940391 | E69: =SUMIFS(SDUD_NDC_data!$H$6:$H$742,SDUD_NDC_data!$D$6:$D$742,"HSS",SDUD_NDC_data!$C$6:$C$742,"Pfizer (Pharmacia & Upjohn) - brand",SDUD_NDC_data!$B$6:$B$742,"2021")/SUMIFS(SDUD_NDC_data!$H$6:$H$742,SDUD_NDC_data!$D$6:$D$742,"HSS",SDUD_NDC_data!$B$6:$B$742,"2021") -> 0.99998131 | F69: =SUMIFS(SDUD_NDC_data!$H$6:$H$742,SDUD_NDC_data!$D$6:$D$742,"HSS",SDUD_NDC_data!$C$6:$C$742,"Pfizer (Pharmacia & Upjohn) - brand",SDUD_NDC_data!$B$6:$B$742,"2022")/SUMIFS(SDUD_NDC_data!$H$6:$H$742,SDUD_NDC_data!$D$6:$D$742,"HSS",SDUD_NDC_data!$B$6:$B$742,"2022") -> 1 | G69: =SUMIFS(SDUD_NDC_data!$H$6:$H$742,SDUD_NDC_data!$D$6:$D$742,"HSS",SDUD_NDC_data!$C$6:$C$742,"Pfizer (Pharmacia & Upjohn) - brand",SDUD_NDC_data!$B$6:$B$742,"2023")/SUMIFS(SDUD_NDC_data!$H$6:$H$742,SDUD_NDC_data!$D$6:$D$742,"HSS",SDUD_NDC_data!$B$6:$B$742,"2023") -> 1 | H69: =SUMIFS(SDUD_NDC_data!$H$6:$H$742,SDUD_NDC_data!$D$6:$D$742,"HSS",SDUD_NDC_data!$C$6:$C$742,"Pfizer (Pharmacia & Upjohn) - brand",SDUD_NDC_data!$B$6:$B$742,"2024")/SUMIFS(SDUD_NDC_data!$H$6:$H$742,SDUD_NDC_data!$D$6:$D$742,"HSS",SDUD_NDC_data!$B$6:$B$742,"2024") -> 0.99861439 | I69: =SUMIFS(SDUD_NDC_data!$H$6:$H$742,SDUD_NDC_data!$D$6:$D$742,"HSS",SDUD_NDC_data!$C$6:$C$742,"Pfizer (Pharmacia & Upjohn) - brand",SDUD_NDC_data!$B$6:$B$742,"2025")/SUMIFS(SDUD_NDC_data!$H$6:$H$742,SDUD_NDC_data!$D$6:$D$742,"HSS",SDUD_NDC_data!$B$6:$B$742,"2025") -> 0.9716127 | J69: =SUMIFS(SDUD_NDC_data!$H$6:$H$742,SDUD_NDC_data!$D$6:$D$742,"HSS",SDUD_NDC_data!$C$6:$C$742,"Pfizer (Pharmacia & Upjohn) - brand",SDUD_NDC_data!$B$6:$B$742,"2026")/SUMIFS(SDUD_NDC_data!$H$6:$H$742,SDUD_NDC_data!$D$6:$D$742,"HSS",SDUD_NDC_data!$B$6:$B$742,"2026") -> 0.96473679
A70: MPA | B70: =SUMIFS(SDUD_NDC_data!$H$6:$H$742,SDUD_NDC_data!$D$6:$D$742,"MPA",SDUD_NDC_data!$C$6:$C$742,"Pfizer (Pharmacia & Upjohn) - brand",SDUD_NDC_data!$B$6:$B$742,"2018")/SUMIFS(SDUD_NDC_data!$H$6:$H$742,SDUD_NDC_data!$D$6:$D$742,"MPA",SDUD_NDC_data!$B$6:$B$742,"2018") -> 0.86558196 | C70: =SUMIFS(SDUD_NDC_data!$H$6:$H$742,SDUD_NDC_data!$D$6:$D$742,"MPA",SDUD_NDC_data!$C$6:$C$742,"Pfizer (Pharmacia & Upjohn) - brand",SDUD_NDC_data!$B$6:$B$742,"2019")/SUMIFS(SDUD_NDC_data!$H$6:$H$742,SDUD_NDC_data!$D$6:$D$742,"MPA",SDUD_NDC_data!$B$6:$B$742,"2019") -> 0.80378848 | D70: =SUMIFS(SDUD_NDC_data!$H$6:$H$742,SDUD_NDC_data!$D$6:$D$742,"MPA",SDUD_NDC_data!$C$6:$C$742,"Pfizer (Pharmacia & Upjohn) - brand",SDUD_NDC_data!$B$6:$B$742,"2020")/SUMIFS(SDUD_NDC_data!$H$6:$H$742,SDUD_NDC_data!$D$6:$D$742,"MPA",SDUD_NDC_data!$B$6:$B$742,"2020") -> 0.78152261 | E70: =SUMIFS(SDUD_NDC_data!$H$6:$H$742,SDUD_NDC_data!$D$6:$D$742,"MPA",SDUD_NDC_data!$C$6:$C$742,"Pfizer (Pharmacia & Upjohn) - brand",SDUD_NDC_data!$B$6:$B$742,"2021")/SUMIFS(SDUD_NDC_data!$H$6:$H$742,SDUD_NDC_data!$D$6:$D$742,"MPA",SDUD_NDC_data!$B$6:$B$742,"2021") -> 0.70622453 | F70: =SUMIFS(SDUD_NDC_data!$H$6:$H$742,SDUD_NDC_data!$D$6:$D$742,"MPA",SDUD_NDC_data!$C$6:$C$742,"Pfizer (Pharmacia & Upjohn) - brand",SDUD_NDC_data!$B$6:$B$742,"2022")/SUMIFS(SDUD_NDC_data!$H$6:$H$742,SDUD_NDC_data!$D$6:$D$742,"MPA",SDUD_NDC_data!$B$6:$B$742,"2022") -> 0.5847358 | G70: =SUMIFS(SDUD_NDC_data!$H$6:$H$742,SDUD_NDC_data!$D$6:$D$742,"MPA",SDUD_NDC_data!$C$6:$C$742,"Pfizer (Pharmacia & Upjohn) - brand",SDUD_NDC_data!$B$6:$B$742,"2023")/SUMIFS(SDUD_NDC_data!$H$6:$H$742,SDUD_NDC_data!$D$6:$D$742,"MPA",SDUD_NDC_data!$B$6:$B$742,"2023") -> 0.66509559 | H70: =SUMIFS(SDUD_NDC_data!$H$6:$H$742,SDUD_NDC_data!$D$6:$D$742,"MPA",SDUD_NDC_data!$C$6:$C$742,"Pfizer (Pharmacia & Upjohn) - brand",SDUD_NDC_data!$B$6:$B$742,"2024")/SUMIFS(SDUD_NDC_data!$H$6:$H$742,SDUD_NDC_data!$D$6:$D$742,"MPA",SDUD_NDC_data!$B$6:$B$742,"2024") -> 0.64368667 | I70: =SUMIFS(SDUD_NDC_data!$H$6:$H$742,SDUD_NDC_data!$D$6:$D$742,"MPA",SDUD_NDC_data!$C$6:$C$742,"Pfizer (Pharmacia & Upjohn) - brand",SDUD_NDC_data!$B$6:$B$742,"2025")/SUMIFS(SDUD_NDC_data!$H$6:$H$742,SDUD_NDC_data!$D$6:$D$742,"MPA",SDUD_NDC_data!$B$6:$B$742,"2025") -> 0.63179069 | J70: =SUMIFS(SDUD_NDC_data!$H$6:$H$742,SDUD_NDC_data!$D$6:$D$742,"MPA",SDUD_NDC_data!$C$6:$C$742,"Pfizer (Pharmacia & Upjohn) - brand",SDUD_NDC_data!$B$6:$B$742,"2026")/SUMIFS(SDUD_NDC_data!$H$6:$H$742,SDUD_NDC_data!$D$6:$D$742,"MPA",SDUD_NDC_data!$B$6:$B$742,"2026") -> 0.63447118
A72: MPSS by strength: share of prescriptions, 2025 and Q1 2026
A73: Strength | B73: Strength share of 2025 MPSS Rx | C73: Pfizer 2025 | D73: Pfizer Q1 2026 | E73: Dr. Reddy's Q1 2026 | F73: Fresenius Q1 2026 | G73: Hikma Q1 2026
A74: 40 mg | B74: =SUMIFS(SDUD_NDC_data!$G$6:$G$742,SDUD_NDC_data!$D$6:$D$742,"MPSS",SDUD_NDC_data!$E$6:$E$742,$A74,SDUD_NDC_data!$B$6:$B$742,"2025")/SUMIFS(SDUD_NDC_data!$G$6:$G$742,SDUD_NDC_data!$D$6:$D$742,"MPSS",SDUD_NDC_data!$B$6:$B$742,"2025") -> 0.22686 | C74: =IF(SUMIFS(SDUD_NDC_data!$G$6:$G$742,SDUD_NDC_data!$D$6:$D$742,"MPSS",SDUD_NDC_data!$E$6:$E$742,$A74,SDUD_NDC_data!$B$6:$B$742,"2025")=0,0,SUMIFS(SDUD_NDC_data!$G$6:$G$742,SDUD_NDC_data!$D$6:$D$742,"MPSS",SDUD_NDC_data!$E$6:$E$742,$A74,SDUD_NDC_data!$B$6:$B$742,"2025",SDUD_NDC_data!$C$6:$C$742,"Pfizer (Pharmacia & Upjohn) - brand")/SUMIFS(SDUD_NDC_data!$G$6:$G$742,SDUD_NDC_data!$D$6:$D$742,"MPSS",SDUD_NDC_data!$E$6:$E$742,$A74,SDUD_NDC_data!$B$6:$B$742,"2025")) -> 0.76972345 | D74: =IF(SUMIFS(SDUD_NDC_data!$G$6:$G$742,SDUD_NDC_data!$D$6:$D$742,"MPSS",SDUD_NDC_data!$E$6:$E$742,$A74,SDUD_NDC_data!$B$6:$B$742,"2026")=0,0,SUMIFS(SDUD_NDC_data!$G$6:$G$742,SDUD_NDC_data!$D$6:$D$742,"MPSS",SDUD_NDC_data!$E$6:$E$742,$A74,SDUD_NDC_data!$B$6:$B$742,"2026",SDUD_NDC_data!$C$6:$C$742,"Pfizer (Pharmacia & Upjohn) - brand")/SUMIFS(SDUD_NDC_data!$G$6:$G$742,SDUD_NDC_data!$D$6:$D$742,"MPSS",SDUD_NDC_data!$E$6:$E$742,$A74,SDUD_NDC_data!$B$6:$B$742,"2026")) -> 0.74663609 | E74: =IF(SUMIFS(SDUD_NDC_data!$G$6:$G$742,SDUD_NDC_data!$D$6:$D$742,"MPSS",SDUD_NDC_data!$E$6:$E$742,$A74,SDUD_NDC_data!$B$6:$B$742,"2026")=0,0,SUMIFS(SDUD_NDC_data!$G$6:$G$742,SDUD_NDC_data!$D$6:$D$742,"MPSS",SDUD_NDC_data!$E$6:$E$742,$A74,SDUD_NDC_data!$B$6:$B$742,"2026",SDUD_NDC_data!$C$6:$C$742,"Dr. Reddy's")/SUMIFS(SDUD_NDC_data!$G$6:$G$742,SDUD_NDC_data!$D$6:$D$742,"MPSS",SDUD_NDC_data!$E$6:$E$742,$A74,SDUD_NDC_data!$B$6:$B$742,"2026")) -> 0.15639896 | F74: =IF(SUMIFS(SDUD_NDC_data!$G$6:$G$742,SDUD_NDC_data!$D$6:$D$742,"MPSS",SDUD_NDC_data!$E$6:$E$742,$A74,SDUD_NDC_data!$B$6:$B$742,"2026")=0,0,SUMIFS(SDUD_NDC_data!$G$6:$G$742,SDUD_NDC_data!$D$6:$D$742,"MPSS",SDUD_NDC_data!$E$6:$E$742,$A74,SDUD_NDC_data!$B$6:$B$742,"2026",SDUD_NDC_data!$C$6:$C$742,"Fresenius Kabi")/SUMIFS(SDUD_NDC_data!$G$6:$G$742,SDUD_NDC_data!$D$6:$D$742,"MPSS",SDUD_NDC_data!$E$6:$E$742,$A74,SDUD_NDC_data!$B$6:$B$742,"2026")) -> 0.062149279 | G74: =IF(SUMIFS(SDUD_NDC_data!$G$6:$G$742,SDUD_NDC_data!$D$6:$D$742,"MPSS",SDUD_NDC_data!$E$6:$E$742,$A74,SDUD_NDC_data!$B$6:$B$742,"2026")=0,0,SUMIFS(SDUD_NDC_data!$G$6:$G$742,SDUD_NDC_data!$D$6:$D$742,"MPSS",SDUD_NDC_data!$E$6:$E$742,$A74,SDUD_NDC_data!$B$6:$B$742,"2026",SDUD_NDC_data!$C$6:$C$742,"Hikma (West-Ward)")/SUMIFS(SDUD_NDC_data!$G$6:$G$742,SDUD_NDC_data!$D$6:$D$742,"MPSS",SDUD_NDC_data!$E$6:$E$742,$A74,SDUD_NDC_data!$B$6:$B$742,"2026")) -> 0.034031256
A75: 125 mg | B75: =SUMIFS(SDUD_NDC_data!$G$6:$G$742,SDUD_NDC_data!$D$6:$D$742,"MPSS",SDUD_NDC_data!$E$6:$E$742,$A75,SDUD_NDC_data!$B$6:$B$742,"2025")/SUMIFS(SDUD_NDC_data!$G$6:$G$742,SDUD_NDC_data!$D$6:$D$742,"MPSS",SDUD_NDC_data!$B$6:$B$742,"2025") -> 0.72197705 | C75: =IF(SUMIFS(SDUD_NDC_data!$G$6:$G$742,SDUD_NDC_data!$D$6:$D$742,"MPSS",SDUD_NDC_data!$E$6:$E$742,$A75,SDUD_NDC_data!$B$6:$B$742,"2025")=0,0,SUMIFS(SDUD_NDC_data!$G$6:$G$742,SDUD_NDC_data!$D$6:$D$742,"MPSS",SDUD_NDC_data!$E$6:$E$742,$A75,SDUD_NDC_data!$B$6:$B$742,"2025",SDUD_NDC_data!$C$6:$C$742,"Pfizer (Pharmacia & Upjohn) - brand")/SUMIFS(SDUD_NDC_data!$G$6:$G$742,SDUD_NDC_data!$D$6:$D$742,"MPSS",SDUD_NDC_data!$E$6:$E$742,$A75,SDUD_NDC_data!$B$6:$B$742,"2025")) -> 0.75269803 | D75: =IF(SUMIFS(SDUD_NDC_data!$G$6:$G$742,SDUD_NDC_data!$D$6:$D$742,"MPSS",SDUD_NDC_data!$E$6:$E$742,$A75,SDUD_NDC_data!$B$6:$B$742,"2026")=0,0,SUMIFS(SDUD_NDC_data!$G$6:$G$742,SDUD_NDC_data!$D$6:$D$742,"MPSS",SDUD_NDC_data!$E$6:$E$742,$A75,SDUD_NDC_data!$B$6:$B$742,"2026",SDUD_NDC_data!$C$6:$C$742,"Pfizer (Pharmacia & Upjohn) - brand")/SUMIFS(SDUD_NDC_data!$G$6:$G$742,SDUD_NDC_data!$D$6:$D$742,"MPSS",SDUD_NDC_data!$E$6:$E$742,$A75,SDUD_NDC_data!$B$6:$B$742,"2026")) -> 0.74495765 | E75: =IF(SUMIFS(SDUD_NDC_data!$G$6:$G$742,SDUD_NDC_data!$D$6:$D$742,"MPSS",SDUD_NDC_data!$E$6:$E$742,$A75,SDUD_NDC_data!$B$6:$B$742,"2026")=0,0,SUMIFS(SDUD_NDC_data!$G$6:$G$742,SDUD_NDC_data!$D$6:$D$742,"MPSS",SDUD_NDC_data!$E$6:$E$742,$A75,SDUD_NDC_data!$B$6:$B$742,"2026",SDUD_NDC_data!$C$6:$C$742,"Dr. Reddy's")/SUMIFS(SDUD_NDC_data!$G$6:$G$742,SDUD_NDC_data!$D$6:$D$742,"MPSS",SDUD_NDC_data!$E$6:$E$742,$A75,SDUD_NDC_data!$B$6:$B$742,"2026")) -> 0.17068686 | F75: =IF(SUMIFS(SDUD_NDC_data!$G$6:$G$742,SDUD_NDC_data!$D$6:$D$742,"MPSS",SDUD_NDC_data!$E$6:$E$742,$A75,SDUD_NDC_data!$B$6:$B$742,"2026")=0,0,SUMIFS(SDUD_NDC_data!$G$6:$G$742,SDUD_NDC_data!$D$6:$D$742,"MPSS",SDUD_NDC_data!$E$6:$E$742,$A75,SDUD_NDC_data!$B$6:$B$742,"2026",SDUD_NDC_data!$C$6:$C$742,"Fresenius Kabi")/SUMIFS(SDUD_NDC_data!$G$6:$G$742,SDUD_NDC_data!$D$6:$D$742,"MPSS",SDUD_NDC_data!$E$6:$E$742,$A75,SDUD_NDC_data!$B$6:$B$742,"2026")) -> 0.054678483 | G75: =IF(SUMIFS(SDUD_NDC_data!$G$6:$G$742,SDUD_NDC_data!$D$6:$D$742,"MPSS",SDUD_NDC_data!$E$6:$E$742,$A75,SDUD_NDC_data!$B$6:$B$742,"2026")=0,0,SUMIFS(SDUD_NDC_data!$G$6:$G$742,SDUD_NDC_data!$D$6:$D$742,"MPSS",SDUD_NDC_data!$E$6:$E$742,$A75,SDUD_NDC_data!$B$6:$B$742,"2026",SDUD_NDC_data!$C$6:$C$742,"Hikma (West-Ward)")/SUMIFS(SDUD_NDC_data!$G$6:$G$742,SDUD_NDC_data!$D$6:$D$742,"MPSS",SDUD_NDC_data!$E$6:$E$742,$A75,SDUD_NDC_data!$B$6:$B$742,"2026")) -> 0.028737993
A76: 500 mg | B76: =SUMIFS(SDUD_NDC_data!$G$6:$G$742,SDUD_NDC_data!$D$6:$D$742,"MPSS",SDUD_NDC_data!$E$6:$E$742,$A76,SDUD_NDC_data!$B$6:$B$742,"2025")/SUMIFS(SDUD_NDC_data!$G$6:$G$742,SDUD_NDC_data!$D$6:$D$742,"MPSS",SDUD_NDC_data!$B$6:$B$742,"2025") -> 0.01356585 | C76: =IF(SUMIFS(SDUD_NDC_data!$G$6:$G$742,SDUD_NDC_data!$D$6:$D$742,"MPSS",SDUD_NDC_data!$E$6:$E$742,$A76,SDUD_NDC_data!$B$6:$B$742,"2025")=0,0,SUMIFS(SDUD_NDC_data!$G$6:$G$742,SDUD_NDC_data!$D$6:$D$742,"MPSS",SDUD_NDC_data!$E$6:$E$742,$A76,SDUD_NDC_data!$B$6:$B$742,"2025",SDUD_NDC_data!$C$6:$C$742,"Pfizer (Pharmacia & Upjohn) - brand")/SUMIFS(SDUD_NDC_data!$G$6:$G$742,SDUD_NDC_data!$D$6:$D$742,"MPSS",SDUD_NDC_data!$E$6:$E$742,$A76,SDUD_NDC_data!$B$6:$B$742,"2025")) -> 0.7515429 | D76: =IF(SUMIFS(SDUD_NDC_data!$G$6:$G$742,SDUD_NDC_data!$D$6:$D$742,"MPSS",SDUD_NDC_data!$E$6:$E$742,$A76,SDUD_NDC_data!$B$6:$B$742,"2026")=0,0,SUMIFS(SDUD_NDC_data!$G$6:$G$742,SDUD_NDC_data!$D$6:$D$742,"MPSS",SDUD_NDC_data!$E$6:$E$742,$A76,SDUD_NDC_data!$B$6:$B$742,"2026",SDUD_NDC_data!$C$6:$C$742,"Pfizer (Pharmacia & Upjohn) - brand")/SUMIFS(SDUD_NDC_data!$G$6:$G$742,SDUD_NDC_data!$D$6:$D$742,"MPSS",SDUD_NDC_data!$E$6:$E$742,$A76,SDUD_NDC_data!$B$6:$B$742,"2026")) -> 0.66214689 | E76: =IF(SUMIFS(SDUD_NDC_data!$G$6:$G$742,SDUD_NDC_data!$D$6:$D$742,"MPSS",SDUD_NDC_data!$E$6:$E$742,$A76,SDUD_NDC_data!$B$6:$B$742,"2026")=0,0,SUMIFS(SDUD_NDC_data!$G$6:$G$742,SDUD_NDC_data!$D$6:$D$742,"MPSS",SDUD_NDC_data!$E$6:$E$742,$A76,SDUD_NDC_data!$B$6:$B$742,"2026",SDUD_NDC_data!$C$6:$C$742,"Dr. Reddy's")/SUMIFS(SDUD_NDC_data!$G$6:$G$742,SDUD_NDC_data!$D$6:$D$742,"MPSS",SDUD_NDC_data!$E$6:$E$742,$A76,SDUD_NDC_data!$B$6:$B$742,"2026")) -> 0.19322034 | F76: =IF(SUMIFS(SDUD_NDC_data!$G$6:$G$742,SDUD_NDC_data!$D$6:$D$742,"MPSS",SDUD_NDC_data!$E$6:$E$742,$A76,SDUD_NDC_data!$B$6:$B$742,"2026")=0,0,SUMIFS(SDUD_NDC_data!$G$6:$G$742,SDUD_NDC_data!$D$6:$D$742,"MPSS",SDUD_NDC_data!$E$6:$E$742,$A76,SDUD_NDC_data!$B$6:$B$742,"2026",SDUD_NDC_data!$C$6:$C$742,"Fresenius Kabi")/SUMIFS(SDUD_NDC_data!$G$6:$G$742,SDUD_NDC_data!$D$6:$D$742,"MPSS",SDUD_NDC_data!$E$6:$E$742,$A76,SDUD_NDC_data!$B$6:$B$742,"2026")) -> 0 | G76: =IF(SUMIFS(SDUD_NDC_data!$G$6:$G$742,SDUD_NDC_data!$D$6:$D$742,"MPSS",SDUD_NDC_data!$E$6:$E$742,$A76,SDUD_NDC_data!$B$6:$B$742,"2026")=0,0,SUMIFS(SDUD_NDC_data!$G$6:$G$742,SDUD_NDC_data!$D$6:$D$742,"MPSS",SDUD_NDC_data!$E$6:$E$742,$A76,SDUD_NDC_data!$B$6:$B$742,"2026",SDUD_NDC_data!$C$6:$C$742,"Hikma (West-Ward)")/SUMIFS(SDUD_NDC_data!$G$6:$G$742,SDUD_NDC_data!$D$6:$D$742,"MPSS",SDUD_NDC_data!$E$6:$E$742,$A76,SDUD_NDC_data!$B$6:$B$742,"2026")) -> 0.14463277
A77: 1000 mg | B77: =SUMIFS(SDUD_NDC_data!$G$6:$G$742,SDUD_NDC_data!$D$6:$D$742,"MPSS",SDUD_NDC_data!$E$6:$E$742,$A77,SDUD_NDC_data!$B$6:$B$742,"2025")/SUMIFS(SDUD_NDC_data!$G$6:$G$742,SDUD_NDC_data!$D$6:$D$742,"MPSS",SDUD_NDC_data!$B$6:$B$742,"2025") -> 0.03683008 | C77: =IF(SUMIFS(SDUD_NDC_data!$G$6:$G$742,SDUD_NDC_data!$D$6:$D$742,"MPSS",SDUD_NDC_data!$E$6:$E$742,$A77,SDUD_NDC_data!$B$6:$B$742,"2025")=0,0,SUMIFS(SDUD_NDC_data!$G$6:$G$742,SDUD_NDC_data!$D$6:$D$742,"MPSS",SDUD_NDC_data!$E$6:$E$742,$A77,SDUD_NDC_data!$B$6:$B$742,"2025",SDUD_NDC_data!$C$6:$C$742,"Pfizer (Pharmacia & Upjohn) - brand")/SUMIFS(SDUD_NDC_data!$G$6:$G$742,SDUD_NDC_data!$D$6:$D$742,"MPSS",SDUD_NDC_data!$E$6:$E$742,$A77,SDUD_NDC_data!$B$6:$B$742,"2025")) -> 0.57197331 | D77: =IF(SUMIFS(SDUD_NDC_data!$G$6:$G$742,SDUD_NDC_data!$D$6:$D$742,"MPSS",SDUD_NDC_data!$E$6:$E$742,$A77,SDUD_NDC_data!$B$6:$B$742,"2026")=0,0,SUMIFS(SDUD_NDC_data!$G$6:$G$742,SDUD_NDC_data!$D$6:$D$742,"MPSS",SDUD_NDC_data!$E$6:$E$742,$A77,SDUD_NDC_data!$B$6:$B$742,"2026",SDUD_NDC_data!$C$6:$C$742,"Pfizer (Pharmacia & Upjohn) - brand")/SUMIFS(SDUD_NDC_data!$G$6:$G$742,SDUD_NDC_data!$D$6:$D$742,"MPSS",SDUD_NDC_data!$E$6:$E$742,$A77,SDUD_NDC_data!$B$6:$B$742,"2026")) -> 0.54090513 | E77: =IF(SUMIFS(SDUD_NDC_data!$G$6:$G$742,SDUD_NDC_data!$D$6:$D$742,"MPSS",SDUD_NDC_data!$E$6:$E$742,$A77,SDUD_NDC_data!$B$6:$B$742,"2026")=0,0,SUMIFS(SDUD_NDC_data!$G$6:$G$742,SDUD_NDC_data!$D$6:$D$742,"MPSS",SDUD_NDC_data!$E$6:$E$742,$A77,SDUD_NDC_data!$B$6:$B$742,"2026",SDUD_NDC_data!$C$6:$C$742,"Dr. Reddy's")/SUMIFS(SDUD_NDC_data!$G$6:$G$742,SDUD_NDC_data!$D$6:$D$742,"MPSS",SDUD_NDC_data!$E$6:$E$742,$A77,SDUD_NDC_data!$B$6:$B$742,"2026")) -> 0.21235857 | F77: =IF(SUMIFS(SDUD_NDC_data!$G$6:$G$742,SDUD_NDC_data!$D$6:$D$742,"MPSS",SDUD_NDC_data!$E$6:$E$742,$A77,SDUD_NDC_data!$B$6:$B$742,"2026")=0,0,SUMIFS(SDUD_NDC_data!$G$6:$G$742,SDUD_NDC_data!$D$6:$D$742,"MPSS",SDUD_NDC_data!$E$6:$E$742,$A77,SDUD_NDC_data!$B$6:$B$742,"2026",SDUD_NDC_data!$C$6:$C$742,"Fresenius Kabi")/SUMIFS(SDUD_NDC_data!$G$6:$G$742,SDUD_NDC_data!$D$6:$D$742,"MPSS",SDUD_NDC_data!$E$6:$E$742,$A77,SDUD_NDC_data!$B$6:$B$742,"2026")) -> 0.20670148 | G77: =IF(SUMIFS(SDUD_NDC_data!$G$6:$G$742,SDUD_NDC_data!$D$6:$D$742,"MPSS",SDUD_NDC_data!$E$6:$E$742,$A77,SDUD_NDC_data!$B$6:$B$742,"2026")=0,0,SUMIFS(SDUD_NDC_data!$G$6:$G$742,SDUD_NDC_data!$D$6:$D$742,"MPSS",SDUD_NDC_data!$E$6:$E$742,$A77,SDUD_NDC_data!$B$6:$B$742,"2026",SDUD_NDC_data!$C$6:$C$742,"Hikma (West-Ward)")/SUMIFS(SDUD_NDC_data!$G$6:$G$742,SDUD_NDC_data!$D$6:$D$742,"MPSS",SDUD_NDC_data!$E$6:$E$742,$A77,SDUD_NDC_data!$B$6:$B$742,"2026")) -> 0.040034813
A78: 2000 mg | B78: =SUMIFS(SDUD_NDC_data!$G$6:$G$742,SDUD_NDC_data!$D$6:$D$742,"MPSS",SDUD_NDC_data!$E$6:$E$742,$A78,SDUD_NDC_data!$B$6:$B$742,"2025")/SUMIFS(SDUD_NDC_data!$G$6:$G$742,SDUD_NDC_data!$D$6:$D$742,"MPSS",SDUD_NDC_data!$B$6:$B$742,"2025") -> 0.000767012 | C78: =IF(SUMIFS(SDUD_NDC_data!$G$6:$G$742,SDUD_NDC_data!$D$6:$D$742,"MPSS",SDUD_NDC_data!$E$6:$E$742,$A78,SDUD_NDC_data!$B$6:$B$742,"2025")=0,0,SUMIFS(SDUD_NDC_data!$G$6:$G$742,SDUD_NDC_data!$D$6:$D$742,"MPSS",SDUD_NDC_data!$E$6:$E$742,$A78,SDUD_NDC_data!$B$6:$B$742,"2025",SDUD_NDC_data!$C$6:$C$742,"Pfizer (Pharmacia & Upjohn) - brand")/SUMIFS(SDUD_NDC_data!$G$6:$G$742,SDUD_NDC_data!$D$6:$D$742,"MPSS",SDUD_NDC_data!$E$6:$E$742,$A78,SDUD_NDC_data!$B$6:$B$742,"2025")) -> 1 | D78: =IF(SUMIFS(SDUD_NDC_data!$G$6:$G$742,SDUD_NDC_data!$D$6:$D$742,"MPSS",SDUD_NDC_data!$E$6:$E$742,$A78,SDUD_NDC_data!$B$6:$B$742,"2026")=0,0,SUMIFS(SDUD_NDC_data!$G$6:$G$742,SDUD_NDC_data!$D$6:$D$742,"MPSS",SDUD_NDC_data!$E$6:$E$742,$A78,SDUD_NDC_data!$B$6:$B$742,"2026",SDUD_NDC_data!$C$6:$C$742,"Pfizer (Pharmacia & Upjohn) - brand")/SUMIFS(SDUD_NDC_data!$G$6:$G$742,SDUD_NDC_data!$D$6:$D$742,"MPSS",SDUD_NDC_data!$E$6:$E$742,$A78,SDUD_NDC_data!$B$6:$B$742,"2026")) -> 1 | E78: =IF(SUMIFS(SDUD_NDC_data!$G$6:$G$742,SDUD_NDC_data!$D$6:$D$742,"MPSS",SDUD_NDC_data!$E$6:$E$742,$A78,SDUD_NDC_data!$B$6:$B$742,"2026")=0,0,SUMIFS(SDUD_NDC_data!$G$6:$G$742,SDUD_NDC_data!$D$6:$D$742,"MPSS",SDUD_NDC_data!$E$6:$E$742,$A78,SDUD_NDC_data!$B$6:$B$742,"2026",SDUD_NDC_data!$C$6:$C$742,"Dr. Reddy's")/SUMIFS(SDUD_NDC_data!$G$6:$G$742,SDUD_NDC_data!$D$6:$D$742,"MPSS",SDUD_NDC_data!$E$6:$E$742,$A78,SDUD_NDC_data!$B$6:$B$742,"2026")) -> 0 | F78: =IF(SUMIFS(SDUD_NDC_data!$G$6:$G$742,SDUD_NDC_data!$D$6:$D$742,"MPSS",SDUD_NDC_data!$E$6:$E$742,$A78,SDUD_NDC_data!$B$6:$B$742,"2026")=0,0,SUMIFS(SDUD_NDC_data!$G$6:$G$742,SDUD_NDC_data!$D$6:$D$742,"MPSS",SDUD_NDC_data!$E$6:$E$742,$A78,SDUD_NDC_data!$B$6:$B$742,"2026",SDUD_NDC_data!$C$6:$C$742,"Fresenius Kabi")/SUMIFS(SDUD_NDC_data!$G$6:$G$742,SDUD_NDC_data!$D$6:$D$742,"MPSS",SDUD_NDC_data!$E$6:$E$742,$A78,SDUD_NDC_data!$B$6:$B$742,"2026")) -> 0 | G78: =IF(SUMIFS(SDUD_NDC_data!$G$6:$G$742,SDUD_NDC_data!$D$6:$D$742,"MPSS",SDUD_NDC_data!$E$6:$E$742,$A78,SDUD_NDC_data!$B$6:$B$742,"2026")=0,0,SUMIFS(SDUD_NDC_data!$G$6:$G$742,SDUD_NDC_data!$D$6:$D$742,"MPSS",SDUD_NDC_data!$E$6:$E$742,$A78,SDUD_NDC_data!$B$6:$B$742,"2026",SDUD_NDC_data!$C$6:$C$742,"Hikma (West-Ward)")/SUMIFS(SDUD_NDC_data!$G$6:$G$742,SDUD_NDC_data!$D$6:$D$742,"MPSS",SDUD_NDC_data!$E$6:$E$742,$A78,SDUD_NDC_data!$B$6:$B$742,"2026")) -> 0
A81: HSS by strength, 2025: large-vial slice and effect of counting 250 mg as 3 billing units
A82: Strength | B82: Rx 2025 | C82: Amount 2025 (US$) | D82: Share of Rx | E82: Share of US$ | F82: Units per vial (2.5 rule) | G82: Units per vial (3 rule) | H82: Billing units, 2.5 rule (Rx-weighted) | I82: Billing units, 3 rule (Rx-weighted)
A83: 100 mg | B83: =SUMIFS(SDUD_NDC_data!$G$6:$G$742,SDUD_NDC_data!$D$6:$D$742,"HSS",SDUD_NDC_data!$E$6:$E$742,$A83,SDUD_NDC_data!$B$6:$B$742,"2025") -> 36146 | C83: =SUMIFS(SDUD_NDC_data!$H$6:$H$742,SDUD_NDC_data!$D$6:$D$742,"HSS",SDUD_NDC_data!$E$6:$E$742,$A83,SDUD_NDC_data!$B$6:$B$742,"2025") -> 2419427.6 | D83: =B83/B$87 -> 0.96898373 | E83: =C83/C$87 -> 0.93952058 | F83: =Assumptions!$C$27 -> 1 | G83: =Assumptions!$C$27 -> 1 | H83: =B83*F83 -> 36146 | I83: =B83*G83 -> 36146
A84: 250 mg | B84: =SUMIFS(SDUD_NDC_data!$G$6:$G$742,SDUD_NDC_data!$D$6:$D$742,"HSS",SDUD_NDC_data!$E$6:$E$742,$A84,SDUD_NDC_data!$B$6:$B$742,"2025") -> 980 | C84: =SUMIFS(SDUD_NDC_data!$H$6:$H$742,SDUD_NDC_data!$D$6:$D$742,"HSS",SDUD_NDC_data!$E$6:$E$742,$A84,SDUD_NDC_data!$B$6:$B$742,"2025") -> 122783.1 | D84: =B84/B$87 -> 0.026271345 | E84: =C84/C$87 -> 0.047679561 | F84: =Assumptions!$C$28 -> 2.5 | G84: =Assumptions!$C$29 -> 3 | H84: =B84*F84 -> 2450 | I84: =B84*G84 -> 2940
A85: 500 mg | B85: =SUMIFS(SDUD_NDC_data!$G$6:$G$742,SDUD_NDC_data!$D$6:$D$742,"HSS",SDUD_NDC_data!$E$6:$E$742,$A85,SDUD_NDC_data!$B$6:$B$742,"2025") -> 16 | C85: =SUMIFS(SDUD_NDC_data!$H$6:$H$742,SDUD_NDC_data!$D$6:$D$742,"HSS",SDUD_NDC_data!$E$6:$E$742,$A85,SDUD_NDC_data!$B$6:$B$742,"2025") -> 1239.82 | D85: =B85/B$87 -> 0.00042891993 | E85: =C85/C$87 -> 0.00048145122 | F85: =Assumptions!$C$30 -> 5 | G85: =Assumptions!$C$30 -> 5 | H85: =B85*F85 -> 80 | I85: =B85*G85 -> 80
A86: 1000 mg | B86: =SUMIFS(SDUD_NDC_data!$G$6:$G$742,SDUD_NDC_data!$D$6:$D$742,"HSS",SDUD_NDC_data!$E$6:$E$742,$A86,SDUD_NDC_data!$B$6:$B$742,"2025") -> 161 | C86: =SUMIFS(SDUD_NDC_data!$H$6:$H$742,SDUD_NDC_data!$D$6:$D$742,"HSS",SDUD_NDC_data!$E$6:$E$742,$A86,SDUD_NDC_data!$B$6:$B$742,"2025") -> 31722.03 | D86: =B86/B$87 -> 0.0043160068 | E86: =C86/C$87 -> 0.012318409 | F86: =Assumptions!$C$31 -> 10 | G86: =Assumptions!$C$31 -> 10 | H86: =B86*F86 -> 1610 | I86: =B86*G86 -> 1610
A87: Total HSS 2025 | B87: =SUM(B83:B86) -> 37303 | C87: =SUM(C83:C86) -> 2575172.6 | D87: =SUM(D83:D86) -> 1 | E87: =SUM(E83:E86) -> 1 | H87: =SUM(H83:H86) -> 40286 | I87: =SUM(I83:I86) -> 40776
A89: 250 mg + 500 mg + 1 g prescriptions, 2025 | B89: =SUM(B84:B86) -> 1157
A90: 250 mg + 500 mg + 1 g share of HSS Rx, 2025 | B90: =SUM(D84:D86) -> 0.031016272
A91: 250 mg + 500 mg + 1 g share of HSS Medicaid US$, 2025 | B91: =SUM(E84:E86) -> 0.060479422
A92: Mechanical J1720 ASP drag if 250 mg counts as 3 units (same dollars) | B92: =1-H87/I87 -> 0.012016873
A94: Drag method: per-unit ASP = sales / billing units. Holding dollars fixed, moving 250 mg from 2.5 to 3 units scales ASP by (units at 2.5) / (units at 3). Rx used as the vial-mix proxy.

Sheet CMS_Spending
A1: CMS spending datasets: Part D 2024, Medicaid Spending by Drug 2024, Part B by HCPCS
A2: Inputs copied from S20, S21, S22/S23. Manufacturer rows only (dataset 'Overall' rows excluded to avoid double counting).
A4: Medicare Part D Spending by Drug (source S21), data year 2024
A5: Molecule | B5: Brand name | C5: Manufacturer | D5: Company group | E5: Brand / generic | F5: Total spending (US$) | G5: Dosage units | H5: Claims
A6: HSS | B6: Hydrocortisone Sod Succinate | C6: Cipla USA, Inc. | D6: Cipla | E6: Generic | F6: 4575.61 | G6: 336 | H6: 110
A7: HSS | B7: Solu-Cortef | C7: Pfizer US Pharm | D7: Pfizer | E7: Brand | F7: 989904.71 | G7: 100019.85 | H7: 13384
A8: HSS | B8: Solu-Cortef | C8: Pharmacia-Upjhn | D8: Pfizer | E8: Brand | F8: 123492.13 | G8: 10275.5 | H8: 1790
A9: MPA | B9: Depo-Medrol | C9: Pharmacia-Upjhn | D9: Pfizer | E9: Brand | F9: 25135.02 | G9: 1730 | H9: 914
A10: MPA | B10: Methylprednisolone Acetate | C10: Amneal Bio-Nova | D10: Amneal | E10: Generic | F10: 374.9 | G10: 25 | H10: 22
A11: MPA | B11: Methylprednisolone Acetate | C11: Amneal Bioscien | D11: Amneal | E11: Generic | F11: 182378.26 | G11: 16180.5 | H11: 10398
A12: MPA | B12: Methylprednisolone Acetate | C12: Amneal-Premier | D12: Amneal | E12: Generic | F12: 10316.2 | G12: 961 | H12: 583
A13: MPA | B13: Methylprednisolone Acetate | C13: Eugia US LLC | D13: Eugia | E13: Generic | F13: 2932.95 | G13: 437 | H13: 48
A14: MPA | B14: Methylprednisolone Acetate | C14: Sagent Pharmace | D14: Sagent | E14: Generic | F14: 11266.13 | G14: 1724 | H14: 249
A15: MPA | B15: Methylprednisolone Acetate | C15: Sandoz | D15: Sandoz | E15: Generic | F15: 13189.24 | G15: 1192 | H15: 220
A16: MPSS | B16: Methylprednisolone Sodium Succ* | C16: Amneal Bioscien | D16: Amneal | E16: Generic | F16: 289.91 | G16: 51 | H16: 13
A17: MPSS | B17: Methylprednisolone Sodium Succ* | C17: App/Fresenius K | D17: Fresenius Kabi | E17: Generic | F17: 136560.03 | G17: 26220.38 | H17: 2155
... A26: MPSS | B26: Solu-Medrol* | C26: Phar-Prep/Pfize | D26: Pfizer | E26: Brand | F26: 3632.57 | G26: 579 | H26: 169
A29: Medicaid Spending by Drug (source S20), data year 2024
A30: Molecule | B30: Brand name | C30: Manufacturer | D30: Company group | E30: Brand / generic | F30: Total spending (US$) | G30: Dosage units | H30: Claims
A31: HSS | B31: Hydrocortisone Sod Succinate | C31: Cipla USA, Inc. | D31: Cipla | E31: Generic | F31: 14610.12 | G31: 262 | H31: 145
A32: HSS | B32: Solu-Cortef | C32: Pfizer US Pharm | D32: Pfizer | E32: Brand | F32: 3382163.2 | G32: 71183.757 | H32: 31029
A33: HSS | B33: Solu-Cortef | C33: Pharmacia-Upjhn | D33: Pfizer | E33: Brand | F33: 702861.71 | G33: 10843 | H33: 6607
A34: MPA | B34: Depo-Medrol | C34: Pfizer-Novaplus | D34: Pfizer | E34: Brand | F34: 421617.12 | G34: 37174.879 | H34: 12325
A35: MPA | B35: Depo-Medrol | C35: Pharmacia-Upjhn | D35: Pfizer | E35: Brand | F35: 5318737.8 | G35: 509159.49 | H35: 282650
A36: MPA | B36: Methylprednisolone Acetate | C36: Amneal Bio-Nova | D36: Amneal | E36: Generic | F36: 124182.08 | G36: 11910.378 | H36: 6446
A37: MPA | B37: Methylprednisolone Acetate | C37: Amneal Bioscien | D37: Amneal | E37: Generic | F37: 2085182.3 | G37: 231614.18 | H37: 125503
A38: MPA | B38: Methylprednisolone Acetate | C38: Amneal-Premier | D38: Amneal | E38: Generic | F38: 115197.14 | G38: 9458.193 | H38: 6503
A39: MPA | B39: Methylprednisolone Acetate | C39: Eugia US LLC | D39: Eugia | E39: Generic | F39: 42261.58 | G39: 11542.53 | H39: 3569
A40: MPA | B40: Methylprednisolone Acetate | C40: Northstar Rx Ll | D40: Other | E40: Generic | F40: 2180.8 | G40: 384.588 | H40: 67
A41: MPA | B41: Methylprednisolone Acetate | C41: Par Pharm. | D41: Endo/Par | E41: Generic | F41: 110485.35 | G41: 68309.632 | H41: 7270
A42: MPA | B42: Methylprednisolone Acetate | C42: Sagent Pharmace | D42: Sagent | E42: Generic | F42: 442217.47 | G42: 59973.859 | H42: 27757
... A58: MPSS | B58: Solu-Medrol* | C58: Pharmacia/Upjhn* | D58: Pfizer | E58: Brand | F58: 0 | G58: 73.25 | H58: 58
A61: Calculations (2024)
A62: Measure | F62: MPSS | G62: HSS | H62: MPA
A63: Part D: brand share of claims | F63: =SUMIFS($H$6:$H$26,$A$6:$A$26,"MPSS",$E$6:$E$26,"Brand")/SUMIFS($H$6:$H$26,$A$6:$A$26,"MPSS") -> 0.46614142 | G63: =SUMIFS($H$6:$H$26,$A$6:$A$26,"HSS",$E$6:$E$26,"Brand")/SUMIFS($H$6:$H$26,$A$6:$A$26,"HSS") -> 0.99280293 | H63: =SUMIFS($H$6:$H$26,$A$6:$A$26,"MPA",$E$6:$E$26,"Brand")/SUMIFS($H$6:$H$26,$A$6:$A$26,"MPA") -> 0.073508123
A64: Part D: Dr. Reddy's share of claims | F64: =SUMIFS($H$6:$H$26,$A$6:$A$26,"MPSS",$D$6:$D$26,"Dr. Reddy's")/SUMIFS($H$6:$H$26,$A$6:$A$26,"MPSS") -> 0.26504102 | G64: =SUMIFS($H$6:$H$26,$A$6:$A$26,"HSS",$D$6:$D$26,"Dr. Reddy's")/SUMIFS($H$6:$H$26,$A$6:$A$26,"HSS") -> 0 | H64: =SUMIFS($H$6:$H$26,$A$6:$A$26,"MPA",$D$6:$D$26,"Dr. Reddy's")/SUMIFS($H$6:$H$26,$A$6:$A$26,"MPA") -> 0
A65: Part D: Fresenius Kabi share of claims | F65: =SUMIFS($H$6:$H$26,$A$6:$A$26,"MPSS",$D$6:$D$26,"Fresenius Kabi")/SUMIFS($H$6:$H$26,$A$6:$A$26,"MPSS") -> 0.2456049 | G65: =SUMIFS($H$6:$H$26,$A$6:$A$26,"HSS",$D$6:$D$26,"Fresenius Kabi")/SUMIFS($H$6:$H$26,$A$6:$A$26,"HSS") -> 0 | H65: =SUMIFS($H$6:$H$26,$A$6:$A$26,"MPA",$D$6:$D$26,"Fresenius Kabi")/SUMIFS($H$6:$H$26,$A$6:$A$26,"MPA") -> 0
A66: Part D: Hikma share of claims | F66: =SUMIFS($H$6:$H$26,$A$6:$A$26,"MPSS",$D$6:$D$26,"Hikma")/SUMIFS($H$6:$H$26,$A$6:$A$26,"MPSS") -> 0.022789426 | G66: =SUMIFS($H$6:$H$26,$A$6:$A$26,"HSS",$D$6:$D$26,"Hikma")/SUMIFS($H$6:$H$26,$A$6:$A$26,"HSS") -> 0 | H66: =SUMIFS($H$6:$H$26,$A$6:$A$26,"MPA",$D$6:$D$26,"Hikma")/SUMIFS($H$6:$H$26,$A$6:$A$26,"MPA") -> 0
A67: Part D: Amneal share of claims | F67: =SUMIFS($H$6:$H$26,$A$6:$A$26,"MPSS",$D$6:$D$26,"Amneal")/SUMIFS($H$6:$H$26,$A$6:$A$26,"MPSS") -> 0.00042323219 | G67: =SUMIFS($H$6:$H$26,$A$6:$A$26,"HSS",$D$6:$D$26,"Amneal")/SUMIFS($H$6:$H$26,$A$6:$A$26,"HSS") -> 0 | H67: =SUMIFS($H$6:$H$26,$A$6:$A$26,"MPA",$D$6:$D$26,"Amneal")/SUMIFS($H$6:$H$26,$A$6:$A$26,"MPA") -> 0.88491234
A68: Part D: brand claims | F68: =SUMIFS($H$6:$H$26,$A$6:$A$26,"MPSS",$E$6:$E$26,"Brand") -> 14318 | G68: =SUMIFS($H$6:$H$26,$A$6:$A$26,"HSS",$E$6:$E$26,"Brand") -> 15174 | H68: =SUMIFS($H$6:$H$26,$A$6:$A$26,"MPA",$E$6:$E$26,"Brand") -> 914
A69: Part D: total claims | F69: =SUMIFS($H$6:$H$26,$A$6:$A$26,"MPSS") -> 30716 | G69: =SUMIFS($H$6:$H$26,$A$6:$A$26,"HSS") -> 15284 | H69: =SUMIFS($H$6:$H$26,$A$6:$A$26,"MPA") -> 12434
A70: Part D: generic spend per dosage unit (US$) | F70: =IFERROR(SUMIFS($F$6:$F$26,$A$6:$A$26,"MPSS",$E$6:$E$26,"Generic")/SUMIFS($G$6:$G$26,$A$6:$A$26,"MPSS",$E$6:$E$26,"Generic"),0) -> 4.6597265 | G70: =IFERROR(SUMIFS($F$6:$F$26,$A$6:$A$26,"HSS",$E$6:$E$26,"Generic")/SUMIFS($G$6:$G$26,$A$6:$A$26,"HSS",$E$6:$E$26,"Generic"),0) -> 13.617887 | H70: =IFERROR(SUMIFS($F$6:$F$26,$A$6:$A$26,"MPA",$E$6:$E$26,"Generic")/SUMIFS($G$6:$G$26,$A$6:$A$26,"MPA",$E$6:$E$26,"Generic"),0) -> 10.743813
A71: Part D: brand spend per dosage unit (US$) | F71: =IFERROR(SUMIFS($F$6:$F$26,$A$6:$A$26,"MPSS",$E$6:$E$26,"Brand")/SUMIFS($G$6:$G$26,$A$6:$A$26,"MPSS",$E$6:$E$26,"Brand"),0) -> 7.39553 | G71: =IFERROR(SUMIFS($F$6:$F$26,$A$6:$A$26,"HSS",$E$6:$E$26,"Brand")/SUMIFS($G$6:$G$26,$A$6:$A$26,"HSS",$E$6:$E$26,"Brand"),0) -> 10.094685 | H71: =IFERROR(SUMIFS($F$6:$F$26,$A$6:$A$26,"MPA",$E$6:$E$26,"Brand")/SUMIFS($G$6:$G$26,$A$6:$A$26,"MPA",$E$6:$E$26,"Brand"),0) -> 14.528913
A72: Part D: generic vs brand spend per unit | F72: =IFERROR(F70/F71-1,0) -> -0.36992662 | G72: =IFERROR(G70/G71-1,0) -> 0.34901551 | H72: =IFERROR(H70/H71-1,0) -> -0.26052188
A73: Part D: total spending (US$) | F73: =SUMIFS($F$6:$F$26,$A$6:$A$26,"MPSS") -> 784577.82 | G73: =SUMIFS($F$6:$F$26,$A$6:$A$26,"HSS") -> 1117972.4 | H73: =SUMIFS($F$6:$F$26,$A$6:$A$26,"MPA") -> 245592.7
A74: Medicaid Spending by Drug: brand US$ | F74: =SUMIFS($F$31:$F$58,$A$31:$A$58,"MPSS",$E$31:$E$58,"Brand") -> 22506080 | G74: =SUMIFS($F$31:$F$58,$A$31:$A$58,"HSS",$E$31:$E$58,"Brand") -> 4085024.9 | H74: =SUMIFS($F$31:$F$58,$A$31:$A$58,"MPA",$E$31:$E$58,"Brand") -> 5740354.9
A75: Medicaid Spending by Drug: generic US$ | F75: =SUMIFS($F$31:$F$58,$A$31:$A$58,"MPSS",$E$31:$E$58,"Generic") -> 8953135.4 | G75: =SUMIFS($F$31:$F$58,$A$31:$A$58,"HSS",$E$31:$E$58,"Generic") -> 14610.12 | H75: =SUMIFS($F$31:$F$58,$A$31:$A$58,"MPA",$E$31:$E$58,"Generic") -> 3121661.2
A76: Medicaid Spending by Drug: brand share of US$ | F76: =F74/(F74+F75) -> 0.715405 | G76: =G74/(G74+G75) -> 0.99643624 | H76: =H74/(H74+H75) -> 0.64774819
A77: Medicaid Spending by Drug: total US$ | F77: =SUMIFS($F$31:$F$58,$A$31:$A$58,"MPSS") -> 31459215 | G77: =SUMIFS($F$31:$F$58,$A$31:$A$58,"HSS") -> 4099635 | H77: =SUMIFS($F$31:$F$58,$A$31:$A$58,"MPA") -> 8862016
A80: Medicare Part B fee-for-service spending by HCPCS (sources S22 for DY2024 release, S23 for earlier releases)
A81: HCPCS | B81: Year | C81: Molecule | D81: Release (data year) | F81: Total spending (US$) | G81: Dosage units | H81: Claims | I81: Avg spend per unit (US$)
A82: J1010 | B82: 2024 | C82: MPA | D82: 2024 | F82: 10310247 | G82: 80220708 | H82: 1297268 | I82: 0.12852352
A83: J1020 | B83: 2016 | C83: MPA | D83: 2020 | F83: 1549673.4 | G83: 346694 | H83: 212079 | I83: 4.47
A84: J1020 | B84: 2017 | C84: MPA | D84: 2021 | F84: 1537166.4 | G84: 305879 | H84: 193233 | I84: 5.03
A85: J1020 | B85: 2018 | C85: MPA | D85: 2022 | F85: 1308786.7 | G85: 279662.1 | H85: 175979 | I85: 4.679886
A86: J1020 | B86: 2019 | C86: MPA | D86: 2023 | F86: 999440.35 | G86: 267025.5 | H86: 163885 | I86: 3.7428648
A87: J1020 | B87: 2020 | C87: MPA | D87: 2023 | F87: 720396.57 | G87: 205254.5 | H87: 129771 | I87: 3.5097724
A88: J1020 | B88: 2021 | C88: MPA | D88: 2023 | F88: 683929.23 | G88: 215296.1 | H88: 139862 | I88: 3.1766912
A89: J1020 | B89: 2022 | C89: MPA | D89: 2023 | F89: 517089.77 | G89: 163381 | H89: 105680 | I89: 3.1649321
A90: J1020 | B90: 2023 | C90: MPA | D90: 2023 | F90: 957975.49 | G90: 169844.5 | H90: 108610 | I90: 5.6403092
A91: J1030 | B91: 2016 | C91: MPA | D91: 2020 | F91: 13194644 | G91: 2843544 | H91: 1970740 | I91: 4.64
A92: J1030 | B92: 2017 | C92: MPA | D92: 2021 | F92: 16228687 | G92: 2844384 | H92: 1969507 | I92: 5.71
A93: J1030 | B93: 2018 | C93: MPA | D93: 2022 | F93: 18181489 | G93: 2754043.4 | H93: 1893658 | I93: 6.6017437
... A132: J2930 | B132: 2023 | C132: MPSS | D132: 2023 | F132: 1469059.3 | G132: 270487.8 | H132: 190838 | I132: 5.4311482
A134: Part B calculations
A135: Measure | F135: Value
A136: J1720 average spend per unit, 2016 | F136: =SUMIFS($I$82:$I$132,$A$82:$A$132,"J1720",$B$82:$B$132,"2016") -> 7.51
A137: J1720 average spend per unit, 2024 | F137: =SUMIFS($I$82:$I$132,$A$82:$A$132,"J1720",$B$82:$B$132,"2024") -> 17.99459
A138: J1720 dosage units, 2016 | F138: =SUMIFS($G$82:$G$132,$A$82:$A$132,"J1720",$B$82:$B$132,"2016") -> 54721
A139: J1720 dosage units, 2018 | F139: =SUMIFS($G$82:$G$132,$A$82:$A$132,"J1720",$B$82:$B$132,"2018") -> 50235.9
A140: J1720 dosage units, 2024 | F140: =SUMIFS($G$82:$G$132,$A$82:$A$132,"J1720",$B$82:$B$132,"2024") -> 26691.5
A141: J1720 average spend per unit, 2018 | F141: =SUMIFS($I$82:$I$132,$A$82:$A$132,"J1720",$B$82:$B$132,"2018") -> 11.832377
A142: J2930 dosage units, 2023 | F142: =SUMIFS($G$82:$G$132,$A$82:$A$132,"J2930",$B$82:$B$132,"2023") -> 270487.8
A143: J2919 dosage units (5 mg), 2024 (Apr-Dec) | F143: =SUMIFS($G$82:$G$132,$A$82:$A$132,"J2919",$B$82:$B$132,"2024") -> 4151843.2
A144: J1010 dosage units (1 mg), 2024 (Apr-Dec) | F144: =SUMIFS($G$82:$G$132,$A$82:$A$132,"J1010",$B$82:$B$132,"2024") -> 80220708
A145: HSS spend 2023 (J1720) | F145: =SUMIFS($F$82:$F$132,$A$82:$A$132,"J1720",$B$82:$B$132,"2023") -> 441126.91
A146: MPSS spend 2023 (J2920 + J2930) | F146: =SUMIFS($F$82:$F$132,$A$82:$A$132,"J2920",$B$82:$B$132,"2023")+SUMIFS($F$82:$F$132,$A$82:$A$132,"J2930",$B$82:$B$132,"2023") -> 1926546.3
A147: Part B FFS: HSS spend / MPSS spend, 2023 | F147: =$F$145/$F$146 -> 0.22897291
A148: Medicaid gross: HSS spend / MPSS spend, 2024 | F148: =G77/F77 -> 0.13031587
A149: Part D: HSS spend / MPSS spend, 2024 | F149: =G73/F73 -> 1.4249351

Sheet Market_Size
A1: Market-size figures, ICICI estimates and Pfizer Medrol revenue
A4: Item | B4: Value | C4: Unit | D4: Source / note
A5: Combined US market, MPSS + HSS (Frost & Sullivan via RHP) | B5: 288 | C5: US$ mn | D5: S24 p.182; also S26
A6: ICICI: US market | B6: 300 | C6: US$ mn | D6: S27: '~US$300 million'
A7: ICICI: Pfizer share quoted | B7: 0.9 | C7: % | D7: S27: '90% market share is currently with innovator Pfizer'
A8: IMS: MPSS US sales, 12m to Oct 2015 (Aurobindo strengths) | B8: 102 | C8: US$ mn | D8: S30
A9: IMS: MPSS US sales, 12m to Jan 2016 | B9: 123.5 | C9: US$ mn | D9: S29
A10: IQVIA: Solu-Medrol brand + generic US sales, MAT Feb 2022 | B10: 144 | C10: US$ mn | D10: S28
A11: IQVIA: MPA 40/80 mg/mL single-dose vials, 12m to Nov 2025 | B11: 57.4 | C11: US$ mn | D11: S31
A12: Global DCV market 2025 (Frost & Sullivan) | B12: 1811 | C12: US$ mn | D12: S24 pp.180-182
A13: Global DCV market CAGR 2025-2030 (Frost & Sullivan) | B13: 0.095 | C13: % | D13: S24
A14: Mhow DCV capacity | B14: 20 | C14: mn vials / yr | D14: S24 (20 million vials per annum)
A15: ICICI complex-injectables revenue FY27E | B15: 100 | C15: INR cr | D15: S27 (milestones)
A16: ICICI complex-injectables revenue FY28E | B16: 176.5 | C16: INR cr | D16: S27
A17: ICICI complex-injectables revenue FY29E | B17: 207.7 | C17: INR cr | D17: S27
A19: Calculations
A20: Measure | B20: Value | C20: Unit | D20: Formula basis
A21: Implied HSS market by subtraction (288 - 144) | B21: =B5-B10 -> 144 | C21: US$ mn | D21: Mixes 2022 IQVIA with a later F&S figure; indicative only
A22: Global DCV market 2030 implied by F&S CAGR | B22: =B12*(1+B13)^5 -> 2850.9464 | C22: US$ mn | D22: 2025 x (1 + CAGR)^5
A23: ICICI FY27E in US$ | B23: =B15*10/Assumptions!$B$9 -> 11.560694 | C23: US$ mn | D23: INR cr x 10 / FX
A24: ICICI FY28E in US$ | B24: =B16*10/Assumptions!$B$9 -> 20.404624 | C24: US$ mn | D24: INR cr x 10 / FX
A25: ICICI FY29E in US$ | B25: =B17*10/Assumptions!$B$9 -> 24.011561 | C25: US$ mn | D25: INR cr x 10 / FX
A26: ICICI FY29E as % of US$288 mn | B26: =B25/B5 -> 0.083373475 | C26: % | D26: FY29E US$ / 288
A27: Part B FFS: HSS / MPSS spend, 2023 | B27: =CMS_Spending!$F$147 -> 0.22897291 | C27: x | D27: Link: CMS_Spending
A28: Medicaid gross: HSS / MPSS spend, 2024 | B28: =CMS_Spending!$F$148 -> 0.13031587 | C28: x | D28: Link: CMS_Spending
A29: Part D: HSS / MPSS spend, 2024 | B29: =CMS_Spending!$F$149 -> 1.4249351 | C29: x | D29: Link: CMS_Spending
A30: Pfizer MPSS share of Medicaid Rx, Q1 2026 (vs ICICI 90%) | B30: =Medicaid_SDUD!$J$18 -> 0.73791431 | C30: % | D30: Link: Medicaid_SDUD
A31: Pfizer MPSS share of Part D claims, 2024 (vs ICICI 90%) | B31: =CMS_Spending!$F$63 -> 0.46614142 | C31: % | D31: Link: CMS_Spending
A32: US MPSS vial-equivalents at Q4'26 ASP per 125 mg vial (rough) | B32: =B10/ASP_growth!$I$7 -> 23.943529 | C32: mn vials | D32: US$144 mn / ASP per 125 mg vial; mixes 2022 sales with 2026 price
A33: Mhow capacity as % of those vial-equivalents (rough) | B33: =B14/B32 -> 0.83529874 | C33: % | D33: 20 mn / vial-equivalents
A36: Pfizer 'Medrol' revenue (scope not stated by Pfizer; likely oral + injectable methylprednisolone)
A37: Year | B37: Worldwide (US$ mn) | C37: US (US$ mn) | D37: Source | E37: US YoY
A38: 2018 | B38: 493 | C38: 266 | D38: S32: Pfizer FY2019 results release (Medrol 2019 and 2018), SEC exhibit 99
A39: 2019 | B39: 469 | C39: 248 | D39: S32: Pfizer FY2019 results release (Medrol 2019 and 2018), SEC exhibit 99 | E39: =C39/C38-1 -> -0.067669173
A40: 2020 | B40: 402 | C40: 198 | D40: S33: Pfizer FY2021 results release (Medrol 2021 and 2020), SEC exhibit 99 | E40: =C40/C39-1 -> -0.2016129
A41: 2021 | B41: 432 | C41: 181 | D41: S33: Pfizer FY2021 results release (Medrol 2021 and 2020), SEC exhibit 99 | E41: =C41/C40-1 -> -0.085858586
A42: 2022 | B42: 328 | C42: 132 | D42: S34: Pfizer FY2023 results release (Medrol 2023 and 2022), SEC exhibit 99 | E42: =C42/C41-1 -> -0.27071823
A43: 2023 | B43: 339 | C43: 132 | D43: S34: Pfizer FY2023 results release (Medrol 2023 and 2022), SEC exhibit 99 | E43: =C43/C42-1 -> 0
A44: US change 2018 to 2023 | C44: =C43/C38-1 -> -0.5037594
A45: Q4 2024 Medrol brand impairment (US$ mn) | B45: 475 | D45: S35: Pfizer 2024 Form 10-K (US$475 mn Medrol impairment)

Sheet Timing
A1: Timing: review clock, exclusivity and elapsed time
A4: Measure | B4: Value | C4: Formula basis
A5: First DCV ANDA filing date (assumed 1st of month) | B5: =Assumptions!$B$11 -> 46266 | C5: Link: Assumptions
A6: Earliest FDA action on 10-month goal | B6: =EDATE(B5,Assumptions!$B$10) -> 46569 | C6: EDATE(filing, review months)
A7: Indian fiscal year of earliest action | B7: ="FY"&TEXT(MOD(IF(MONTH(B6)>=4,YEAR(B6)+1,YEAR(B6)),100),"00") -> FY28 | C7: April-March fiscal year
A8: Second ANDA: earliest action if filed at window start | B8: =EDATE(Assumptions!$B$12,Assumptions!$B$10) -> 46692 | C8: EDATE(window start, review months)
A9: Second ANDA: earliest action if filed at window end | B9: =EDATE(Assumptions!$B$13,Assumptions!$B$10) -> 46783 | C9: EDATE(window end, review months)
A10: Cipla HSS CGT exclusivity end (first marketing + 180 days) | B10: =Assumptions!$B$15+Assumptions!$B$14 -> 45741 | C10: First commercial marketing + 180 days
A11: Months from Cipla HSS approval to report date | B11: =DATEDIF(Assumptions!$B$16,Assumptions!$B$17,"m") -> 25 | C11: DATEDIF in whole months

Sheet Sources
A1: Sources used in this workbook
A2: All links opened and checked on 21 Oct 2026. SEC EDGAR links open in a browser (EDGAR blocks unidentified scripts).
A4: ID | B4: Source | C4: Link
A5: S01 | B5: CMS Medicare Part B ASP pricing files (quarterly payment limits and NDC-HCPCS crosswalks, 2016-2026) | C5: https://www.cms.gov/medicare/payment/part-b-drugs/asp-pricing-files
A6: S02 | B6: CMS October 2026 Part B payment limit file (2Q26 sales) | C6: https://www.cms.gov/files/zip/october-2026-medicare-part-b-payment-limit-files-final.zip
A7: S03 | B7: CMS October 2026 NDC-HCPCS crosswalk (billing units per NDC) | C7: https://www.cms.gov/files/zip/october-2026-ndc-hcpcs-crosswalk-final.zip
A8: S04 | B8: CMS April 2024 ASP file (first quarter of J2919 and J1010) | C8: https://www.cms.gov/files/zip/april-2024-asp-pricing-file.zip
A9: S05 | B9: FDA Orange Book data file (9 Oct 2026) | C9: https://www.fda.gov/media/76860/download
A10: S06 | B10: openFDA NDC directory: methylprednisolone sodium succinate | C10: https://api.fda.gov/drug/ndc.json?search=active_ingredients.name:%22METHYLPREDNISOLONE+SODIUM+SUCCINATE%22&limit=200
A11: S07 | B11: openFDA NDC directory: hydrocortisone sodium succinate | C11: https://api.fda.gov/drug/ndc.json?search=active_ingredients.name:%22HYDROCORTISONE+SODIUM+SUCCINATE%22&limit=100
A12: S08 | B12: FDA Competitive Generic Therapy approvals list | C12: https://www.fda.gov/drugs/generic-drugs/competitive-generic-therapy-approvals
A13: S09 | B13: FDA GDUFA III performance goals letter (10-month standard ANDA goal) | C13: https://www.fda.gov/media/153631/download
A14: S10 | B14: Medicaid State Drug Utilization Data 2018 | C14: https://data.medicaid.gov/dataset/a1f3598e-fc71-51aa-8560-78e7e1a61b09
A15: S11 | B15: Medicaid State Drug Utilization Data 2019 | C15: https://data.medicaid.gov/dataset/daba7980-e219-5996-9bec-90358fd156f1
... A51: S47 | B51: Pfizer Connecticut WAC disclosure, Solu-Medrol, 06 Jul 2026 | C51: https://cdn.pfizer.com/pfizercom/products/ctprescribers/SOLU-MEDROLCTPriceDisclosureShortForm07062026.pdf
